Workbook
Name Debt_Amt3: 'Input Assumptions'!$G$49
Name AUV_Start: 'Input Assumptions'!$D$11
Name Inv_Days: 'Input Assumptions'!$H$9
Name Debt_Rate1: 'Input Assumptions'!$E$51
Name Equity_Cash: 'Input Assumptions'!$E$48
Name Gross_Sales: 'Input Assumptions'!$D$9
Name Pre_Tax_Profit_Target: 'Input Assumptions'!$E$37:$I$37
Name CustAudit_Start: Audit!$F$13
Name BS_Check_II: 'Balance Sheet'!$B$49
Name Growth_Rate: 'Input Assumptions'!$E$21:$I$21
Name Operating_Expenses: 'Input Assumptions'!$E$34:$I$34
Name Acc_Pay_Days_Mat: 'Input Assumptions'!$H$8
Name Direct_Labor_Cost: 'Input Assumptions'!$E$29:$I$29
Name Nav_Valuation: Model!$A$304
Name Nav_Debt: Model!$A$189
Name Debt_Term1: 'Input Assumptions'!$E$50
Name Nav_ROI: Model!$A$282
Name Facilities: 'Input Assumptions'!$E$30:$I$30
Name EBITDA_Multiple: 'Input Assumptions'!$D$13
Name Marketing: 'Input Assumptions'!$E$31:$I$31
Name Workings_BS: Model!$B$90
Name BS_Check: Model!$D$117
Name Fin_Year_End: 'Input Assumptions'!$D$8
Name Audit_SumChk: Audit!$B$9
Name Distributions: 'Input Assumptions'!$E$55:$I$55
Name Payroll_Tax: 'Input Assumptions'!$E$33:$I$33
Name Audit_Start: Audit!$B$13
Name Nav_BS: Model!$A$90
Name Management_Salaries: 'Input Assumptions'!$E$32:$I$32
Name LTGR: Model!$E$306
Name Company_Name: 'Input Assumptions'!$E$4
Name Start_Date: 'Input Assumptions'!$D$7
Name Nav_CF: Model!$A$119
Name Other_Inv_WorkCapital: 'Input Assumptions'!$E$44:$I$44
Name Debt_Amt1: 'Input Assumptions'!$E$49
Name Breakeven: Model!$C$250
Name Royalty_Fee: 'Input Assumptions'!$E$24:$I$24
Name Nav_CT: Model!$A$146
Name Nav_Breakeven: Model!$A$245
Name Fixed_Assets: 'Input Assumptions'!$E$42:$I$42
Name CustAudit_SumChk: Audit!$F$9
Name WACC: Model!$E$305
Name Shareholder_Salary_Adj: 'Input Assumptions'!$E$38:$I$38
Name AUV_Reached: 'Input Assumptions'!$D$10
Name Workings_PL: Model!$B$15
Name Acc_Rec_Days: 'Input Assumptions'!$H$7
Name Debt_Term3: 'Input Assumptions'!$G$50
Name Debt_Rate2: 'Input Assumptions'!$F$51
Name Depreciation_Rate: 'Input Assumptions'!$H$10
Name Other_Inv_Spending: 'Input Assumptions'!$E$43:$I$43
Name Marketing_Fee: 'Input Assumptions'!$E$25:$I$25
Name Corp_Tax_Pay_Lag: 'Input Assumptions'!$H$11
Name Debt_Rate3: 'Input Assumptions'!$G$51
Name Debt_Term2: 'Input Assumptions'!$F$50
Name CT_Sum: Model!$B$85
Name Nav_PL: Model!$A$15
Name Materials_COGs: 'Input Assumptions'!$E$28:$I$28
Name Corp_Tax: 'Input Assumptions'!$D$12
Name Nav_WC: Model!$A$161
Name Debt_Amt2: 'Input Assumptions'!$F$49

Sheet Start Here!
C2: <<<<Click here to watch our introduction video>>>>

Sheet Glossary
B2: Key Terms and Definitions
B4: Term | C4: Definition | D4: Benchmark
B5: Payback period | C5: The payback period is a financial metric used to evaluate the time it takes for an investment to generate an amount of money equal to the original investment cost. In other words, it calculates how long it takes for an investor to recoup the initial outlay. | D5: 4-7 years
B6: EBITDA | C6: A way to look at a business's earnings before considering interest, taxes, depreciation, and amortization. It's like a scorecard that tells you how much money the core operations of a small business made, without getting into the details of certain financial expenses and accounting practices. It helps provide a clearer picture of the business's operational performance. | D6: 10-20% of gross revenues
B7: Adjusted (Adj) Net Profit Before Tax | C7: Net Profit Before Tax is the earnings after depreciation, amortization, and interest payments are deducted. The Net Profit Before Tax is 'adjusted' to account for cases where the owner decides to perform a role in the business for which they receive no salary or under salary. By adjusting the Net Profit Before Tax, you can better understand the 'true' performance of the business. | D7: 10%-15% of gross revenues
B8: Shareholder salary adjustment (+=underpayed) | C8: Sometimes a business owner will decide to perform a job within the business that should pay a certain salary per year, but they go without pay instead in order to preserve capital (sweat equity). This is the same as putting that amount into the business as an investor and hiring someone else to perform the role. It is key that we account for this so that you can understand the ‘true’ investment to calculate your potential returns as well as to calculate the ‘true’ pre-tax net income to understand how the business is actually performing. If the adjustment is positive, that means that the owner/operator was underpaid. | D8: Specific to each investor's individual case
B9: EBITDA Multiple | C9: A number that tells you how much people are willing to pay for a business compared to its EBITDA. This multiple can give a general idea of how valuable the market thinks a business is relative to its earnings. Think of it like a price tag: if the multiple is higher, the market generally sees the business as more valuable for each dollar it earns. | D9: 4x-7x depending on the franchise
B10: Average Unit Volume (AUV) | C10: In the franchise industry, "average unit volume" (AUV) refers to the average sales generated by a single franchise unit over a specified period, usually a year. It provides a measure of the financial performance and potential profitability of individual franchise units. | D10: See Input Assumptions sheet
B11: Operating Expenses - Direct Labor Cost | C11: Total "gross wages" paid to anyone who spends more than 50% of their time working on revenue producing activities. We do not recommend adding payroll taxes and benefits to this number since it clouds the simple decision making that can come from the Direct LER (labor efficiency ratio). | D11: Generally 25-30% of Gross Sales
B12: Operating Expenses - Facilities | C12: Total costs related to rent, utilities, telecommunications, IT costs, and vehicle fleet in the business. | D12: Individual franchise unit specific
B13: Equity - Cash | C13: The outside equity you invest into the business | D13: Assuming financing, typically 25% of total franchise investment cost.
B14: Core Capital | C14: Monthly operating expenses and labor expenses in cash and nothing drawn on a line of credit. | D14: Individual franchise unit specific
B15: Estimated Distributions | C15: Amounts of money taken out of the business by the owners or partners. After the business earns money and pays its bills, the leftover profits can either be kept in the business or distributed to the owners. | D15: Depends on post-tax profitability
... B19: Cash Flow | C19: Refers to the money coming into and going out of the business. | D19: N/A

Sheet Input Assumptions
B1: Assumptions Input
B4: Company Name: | E4: ABC Company
E6: Explanation | K6: Click to Navigate
B7: Start of Business Operations: | C7: Explanation | D7: 45505 | E7: Accounts Receivable Days: | H7: 30 | K7: Summary Financials
B8: Financial Year End: | D8: =EOMONTH(Start_Date,11) -> 45869 | E8: Accounts Payable Days - Materials: | H8: 60 | K8: P&L Statement
B9: Gross Sales/Average Unit Volume (AUV): | C9: Explanation | D9: 526994 | E9: Inventory Days: | H9: 60 | K9: Balance Sheet
B10: Time to Reach AUV (months): | C10: Explanation | D10: 18 | E10: Fixed Assets Depreciation Rate: | H10: 0.25 | K10: Cash Flow Statement
B11: Starting Month AUV % | C11: Explanation | D11: 0.3 | E11: Tax Payment Delay (in months): | H11: 9 | K11: Returns on Invested Capital
B12: Corporation Tax: | C12: Explanation | D12: 0.21 | K12: Valuation
B13: EBITDA Multiple | C13: Explanation | D13: 5 | K13: Model
E17: =IF(MONTH(Fin_Year_End)=12,YEAR(Start_Date)+B$18,YEAR(Start_Date)+B$18&"-"&YEAR(Start_Date)+E$18) -> 2024-2025 | F17: =IF(MONTH(Fin_Year_End)=12,YEAR(Start_Date)+E$18,YEAR(Start_Date)+E$18&"-"&YEAR(Start_Date)+F$18) -> 2025-2026 | G17: =IF(MONTH(Fin_Year_End)=12,YEAR(Start_Date)+F$18,YEAR(Start_Date)+F$18&"-"&YEAR(Start_Date)+G$18) -> 2026-2027 | H17: =IF(MONTH(Fin_Year_End)=12,YEAR(Start_Date)+G$18,YEAR(Start_Date)+G$18&"-"&YEAR(Start_Date)+H$18) -> 2027-2028 | I17: =IF(MONTH(Fin_Year_End)=12,YEAR(Start_Date)+H$18,YEAR(Start_Date)+H$18&"-"&YEAR(Start_Date)+I$18) -> 2028-2029
E18: 1 | F18: =E18+1 -> 2 | G18: =F18+1 -> 3 | H18: =G18+1 -> 4 | I18: =H18+1 -> 5
E19: Year 1 | F19: Year 2 | G19: Year 3 | H19: Year 4 | I19: Year 5
B21: Revenue | C21: Explanation | D21: Annual Growth Rate (% of Revenue) | E21: 0.13 | F21: 0.13 | G21: 0.1 | H21: 0.08 | I21: 0.08
B24: Franchise fees | C24: Explanation | D24: Royalty Fee (% of Revenue) | E24: 0.07 | F24: 0.07 | G24: 0.07 | H24: 0.07 | I24: 0.07
D25: Marketing Fee /Ad Fund (% of Revenue) | E25: 0 | F25: 0 | G25: 0 | H25: 0 | I25: 0
B28: Operating Expenses | C28: Explanation | D28: Materials COGs (% of Revenue) | E28: 0.32 | F28: 0.32 | G28: 0.32 | H28: 0.32 | I28: 0.32
C29: Explanation | D29: Direct Labor Cost (% of Revenue) | E29: 0.15 | F29: 0.15 | G29: 0.15 | H29: 0.15 | I29: 0.15
C30: Explanation | D30: Facilities ($) | E30: 40000 | F30: =E30*1.03 -> 41200 | G30: =F30*1.03 -> 42436 | H30: =G30*1.03 -> 43709.08 | I30: =H30*1.03 -> 45020.352
C31: Explanation | D31: Marketing (% of Revenue) | E31: 0.05 | F31: 0.04 | G31: 0.02 | H31: 0.02 | I31: 0.02
C32: Explanation | D32: Management & Admin Salaries ($) | E32: 0 | F32: ='P&L Statement'!F20/3 -> 78437.593 | G32: ='P&L Statement'!G20/3 -> 91017.433 | H32: ='P&L Statement'!H20/3 -> 99458.128 | I32: ='P&L Statement'!I20/3 -> 107713.1
C33: Explanation | D33: Payroll Taxes & Benefits (% of Direct Labor Cost and Management & Admin Salaries) | E33: 0.2 | F33: 0.2 | G33: 0.2 | H33: 0.2 | I33: 0.2
C34: Explanation | D34: Other Operating Expenses (% of Revenue) | E34: 0.03 | F34: 0.03 | G34: 0.03 | H34: 0.03 | I34: 0.03
B37: P&L Calculations | D37: Target Pre-tax Profit (% of Revenue) | E37: 0.15 | F37: 0.15 | G37: 0.15 | H37: 0.15 | I37: 0.15
C38: Explanation | D38: Shareholder salary adjustment (+=underpayed) | E38: 55000 | F38: 0 | G38: 0 | H38: 0 | I38: 0
B41: Total Investment Spending | C41: Explanation | D41: Total investment required | E41: =+AVERAGE(151350,447150) -> 299250
D42: CapEx investments | E42: =32000+AVERAGE(9650,22000)+22500+2500+AVERAGE(5000,30000)+AVERAGE(50000,125000) -> 177825
D43: Non-CapEx investments | E43: =E41-E42-E44 -> 93675
D44: Working Capital / Additional Funds | E44: =+AVERAGE(18500,37000) -> 27750
D45: Check - total investment required | E45: =E41-SUM(E42:E44) -> 0 | F45: =F41-SUM(F42:F44) -> 0 | G45: =G41-SUM(G42:G44) -> 0 | H45: =H41-SUM(H42:H44) -> 0 | I45: =I41-SUM(I42:I44) -> 0
B48: Financing | C48: Explanation | D48: Equity / Cash Injection | E48: =E41*0.2 -> 59850
D49: Debt | E49: =E41*0.8 -> 239400
D50: Debt Term (Months) | E50: =12*12 -> 144
D51: Debt Interest Rate | E51: 0.105
D52: Check - additional financing above total investment required | E52: =SUM(E48:E49)-E41 -> 0
B55: Distributions | C55: Explanation | D55: Estimated Distributions from the Company | E55: 0 | F55: 0 | G55: 0 | H55: 0 | I55: 0

Sheet Summary Financials
B1: Year | E1: ='Input Assumptions'!E$18 -> 1 | F1: ='Input Assumptions'!F$18 -> 2 | G1: ='Input Assumptions'!G$18 -> 3 | H1: ='Input Assumptions'!H$18 -> 4 | I1: ='Input Assumptions'!I$18 -> 5
E2: =Model!E$13 -> 2024-2025 | F2: =Model!F$13 -> 2025-2026 | G2: =Model!G$13 -> 2026-2027 | H2: =Model!H$13 -> 2027-2028 | I2: =Model!I$13 -> 2028-2029
E3: =Model!E$12 -> Year 1 | F3: =Model!F$12 -> Year 2 | G3: =Model!G$12 -> Year 3 | H3: =Model!H$12 -> Year 4 | I3: =Model!I$12 -> Year 5
B5: Summary Financials | E5: =Curr_USD -> $ USD | F5: =Curr_USD -> $ USD | G5: =Curr_USD -> $ USD | H5: =Curr_USD -> $ USD | I5: =Curr_USD -> $ USD
B7: Ramp up to AUV % then Average Growth Rate | E7: =Model!E$24 -> 0.54953704 | F7: =Model!F$24 -> 0.51638889 | G7: =Model!G$24 -> 0.1 | H7: =Model!H$24 -> 0.08 | I7: =Model!I$24 -> 0.08
B9: Revenue | E9: =Model!E$26 -> 289602.72 | F9: =Model!F$26 -> 511549.52 | G9: =Model!G$26 -> 593591.95 | H9: =Model!H$26 -> 648639.97 | I9: =Model!I$26 -> 702476.76
B11: Cost of Sales | E11: =Model!E$35 -> -92672.871 | F11: =Model!F$35 -> -163695.85 | G11: =Model!G$35 -> -189949.43 | H11: =Model!H$35 -> -207564.79 | I11: =Model!I$35 -> -224792.56
B12: COGS (as % of revenue) | E12: {=INDEX(Materials_COGs,E$1)} -> 0.32 | F12: {=INDEX(Materials_COGs,F$1)} -> 0.32 | G12: {=INDEX(Materials_COGs,G$1)} -> 0.32 | H12: {=INDEX(Materials_COGs,H$1)} -> 0.32 | I12: {=INDEX(Materials_COGs,I$1)} -> 0.32
B14: Gross Profit | E14: =E9+E11 -> 196929.85 | F14: =F9+F11 -> 347853.68 | G14: =G9+G11 -> 403642.53 | H14: =H9+H11 -> 441075.18 | I14: =I9+I11 -> 477684.2
B15: Gross Profit % | E15: =IFERROR(E14/E$9,0) -> 0.68 | F15: =IFERROR(F14/F$9,0) -> 0.68 | G15: =IFERROR(G14/G$9,0) -> 0.68 | H15: =IFERROR(H14/H$9,0) -> 0.68 | I15: =IFERROR(I14/I$9,0) -> 0.68
B17: Direct Labor | E17: =Model!E$42 -> -43440.408 | F17: =Model!F$42 -> -76732.428 | G17: =Model!G$42 -> -89038.793 | H17: =Model!H$42 -> -97295.995 | I17: =Model!I$42 -> -105371.51
B18: Direct Labor (as % of revenue) | E18: {=INDEX(Direct_Labor_Cost,E$1)} -> 0.15 | F18: {=INDEX(Direct_Labor_Cost,F$1)} -> 0.15 | G18: {=INDEX(Direct_Labor_Cost,G$1)} -> 0.15 | H18: {=INDEX(Direct_Labor_Cost,H$1)} -> 0.15 | I18: {=INDEX(Direct_Labor_Cost,I$1)} -> 0.15
B19: Contribution Margin (as % of revenue) | E19: =IFERROR((E14+E17)/E$9,0) -> 0.53 | F19: =IFERROR((F14+F17)/F$9,0) -> 0.53 | G19: =IFERROR((G14+G17)/G$9,0) -> 0.53 | H19: =IFERROR((H14+H17)/H$9,0) -> 0.53 | I19: =IFERROR((I14+I17)/I$9,0) -> 0.53
B21: Total Operating Expenses | E21: =Model!E$67 -> -165531.3 | F21: =Model!F$67 -> -186480.06 | G21: =Model!G$67 -> -199144.28 | H21: =Model!H$67 -> -214950.03 | I21: =Model!I$67 -> -230474.22
B22: Total Operating Expenses (as % of revenue) | E22: =IFERROR(E$21/E$9,0) -> -0.57158061 | F22: =IFERROR(F$21/F$9,0) -> -0.36453961 | G22: =IFERROR(G$21/G$9,0) -> -0.33549019 | H22: =IFERROR(H$21/H$9,0) -> -0.33138573 | I22: =IFERROR(I$21/I$9,0) -> -0.32808803
B24: EBITDA | E24: =Model!E70 -> -32314.048 | F24: =Model!F70 -> 48832.716 | G24: =Model!G70 -> 73908.023 | H24: =Model!H70 -> 83424.353 | I24: =Model!I70 -> 92665.093
B25: EBITDA (as % of revenue) | E25: =Model!E71 -> -0.11158061 | F25: =Model!F71 -> 0.095460388 | G25: =Model!G71 -> 0.12450981 | H25: =Model!H71 -> 0.12861427 | I25: =Model!I71 -> 0.13191197
B27: =Model!B73 -> Depreciation & Amortization | E27: =Model!E73 -> -44456.25 | F27: =Model!F73 -> -44456.25 | G27: =Model!G73 -> -44456.25 | H27: =Model!H73 -> -44456.25 | I27: =Model!I73 -> 0
B28: =Model!B76 -> Interest | E28: =Model!E76 -> -24089.625 | F28: =Model!F76 -> -21994.875 | G28: =Model!G76 -> -19900.125 | H28: =Model!H76 -> -17805.375 | I28: =Model!I76 -> -15710.625
B30: =Model!B78 -> Net Profit Before Tax | C30: Explanation | E30: =Model!E78 -> -100859.92 | F30: =Model!F78 -> -17618.409 | G30: =Model!G78 -> 9551.648 | H30: =Model!H78 -> 21162.728 | I30: =Model!I78 -> 76954.468
B31: =Model!B79 -> Net PBT(as % of revenue) | E31: =Model!E79 -> -0.34826994 | F31: =Model!F79 -> -0.034441258 | G31: =Model!G79 -> 0.016091269 | H31: =Model!H79 -> 0.032626309 | I31: =Model!I79 -> 0.10954735
B33: Adj. Net Profit Before Tax | C33: Explanation | E33: =E30-'Input Assumptions'!E38 -> -155859.92 | F33: =F30-'Input Assumptions'!F38 -> -17618.409 | G33: =G30-'Input Assumptions'!G38 -> 9551.648 | H33: =H30-'Input Assumptions'!H38 -> 21162.728 | I33: =I30-'Input Assumptions'!I38 -> 76954.468
B34: Adj. Net PBT (as % of revenue) | E34: =E33/E9 -> -0.53818528 | F34: =F33/F9 -> -0.034441258 | G34: =G33/G9 -> 0.016091269 | H34: =H33/H9 -> 0.032626309 | I34: =I33/I9 -> 0.10954735
B38: Labor Efficiency | C38: Explanation
B40: Direct LER | E40: ='P&L Statement'!E18 -> 4.0666667 | F40: ='P&L Statement'!F18 -> 4.0666667 | G40: ='P&L Statement'!G18 -> 4.0666667 | H40: ='P&L Statement'!H18 -> 4.0666667 | I40: ='P&L Statement'!I18 -> 4.0666667
B42: Admin LER - Forecasted | E42: ='P&L Statement'!E32 | F42: ='P&L Statement'!F32 -> 3 | G42: ='P&L Statement'!G32 -> 3 | H42: ='P&L Statement'!H32 -> 3 | I42: ='P&L Statement'!I32 -> 3
B43: Admin LER - Benchmark | E43: 2 | F43: 2 | G43: 2 | H43: 2 | I43: 2
B44: Difference | E44: =IFERROR(E42-E43,"") -> -2 | F44: =IFERROR(F42-F43,"") -> 1 | G44: =IFERROR(G42-G43,"") -> 1 | H44: =IFERROR(H42-H43,"") -> 1 | I44: =IFERROR(I42-I43,"") -> 1
B46: Adj Total LER - Actual | E46: ='P&L Statement'!E60 -> 1.7945645 | F46: ='P&L Statement'!F60 -> 2.010989 | G46: ='P&L Statement'!G60 -> 2.010989 | H46: ='P&L Statement'!H60 -> 2.010989 | I46: ='P&L Statement'!I60 -> 2.010989
B47: Adj Total LER - Benchmark | E47: 2 | F47: 2 | G47: 2 | H47: 2 | I47: 2
B48: Difference | E48: =IFERROR(E46-E47,"") -> -0.20543552 | F48: =IFERROR(F46-F47,"") -> 0.010989011 | G48: =IFERROR(G46-G47,"") -> 0.010989011 | H48: =IFERROR(H46-H47,"") -> 0.010989011 | I48: =IFERROR(I46-I47,"") -> 0.010989011
B50: Salary Cap | E50: ='P&L Statement'!E56 -> 61360.952 | F50: ='P&L Statement'!F56 -> 127270.31 | G50: ='P&L Statement'!G56 -> 164925.46 | H50: ='P&L Statement'!H56 -> 182882.48 | I50: ='P&L Statement'!I56 -> 200378.2
B51: (Over)/Under cap Using Adj Total Wages | E51: ='P&L Statement'!E57 -> -37079.456 | F51: ='P&L Statement'!F57 -> -27899.712 | G51: ='P&L Statement'!G57 -> -15130.77 | H51: ='P&L Statement'!H57 -> -13871.642 | I51: ='P&L Statement'!I57 -> -12706.421
B54: Balance Sheet
B56: Assets | E56: =Model!E100 -> 199293.17 | F56: =Model!F100 -> 169887.92 | G56: =Model!G100 -> 162527.95 | H56: =Model!H100 -> 166401.19 | I56: =Model!I100 -> 226287
B57: (of which Cash) | E57: =Model!E92 -> 12088.443 | F57: =Model!F92 -> 6064.8014 | G57: =Model!G92 -> 35316.959 | H57: =Model!H92 -> 76777.854 | I57: =Model!I92 -> 129224.97
B59: Liabilities | E59: =Model!E110 -> 240303.1 | F59: =Model!F110 -> 228516.25 | G59: =Model!G110 -> 211604.63 | H59: =Model!H110 -> 194315.15 | I59: =Model!I110 -> 177246.49
B61: Total Net Assets | E61: =Model!E112 -> -41009.923 | F61: =Model!F112 -> -58628.332 | G61: =Model!G112 -> -49076.683 | H61: =Model!H112 -> -27913.955 | I61: =Model!I112 -> 49040.513
B63: Total Liabilities and Equity | E63: =Model!E116 -> -41009.923 | F63: =Model!F116 -> -58628.332 | G63: =Model!G116 -> -49076.683 | H63: =Model!H116 -> -27913.955 | I63: =Model!I116 -> 49040.513
B64: (of which Retained Earnings) | E64: =Model!E115 -> -100859.92 | F64: =Model!F115 -> -118478.33 | G64: =Model!G115 -> -108926.68 | H64: =Model!H115 -> -87763.955 | I64: =Model!I115 -> -10809.487
B67: Cash Flow
B69: Closing Cash Balance | E69: =Model!E144 -> 12088.443 | F69: =Model!F144 -> 6064.8014 | G69: =Model!G144 -> 35316.959 | H69: =Model!H144 -> 76777.854 | I69: =Model!I144 -> 129224.97
B72: Working Capital
B74: Accounts Receivables Closing | E74: =Model!E166 -> 32582.962 | F74: =Model!F166 -> 45337.891 | G74: =Model!G166 -> 50085.361 | H74: =Model!H166 -> 54242.421 | I74: =Model!I166 -> 58744.515
B76: Accounts Payables Closing | E76: =Model!E180 -> 20853.096 | F76: =Model!F180 -> 29016.25 | G76: =Model!G180 -> 32054.631 | H76: =Model!H180 -> 34715.149 | I76: =Model!I180 -> 37596.49
B78: Inventory Closing | E78: =Model!E185 -> 21253.018 | F78: =Model!F185 -> 29572.726 | G78: =Model!G185 -> 32669.377 | H78: =Model!H185 -> 35380.919 | I78: =Model!I185 -> 38317.518
B81: Debt
B83: Closing Balance | E83: =Model!E194 -> 219450 | F83: =Model!F194 -> 199500 | G83: =Model!G194 -> 179550 | H83: =Model!H194 -> 159600 | I83: =Model!I194 -> 139650
B85: Interest Expense | E85: =Model!E196 -> -24089.625 | F85: =Model!F196 -> -21994.875 | G85: =Model!G196 -> -19900.125 | H85: =Model!H196 -> -17805.375 | I85: =Model!I196 -> -15710.625
B88: Capital Expenditure
B90: Total Expenditure | E90: =Model!E239 -> 177825 | F90: =Model!F239 -> 0 | G90: =Model!G239 -> 0 | H90: =Model!H239 -> 0 | I90: =Model!I239 -> 0
B92: Total Depreciation | E92: =Model!E241 -> -44456.25 | F92: =Model!F241 -> -44456.25 | G92: =Model!G241 -> -44456.25 | H92: =Model!H241 -> -44456.25 | I92: =Model!I241 -> 0
B94: Total Net Book Value | E94: =Model!E243 -> 133368.75 | F94: =Model!F243 -> 88912.5 | G94: =Model!G243 -> 44456.25 | H94: =Model!H243 -> 0 | I94: =Model!I243 -> 0
B97: Breakeven Analysis | C97: Explanation
B100: Breakeven date: | C100: =Model!C249 -> 45961
B102: No. Months to Breakeven: | C102: =Breakeven -> 15
B104: Total Expenses | C104: =Model!C252 -> -94208.193
B106: CapEx | C106: =Model!C253 -> -177825
B108: Total Burn | C108: =Model!C254 -> -272033.19
B113: Payback Period Analysis | D113: Explanation
B116: =Model!B273 -> Pre-Tax Net Income | E116: =Model!E273 -> -100859.92 | F116: =Model!F273 -> -17618.409 | G116: =Model!G273 -> 9551.648 | H116: =Model!H273 -> 21162.728 | I116: =Model!I273 -> 76954.468
B117: =Model!B274 -> Pre-Tax Net Income (with expensing Sweat Equity) | E117: =Model!E274 -> -155859.92 | F117: =Model!F274 -> -17618.409 | G117: =Model!G274 -> 9551.648 | H117: =Model!H274 -> 21162.728 | I117: =Model!I274 -> 76954.468
B118: =Model!B275 -> CAPEX | E118: =Model!E275 -> -177825 | F118: =Model!F275 -> 0 | G118: =Model!G275 -> 0 | H118: =Model!H275 -> 0 | I118: =Model!I275 -> 0
E119: =Model!E276 -> -333684.92 | F119: =Model!F276 -> -17618.409 | G119: =Model!G276 -> 9551.648 | H119: =Model!H276 -> 21162.728 | I119: =Model!I276 -> 76954.468
B121: =Model!B278 -> Cumulative Cash Generated (Spent) (incl with expensing Sweat Equity) | E121: =Model!E278 -> -333684.92 | F121: =Model!F278 -> -351303.33 | G121: =Model!G278 -> -341751.68 | H121: =Model!H278 -> -320588.96 | I121: =Model!I278 -> -243634.49
B123: =Model!B280 -> Breakeven - Payback Year | E123: =Model!E280 | F123: =Model!F280 | G123: =Model!G280 | H123: =Model!H280 | I123: =Model!I280
B126: Returns on Invested Capital
B128: ='Returns on Invested Capital'!B8 -> Total Cash Invested | E128: ='Returns on Invested Capital'!E8 -> 299250 | F128: ='Returns on Invested Capital'!F8 -> 299250 | G128: ='Returns on Invested Capital'!G8 -> 299250 | H128: ='Returns on Invested Capital'!H8 -> 299250 | I128: ='Returns on Invested Capital'!I8 -> 299250
B130: ='Returns on Invested Capital'!B9 -> Total Sweat Equity | E130: ='Returns on Invested Capital'!E9 -> 55000 | F130: ='Returns on Invested Capital'!F9 -> 55000 | G130: ='Returns on Invested Capital'!G9 -> 55000 | H130: ='Returns on Invested Capital'!H9 -> 55000 | I130: ='Returns on Invested Capital'!I9 -> 55000
B131: =Model!B136 -> Debt Drawdown | E131: ='Returns on Invested Capital'!E10 -> -100859.92 | F131: ='Returns on Invested Capital'!F10 -> -118478.33 | G131: ='Returns on Invested Capital'!G10 -> -108926.68 | H131: ='Returns on Invested Capital'!H10 -> -87763.955 | I131: ='Returns on Invested Capital'!I10 -> -10809.487
B133: ='Returns on Invested Capital'!B11 -> Total Invested Capital | E133: ='Returns on Invested Capital'!E11 -> 253390.08 | F133: ='Returns on Invested Capital'!F11 -> 235771.67 | G133: ='Returns on Invested Capital'!G11 -> 245323.32 | H133: ='Returns on Invested Capital'!H11 -> 266486.04 | I133: ='Returns on Invested Capital'!I11 -> 343440.51
B135: ='Returns on Invested Capital'!B17 -> After Tax Net Income | E135: ='Returns on Invested Capital'!E17 -> -79679.339 | F135: ='Returns on Invested Capital'!F17 -> -13918.543 | G135: ='Returns on Invested Capital'!G17 -> 7545.8019 | H135: ='Returns on Invested Capital'!H17 -> 16718.555 | I135: ='Returns on Invested Capital'!I17 -> 60794.03
B137: ='Returns on Invested Capital'!B19 -> ROIC | E137: ='Returns on Invested Capital'!E19 -> -0.61509876 | F137: ='Returns on Invested Capital'!F19 -> -0.074726574 | G137: ='Returns on Invested Capital'!G19 -> 0.038934938 | H137: ='Returns on Invested Capital'!H19 -> 0.07941402 | I137: ='Returns on Invested Capital'!I19 -> 0.22406928
B140: Valuation
B142: =Valuation!B5 -> EBITDA Multiple | C142: =Valuation!E5 -> 5
B143: =Valuation!B15 -> Estimated value | E143: =Valuation!E15 -> -436570.24 | F143: =Valuation!F15 -> 244163.58 | G143: =Valuation!G15 -> 369540.12 | H143: =Valuation!H15 -> 417121.77 | I143: =Valuation!I15 -> 463325.47
B145: =Valuation!B10 -> Adj Net Operating Income | E145: =Valuation!E10 -> -87314.048 | F145: =Valuation!F10 -> 48832.716 | G145: =Valuation!G10 -> 73908.023 | H145: =Valuation!H10 -> 83424.353 | I145: =Valuation!I10 -> 92665.093
B146: =Valuation!B15 -> Estimated value | E146: =Valuation!E15 -> -436570.24 | F146: =Valuation!F15 -> 244163.58 | G146: =Valuation!G15 -> 369540.12 | H146: =Valuation!H15 -> 417121.77 | I146: =Valuation!I15 -> 463325.47
B148: =Valuation!B19 -> Replacement return required | E148: =Valuation!E19 -> 0 | F148: =Valuation!F19 -> 0.25316456 | G148: =Valuation!G19 -> 0.25316456 | H148: =Valuation!H19 -> 0.25316456 | I148: =Valuation!I19 -> 0.25316456

Sheet P&L Statement
B1: =Company_Name -> ABC Company | E1: ='Input Assumptions'!E$18 -> 1 | F1: ='Input Assumptions'!F$18 -> 2 | G1: ='Input Assumptions'!G$18 -> 3 | H1: ='Input Assumptions'!H$18 -> 4 | I1: ='Input Assumptions'!I$18 -> 5 | K1: =IF(K$4<Fin_Year_End,1,IF(MONTH(K$4)=MONTH(Fin_Year_End)+1,MIN(J1+1,5),J1)) -> 1 | L1: =IF(L$4<Fin_Year_End,1,IF(MONTH(L$4)=MONTH(Fin_Year_End)+1,MIN(K1+1,5),K1)) -> 1 | M1: =IF(M$4<Fin_Year_End,1,IF(MONTH(M$4)=MONTH(Fin_Year_End)+1,MIN(L1+1,5),L1)) -> 1 | N1: =IF(N$4<Fin_Year_End,1,IF(MONTH(N$4)=MONTH(Fin_Year_End)+1,MIN(M1+1,5),M1)) -> 1 | O1: =IF(O$4<Fin_Year_End,1,IF(MONTH(O$4)=MONTH(Fin_Year_End)+1,MIN(N1+1,5),N1)) -> 1 | P1: =IF(P$4<Fin_Year_End,1,IF(MONTH(P$4)=MONTH(Fin_Year_End)+1,MIN(O1+1,5),O1)) -> 1 | Q1: =IF(Q$4<Fin_Year_End,1,IF(MONTH(Q$4)=MONTH(Fin_Year_End)+1,MIN(P1+1,5),P1)) -> 1 | R1: =IF(R$4<Fin_Year_End,1,IF(MONTH(R$4)=MONTH(Fin_Year_End)+1,MIN(Q1+1,5),Q1)) -> 1 | ... BR1: =IF(BR$4<Fin_Year_End,1,IF(MONTH(BR$4)=MONTH(Fin_Year_End)+1,MIN(BQ1+1,5),BQ1)) -> 5
B2: Profit & Loss
E3: ='Input Assumptions'!E$17 -> 2024-2025 | F3: ='Input Assumptions'!F$17 -> 2025-2026 | G3: ='Input Assumptions'!G$17 -> 2026-2027 | H3: ='Input Assumptions'!H$17 -> 2027-2028 | I3: ='Input Assumptions'!I$17 -> 2028-2029
E4: =Model!E$12 -> Year 1 | F4: =Model!F$12 -> Year 2 | G4: =Model!G$12 -> Year 3 | H4: =Model!H$12 -> Year 4 | I4: =Model!I$12 -> Year 5 | K4: =EOMONTH(Start_Date,-1)+1 -> 45505 | L4: =EOMONTH(K4,0)+1 -> 45536 | M4: =EOMONTH(L4,0)+1 -> 45566 | N4: =EOMONTH(M4,0)+1 -> 45597 | O4: =EOMONTH(N4,0)+1 -> 45627 | P4: =EOMONTH(O4,0)+1 -> 45658 | Q4: =EOMONTH(P4,0)+1 -> 45689 | R4: =EOMONTH(Q4,0)+1 -> 45717 | S4: =EOMONTH(R4,0)+1 -> 45748 | ... BR4: =EOMONTH(BQ4,0)+1 -> 47300
B5: Revenue Growth | E5: ='Input Assumptions'!E$21 -> 0.13 | F5: ='Input Assumptions'!F$21 -> 0.13 | G5: ='Input Assumptions'!G$21 -> 0.1 | H5: ='Input Assumptions'!H$21 -> 0.08 | I5: ='Input Assumptions'!I$21 -> 0.08
B6: Revenue | E6: =SUMIFS($K6:$BR6,$K$1:$BR$1,E$1) -> 289602.72 | F6: =SUMIFS($K6:$BR6,$K$1:$BR$1,F$1) -> 511549.52 | G6: =SUMIFS($K6:$BR6,$K$1:$BR$1,G$1) -> 593591.95 | H6: =SUMIFS($K6:$BR6,$K$1:$BR$1,H$1) -> 648639.97 | I6: =SUMIFS($K6:$BR6,$K$1:$BR$1,I$1) -> 702476.76 | K6: =Model!K$26 -> 13174.85 | L6: =Model!L$26 -> 16590.552 | M6: =Model!M$26 -> 18298.403 | N6: =Model!N$26 -> 20006.254 | O6: =Model!O$26 -> 21714.105 | P6: =Model!P$26 -> 23421.956 | Q6: =Model!Q$26 -> 25129.806 | R6: =Model!R$26 -> 26837.657 | ... BR6: =Model!BR$26 -> 60702.666
B8: Cost of Goods Sold:
B9: Materials | E9: =SUMIFS($K9:$BR9,$K$1:$BR$1,E$1) -> 92672.871 | F9: =SUMIFS($K9:$BR9,$K$1:$BR$1,F$1) -> 163695.85 | G9: =SUMIFS($K9:$BR9,$K$1:$BR$1,G$1) -> 189949.43 | H9: =SUMIFS($K9:$BR9,$K$1:$BR$1,H$1) -> 207564.79 | I9: =SUMIFS($K9:$BR9,$K$1:$BR$1,I$1) -> 224792.56 | K9: =-Model!K35 -> 4215.952 | L9: =-Model!L35 -> 5308.9766 | M9: =-Model!M35 -> 5855.4889 | N9: =-Model!N35 -> 6402.0012 | O9: =-Model!O35 -> 6948.5135 | P9: =-Model!P35 -> 7495.0258 | Q9: =-Model!Q35 -> 8041.5381 | R9: =-Model!R35 -> 8588.0504 | ... BR9: =-Model!BR35 -> 19424.853
B10: Royalties | E10: =SUMIFS($K10:$BR10,$K$1:$BR$1,E$1) -> 20272.19 | F10: =SUMIFS($K10:$BR10,$K$1:$BR$1,F$1) -> 35808.467 | G10: =SUMIFS($K10:$BR10,$K$1:$BR$1,G$1) -> 41551.437 | H10: =SUMIFS($K10:$BR10,$K$1:$BR$1,H$1) -> 45404.798 | I10: =SUMIFS($K10:$BR10,$K$1:$BR$1,I$1) -> 49173.373 | K10: =-Model!K29 -> 922.2395 | L10: =-Model!L29 -> 1161.3386 | M10: =-Model!M29 -> 1280.8882 | N10: =-Model!N29 -> 1400.4378 | O10: =-Model!O29 -> 1519.9873 | P10: =-Model!P29 -> 1639.5369 | Q10: =-Model!Q29 -> 1759.0865 | R10: =-Model!R29 -> 1878.636 | ... BR10: =-Model!BR29 -> 4249.1866
B11: Ad Fund / Brand Fund | E11: =SUMIFS($K11:$BR11,$K$1:$BR$1,E$1) -> 0 | F11: =SUMIFS($K11:$BR11,$K$1:$BR$1,F$1) -> 0 | G11: =SUMIFS($K11:$BR11,$K$1:$BR$1,G$1) -> 0 | H11: =SUMIFS($K11:$BR11,$K$1:$BR$1,H$1) -> 0 | I11: =SUMIFS($K11:$BR11,$K$1:$BR$1,I$1) -> 0 | K11: =-Model!K32 -> 0 | L11: =-Model!L32 -> 0 | M11: =-Model!M32 -> 0 | N11: =-Model!N32 -> 0 | O11: =-Model!O32 -> 0 | P11: =-Model!P32 -> 0 | Q11: =-Model!Q32 -> 0 | R11: =-Model!R32 -> 0 | ... BR11: =-Model!BR32 -> 0
B12: Total Cost of Goods Sold | E12: =SUM(E9:E11) -> 112945.06 | F12: =SUM(F9:F11) -> 199504.31 | G12: =SUM(G9:G11) -> 231500.86 | H12: =SUM(H9:H11) -> 252969.59 | I12: =SUM(I9:I11) -> 273965.94 | K12: =SUM(K9:K11) -> 5138.1915 | L12: =SUM(L9:L11) -> 6470.3152 | M12: =SUM(M9:M11) -> 7136.3771 | N12: =SUM(N9:N11) -> 7802.4389 | O12: =SUM(O9:O11) -> 8468.5008 | P12: =SUM(P9:P11) -> 9134.5627 | Q12: =SUM(Q9:Q11) -> 9800.6245 | R12: =SUM(R9:R11) -> 10466.686 | ... BR12: =SUM(BR9:BR11) -> 23674.04
B14: Gross Profit | E14: =+E6-E12 -> 176657.66 | F14: =+F6-F12 -> 312045.21 | G14: =+G6-G12 -> 362091.09 | H14: =+H6-H12 -> 395670.38 | I14: =+I6-I12 -> 428510.83 | K14: =+K6-K12 -> 8036.6585 | L14: =+L6-L12 -> 10120.237 | M14: =+M6-M12 -> 11162.026 | N14: =+N6-N12 -> 12203.815 | O14: =+O6-O12 -> 13245.604 | P14: =+P6-P12 -> 14287.393 | Q14: =+Q6-Q12 -> 15329.182 | R14: =+R6-R12 -> 16370.971 | ... BR14: =+BR6-BR12 -> 37028.626
B15: Gross Profit as % of Revenue | E15: =IFERROR(E14/E6,0) -> 0.61 | F15: =IFERROR(F14/F6,0) -> 0.61 | G15: =IFERROR(G14/G6,0) -> 0.61 | H15: =IFERROR(H14/H6,0) -> 0.61 | I15: =IFERROR(I14/I6,0) -> 0.61 | K15: =IFERROR(K14/K6,0) -> 0.61 | L15: =IFERROR(L14/L6,0) -> 0.61 | M15: =IFERROR(M14/M6,0) -> 0.61 | N15: =IFERROR(N14/N6,0) -> 0.61 | O15: =IFERROR(O14/O6,0) -> 0.61 | P15: =IFERROR(P14/P6,0) -> 0.61 | Q15: =IFERROR(Q14/Q6,0) -> 0.61 | R15: =IFERROR(R14/R6,0) -> 0.61 | ... BR15: =IFERROR(BR14/BR6,0) -> 0.61
B17: Direct Labor | E17: =SUMIFS($K17:$BR17,$K$1:$BR$1,E$1) -> 43440.408 | F17: =SUMIFS($K17:$BR17,$K$1:$BR$1,F$1) -> 76732.428 | G17: =SUMIFS($K17:$BR17,$K$1:$BR$1,G$1) -> 89038.793 | H17: =SUMIFS($K17:$BR17,$K$1:$BR$1,H$1) -> 97295.995 | I17: =SUMIFS($K17:$BR17,$K$1:$BR$1,I$1) -> 105371.51 | K17: =-Model!K42 -> 1976.2275 | L17: =-Model!L42 -> 2488.5828 | M17: =-Model!M42 -> 2744.7604 | N17: =-Model!N42 -> 3000.9381 | O17: =-Model!O42 -> 3257.1157 | P17: =-Model!P42 -> 3513.2933 | Q17: =-Model!Q42 -> 3769.471 | R17: =-Model!R42 -> 4025.6486 | ... BR17: =-Model!BR42 -> 9105.3998
B18: Direct LER | E18: =IFERROR(E14/E17,"") -> 4.0666667 | F18: =IFERROR(F14/F17,"") -> 4.0666667 | G18: =IFERROR(G14/G17,"") -> 4.0666667 | H18: =IFERROR(H14/H17,"") -> 4.0666667 | I18: =IFERROR(I14/I17,"") -> 4.0666667 | K18: =IFERROR(K14/K17,"") -> 4.0666667 | L18: =IFERROR(L14/L17,"") -> 4.0666667 | M18: =IFERROR(M14/M17,"") -> 4.0666667 | N18: =IFERROR(N14/N17,"") -> 4.0666667 | O18: =IFERROR(O14/O17,"") -> 4.0666667 | P18: =IFERROR(P14/P17,"") -> 4.0666667 | Q18: =IFERROR(Q14/Q17,"") -> 4.0666667 | R18: =IFERROR(R14/R17,"") -> 4.0666667 | ... BR18: =IFERROR(BR14/BR17,"") -> 4.0666667
B20: Contribution Margin | E20: =E14-E17 -> 133217.25 | F20: =F14-F17 -> 235312.78 | G20: =G14-G17 -> 273052.3 | H20: =H14-H17 -> 298374.38 | I20: =I14-I17 -> 323139.31 | K20: =K14-K17 -> 6060.431 | L20: =L14-L17 -> 7631.6539 | M20: =M14-M17 -> 8417.2653 | N20: =N14-N17 -> 9202.8767 | O20: =O14-O17 -> 9988.4881 | P20: =P14-P17 -> 10774.1 | Q20: =Q14-Q17 -> 11559.711 | R20: =R14-R17 -> 12345.322 | ... BR20: =BR14-BR17 -> 27923.226
B21: As % of GP | E21: =IFERROR(E20/E14,"") -> 0.75409836 | F21: =IFERROR(F20/F14,"") -> 0.75409836 | G21: =IFERROR(G20/G14,"") -> 0.75409836 | H21: =IFERROR(H20/H14,"") -> 0.75409836 | I21: =IFERROR(I20/I14,"") -> 0.75409836 | K21: =IFERROR(K20/K14,"") -> 0.75409836 | L21: =IFERROR(L20/L14,"") -> 0.75409836 | M21: =IFERROR(M20/M14,"") -> 0.75409836 | N21: =IFERROR(N20/N14,"") -> 0.75409836 | O21: =IFERROR(O20/O14,"") -> 0.75409836 | P21: =IFERROR(P20/P14,"") -> 0.75409836 | Q21: =IFERROR(Q20/Q14,"") -> 0.75409836 | R21: =IFERROR(R20/R14,"") -> 0.75409836 | ... BR21: =IFERROR(BR20/BR14,"") -> 0.75409836
B23: Operating Expenses:
B24: Facilities | E24: =SUMIFS($K24:$BR24,$K$1:$BR$1,E$1) -> 40000 | F24: =SUMIFS($K24:$BR24,$K$1:$BR$1,F$1) -> 41200 | G24: =SUMIFS($K24:$BR24,$K$1:$BR$1,G$1) -> 42436 | H24: =SUMIFS($K24:$BR24,$K$1:$BR$1,H$1) -> 43709.08 | I24: =SUMIFS($K24:$BR24,$K$1:$BR$1,I$1) -> 45020.352 | K24: =-Model!K54 -> 3333.3333 | L24: =-Model!L54 -> 3333.3333 | M24: =-Model!M54 -> 3333.3333 | N24: =-Model!N54 -> 3333.3333 | O24: =-Model!O54 -> 3333.3333 | P24: =-Model!P54 -> 3333.3333 | Q24: =-Model!Q54 -> 3333.3333 | R24: =-Model!R54 -> 3333.3333 | ... BR24: =-Model!BR54 -> 3751.696
B25: Marketing | E25: =SUMIFS($K25:$BR25,$K$1:$BR$1,E$1) -> 14480.136 | F25: =SUMIFS($K25:$BR25,$K$1:$BR$1,F$1) -> 20461.981 | G25: =SUMIFS($K25:$BR25,$K$1:$BR$1,G$1) -> 11871.839 | H25: =SUMIFS($K25:$BR25,$K$1:$BR$1,H$1) -> 12972.799 | I25: =SUMIFS($K25:$BR25,$K$1:$BR$1,I$1) -> 14049.535 | K25: =-Model!K58 -> 658.7425 | L25: =-Model!L58 -> 829.52759 | M25: =-Model!M58 -> 914.92014 | N25: =-Model!N58 -> 1000.3127 | O25: =-Model!O58 -> 1085.7052 | P25: =-Model!P58 -> 1171.0978 | Q25: =-Model!Q58 -> 1256.4903 | R25: =-Model!R58 -> 1341.8829 | ... BR25: =-Model!BR58 -> 1214.0533
B26: Labor - (Management and Admin) | E26: =SUMIFS($K26:$BR26,$K$1:$BR$1,E$1) -> 0 | F26: =SUMIFS($K26:$BR26,$K$1:$BR$1,F$1) -> 78437.593 | G26: =SUMIFS($K26:$BR26,$K$1:$BR$1,G$1) -> 91017.433 | H26: =SUMIFS($K26:$BR26,$K$1:$BR$1,H$1) -> 99458.128 | I26: =SUMIFS($K26:$BR26,$K$1:$BR$1,I$1) -> 107713.1 | K26: =-Model!K48 -> 0 | L26: =-Model!L48 -> 0 | M26: =-Model!M48 -> 0 | N26: =-Model!N48 -> 0 | O26: =-Model!O48 -> 0 | P26: =-Model!P48 -> 0 | Q26: =-Model!Q48 -> 0 | R26: =-Model!R48 -> 0 | ... BR26: =-Model!BR48 -> 8976.092
B27: Payroll Taxes & Benefits | E27: =SUMIFS($K27:$BR27,$K$1:$BR$1,E$1) -> 8688.0816 | F27: =SUMIFS($K27:$BR27,$K$1:$BR$1,F$1) -> 31034.004 | G27: =SUMIFS($K27:$BR27,$K$1:$BR$1,G$1) -> 36011.245 | H27: =SUMIFS($K27:$BR27,$K$1:$BR$1,H$1) -> 39350.825 | I27: =SUMIFS($K27:$BR27,$K$1:$BR$1,I$1) -> 42616.924 | K27: =-Model!K50 -> 395.2455 | L27: =-Model!L50 -> 497.71656 | M27: =-Model!M50 -> 548.95208 | N27: =-Model!N50 -> 600.18761 | O27: =-Model!O50 -> 651.42314 | P27: =-Model!P50 -> 702.65867 | Q27: =-Model!Q50 -> 753.89419 | R27: =-Model!R50 -> 805.12972 | ... BR27: =-Model!BR50 -> 3616.2984
B28: Other Operating Expenses | E28: =SUMIFS($K28:$BR28,$K$1:$BR$1,E$1) -> 8688.0816 | F28: =SUMIFS($K28:$BR28,$K$1:$BR$1,F$1) -> 15346.486 | G28: =SUMIFS($K28:$BR28,$K$1:$BR$1,G$1) -> 17807.759 | H28: =SUMIFS($K28:$BR28,$K$1:$BR$1,H$1) -> 19459.199 | I28: =SUMIFS($K28:$BR28,$K$1:$BR$1,I$1) -> 21074.303 | K28: =-Model!K62 -> 395.2455 | L28: =-Model!L62 -> 497.71656 | M28: =-Model!M62 -> 548.95208 | N28: =-Model!N62 -> 600.18761 | O28: =-Model!O62 -> 651.42314 | P28: =-Model!P62 -> 702.65867 | Q28: =-Model!Q62 -> 753.89419 | R28: =-Model!R62 -> 805.12972 | ... BR28: =-Model!BR62 -> 1821.08
B29: ='Input Assumptions'!D43 -> Non-CapEx investments | E29: =SUMIFS($K29:$BR29,$K$1:$BR$1,E$1) -> 93675 | F29: =SUMIFS($K29:$BR29,$K$1:$BR$1,F$1) -> 0 | G29: =SUMIFS($K29:$BR29,$K$1:$BR$1,G$1) -> 0 | H29: =SUMIFS($K29:$BR29,$K$1:$BR$1,H$1) -> 0 | I29: =SUMIFS($K29:$BR29,$K$1:$BR$1,I$1) -> 0 | K29: =-Model!K64 -> 7806.25 | L29: =-Model!L64 -> 7806.25 | M29: =-Model!M64 -> 7806.25 | N29: =-Model!N64 -> 7806.25 | O29: =-Model!O64 -> 7806.25 | P29: =-Model!P64 -> 7806.25 | Q29: =-Model!Q64 -> 7806.25 | R29: =-Model!R64 -> 7806.25 | ... BR29: =-Model!BR64 -> 0
B30: Total operating expenses | E30: =SUM(E24:E29) -> 165531.3 | F30: =SUM(F24:F29) -> 186480.06 | G30: =SUM(G24:G29) -> 199144.28 | H30: =SUM(H24:H29) -> 214950.03 | I30: =SUM(I24:I29) -> 230474.22 | K30: =SUM(K24:K29) -> 12588.817 | L30: =SUM(L24:L29) -> 12964.544 | M30: =SUM(M24:M29) -> 13152.408 | N30: =SUM(N24:N29) -> 13340.271 | O30: =SUM(O24:O29) -> 13528.135 | P30: =SUM(P24:P29) -> 13715.998 | Q30: =SUM(Q24:Q29) -> 13903.862 | R30: =SUM(R24:R29) -> 14091.726 | ... BR30: =SUM(BR24:BR29) -> 19379.22
B31: As % of Revenue | E31: =IFERROR(E30/E6,"") -> 0.57158061 | F31: =IFERROR(F30/F6,"") -> 0.36453961 | G31: =IFERROR(G30/G6,"") -> 0.33549019 | H31: =IFERROR(H30/H6,"") -> 0.33138573 | I31: =IFERROR(I30/I6,"") -> 0.32808803 | K31: =IFERROR(K30/K6,"") -> 0.9555188 | L31: =IFERROR(L30/L6,"") -> 0.7814414 | M31: =IFERROR(M30/M6,"") -> 0.71877353 | N31: =IFERROR(N30/N6,"") -> 0.66680506 | O31: =IFERROR(O30/O6,"") -> 0.62301141 | P31: =IFERROR(P30/P6,"") -> 0.58560432 | Q31: =IFERROR(Q30/Q6,"") -> 0.5532817 | R31: =IFERROR(R30/R6,"") -> 0.52507286 | ... BR31: =IFERROR(BR30/BR6,"") -> 0.31924825
B32: Management LER to CM | E32: =IFERROR(E20/E26,"") | F32: =IFERROR(F20/F26,"") -> 3 | G32: =IFERROR(G20/G26,"") -> 3 | H32: =IFERROR(H20/H26,"") -> 3 | I32: =IFERROR(I20/I26,"") -> 3 | K32: =IFERROR(K20/K26,"") | L32: =IFERROR(L20/L26,"") | M32: =IFERROR(M20/M26,"") | N32: =IFERROR(N20/N26,"") | O32: =IFERROR(O20/O26,"") | P32: =IFERROR(P20/P26,"") | Q32: =IFERROR(Q20/Q26,"") | R32: =IFERROR(R20/R26,"") | ... BR32: =IFERROR(BR20/BR26,"") -> 3.1108445
E33: =E34-Model!E70 -> 0 | F33: =F34-Model!F70 -> 1.0186341e-10 | G33: =G34-Model!G70 -> 0 | H33: =H34-Model!H70 -> 0 | I33: =I34-Model!I70 -> 0
B34: Net operating Income | E34: =E20-E30 -> -32314.048 | F34: =F20-F30 -> 48832.716 | G34: =G20-G30 -> 73908.023 | H34: =H20-H30 -> 83424.353 | I34: =I20-I30 -> 92665.093 | K34: =K20-K30 -> -6528.3858 | L34: =L20-L30 -> -5332.8902 | M34: =M20-M30 -> -4735.1424 | N34: =N20-N30 -> -4137.3945 | O34: =O20-O30 -> -3539.6467 | P34: =P20-P30 -> -2941.8989 | Q34: =Q20-Q30 -> -2344.1511 | R34: =R20-R30 -> -1746.4032 | ... BR34: =BR20-BR30 -> 8544.0065
B35: As % of Revenue | E35: =IFERROR(E34/E6,"") -> -0.11158061 | F35: =IFERROR(F34/F6,"") -> 0.095460388 | G35: =IFERROR(G34/G6,"") -> 0.12450981 | H35: =IFERROR(H34/H6,"") -> 0.12861427 | I35: =IFERROR(I34/I6,"") -> 0.13191197 | K35: =IFERROR(K34/K6,"") -> -0.4955188 | L35: =IFERROR(L34/L6,"") -> -0.3214414 | M35: =IFERROR(M34/M6,"") -> -0.25877353 | N35: =IFERROR(N34/N6,"") -> -0.20680506 | O35: =IFERROR(O34/O6,"") -> -0.16301141 | P35: =IFERROR(P34/P6,"") -> -0.12560432 | Q35: =IFERROR(Q34/Q6,"") -> -0.0932817 | R35: =IFERROR(R34/R6,"") -> -0.065072864 | ... BR35: =IFERROR(BR34/BR6,"") -> 0.14075175
B37: Depreciation | E37: =SUMIFS($K37:$BR37,$K$1:$BR$1,E$1) -> -44456.25 | F37: =SUMIFS($K37:$BR37,$K$1:$BR$1,F$1) -> -44456.25 | G37: =SUMIFS($K37:$BR37,$K$1:$BR$1,G$1) -> -44456.25 | H37: =SUMIFS($K37:$BR37,$K$1:$BR$1,H$1) -> -44456.25 | I37: =SUMIFS($K37:$BR37,$K$1:$BR$1,I$1) -> 0 | K37: =Model!K73 -> -3704.6875 | L37: =Model!L73 -> -3704.6875 | M37: =Model!M73 -> -3704.6875 | N37: =Model!N73 -> -3704.6875 | O37: =Model!O73 -> -3704.6875 | P37: =Model!P73 -> -3704.6875 | Q37: =Model!Q73 -> -3704.6875 | R37: =Model!R73 -> -3704.6875 | ... BR37: =Model!BR73 -> 0
B38: Other Income (Expense)
B39: Interest Expense | E39: =SUMIFS($K39:$BR39,$K$1:$BR$1,E$1) -> -24089.625 | F39: =SUMIFS($K39:$BR39,$K$1:$BR$1,F$1) -> -21994.875 | G39: =SUMIFS($K39:$BR39,$K$1:$BR$1,G$1) -> -19900.125 | H39: =SUMIFS($K39:$BR39,$K$1:$BR$1,H$1) -> -17805.375 | I39: =SUMIFS($K39:$BR39,$K$1:$BR$1,I$1) -> -15710.625 | K39: =Model!K76 -> -2087.4766 | L39: =Model!L76 -> -2072.9297 | M39: =Model!M76 -> -2058.3828 | N39: =Model!N76 -> -2043.8359 | O39: =Model!O76 -> -2029.2891 | P39: =Model!P76 -> -2014.7422 | Q39: =Model!Q76 -> -2000.1953 | R39: =Model!R76 -> -1985.6484 | ... BR39: =Model!BR76 -> -1229.2109
B41: Pre-tax Net Income | E41: =E34+E37+E38+E39 -> -100859.92 | F41: =F34+F37+F38+F39 -> -17618.409 | G41: =G34+G37+G38+G39 -> 9551.648 | H41: =H34+H37+H38+H39 -> 21162.728 | I41: =I34+I37+I38+I39 -> 76954.468 | K41: =K34+K37+K38+K39 -> -12320.55 | L41: =L34+L37+L38+L39 -> -11110.507 | M41: =M34+M37+M38+M39 -> -10498.213 | N41: =N34+N37+N38+N39 -> -9885.918 | O41: =O34+O37+O38+O39 -> -9273.6233 | P41: =P34+P37+P38+P39 -> -8661.3286 | Q41: =Q34+Q37+Q38+Q39 -> -8049.0339 | R41: =R34+R37+R38+R39 -> -7436.7392 | ... BR41: =BR34+BR37+BR38+BR39 -> 7314.7956
B42: as a % of Revenue | E42: =E41/E6 -> -0.34826994 | F42: =F41/F6 -> -0.034441258 | G42: =G41/G6 -> 0.016091269 | H42: =H41/H6 -> 0.032626309 | I42: =I41/I6 -> 0.10954735 | K42: =K41/K6 -> -0.93515675 | L42: =L41/L6 -> -0.66968884 | M42: =M41/M6 -> -0.5737229 | N42: =N41/N6 -> -0.49414139 | O42: =O41/O6 -> -0.42707832 | P42: =P41/P6 -> -0.36979528 | Q42: =Q41/Q6 -> -0.32029828 | R42: =R41/R6 -> -0.27710091 | ... BR42: =BR41/BR6 -> 0.12050205
B43: as a % of Gross Profit | E43: =E41/E14 -> -0.57093433 | F43: =F41/F14 -> -0.056461078 | G43: =G41/G14 -> 0.02637913 | H43: =H41/H14 -> 0.053485753 | I43: =I41/I14 -> 0.17958582 | K43: =K41/K14 -> -1.5330439 | L43: =L41/L14 -> -1.0978506 | M43: =M41/M14 -> -0.94052934 | N43: =N41/N14 -> -0.81006785 | O43: =O41/O14 -> -0.70012839 | P43: =P41/P14 -> -0.60622177 | Q43: =Q41/Q14 -> -0.52507915 | R43: =R41/R14 -> -0.45426378 | ... BR43: =BR41/BR14 -> 0.19754434
B45: Target Pre-tax Profit % | E45: =INDEX($K45:$BR45,,MATCH(E$1,$K$1:$BR$1,0)) -> 0.15 | F45: =INDEX($K45:$BR45,,MATCH(F$1,$K$1:$BR$1,0)) -> 0.15 | G45: =INDEX($K45:$BR45,,MATCH(G$1,$K$1:$BR$1,0)) -> 0.15 | H45: =INDEX($K45:$BR45,,MATCH(H$1,$K$1:$BR$1,0)) -> 0.15 | I45: =INDEX($K45:$BR45,,MATCH(I$1,$K$1:$BR$1,0)) -> 0.15 | K45: {=INDEX(Pre_Tax_Profit_Target,K$1)} -> 0.15 | L45: {=INDEX(Pre_Tax_Profit_Target,L$1)} -> 0.15 | M45: {=INDEX(Pre_Tax_Profit_Target,M$1)} -> 0.15 | N45: {=INDEX(Pre_Tax_Profit_Target,N$1)} -> 0.15 | O45: {=INDEX(Pre_Tax_Profit_Target,O$1)} -> 0.15 | P45: {=INDEX(Pre_Tax_Profit_Target,P$1)} -> 0.15 | Q45: {=INDEX(Pre_Tax_Profit_Target,Q$1)} -> 0.15 | R45: {=INDEX(Pre_Tax_Profit_Target,R$1)} -> 0.15 | ... BR45: {=INDEX(Pre_Tax_Profit_Target,BR$1)} -> 0.15
B46: Calculated Pre-tax Profit @15% | E46: =E45*E6 -> 43440.408 | F46: =F45*F6 -> 76732.428 | G46: =G45*G6 -> 89038.793 | H46: =H45*H6 -> 97295.995 | I46: =I45*I6 -> 105371.51 | K46: =K45*K6 -> 1976.2275 | L46: =L45*L6 -> 2488.5828 | M46: =M45*M6 -> 2744.7604 | N46: =N45*N6 -> 3000.9381 | O46: =O45*O6 -> 3257.1157 | P46: =P45*P6 -> 3513.2933 | Q46: =Q45*Q6 -> 3769.471 | R46: =R45*R6 -> 4025.6486 | ... BR46: =BR45*BR6 -> 9105.3998
B47: Above (below) Target | E47: =E41-E46 -> -144300.33 | F47: =F41-F46 -> -94350.837 | G47: =G41-G46 -> -79487.145 | H47: =H41-H46 -> -76133.267 | I47: =I41-I46 -> -28417.046 | K47: =K41-K46 -> -14296.777 | L47: =L41-L46 -> -13599.09 | M47: =M41-M46 -> -13242.973 | N47: =N41-N46 -> -12886.856 | O47: =O41-O46 -> -12530.739 | P47: =P41-P46 -> -12174.622 | Q47: =Q41-Q46 -> -11818.505 | R47: =R41-R46 -> -11462.388 | ... BR47: =BR41-BR46 -> -1790.6042
B49: Shareholder salary adjustment (+=underpayed) | E49: =SUMIFS($K49:$BR49,$K$1:$BR$1,E$1) -> 55000 | F49: =SUMIFS($K49:$BR49,$K$1:$BR$1,F$1) -> 0 | G49: =SUMIFS($K49:$BR49,$K$1:$BR$1,G$1) -> 0 | H49: =SUMIFS($K49:$BR49,$K$1:$BR$1,H$1) -> 0 | I49: =SUMIFS($K49:$BR49,$K$1:$BR$1,I$1) -> 0 | K49: {=IFERROR(INDEX(Shareholder_Salary_Adj,K$1)/12,0)} -> 4583.3333 | L49: {=IFERROR(INDEX(Shareholder_Salary_Adj,L$1)/12,0)} -> 4583.3333 | M49: {=IFERROR(INDEX(Shareholder_Salary_Adj,M$1)/12,0)} -> 4583.3333 | N49: {=IFERROR(INDEX(Shareholder_Salary_Adj,N$1)/12,0)} -> 4583.3333 | O49: {=IFERROR(INDEX(Shareholder_Salary_Adj,O$1)/12,0)} -> 4583.3333 | P49: {=IFERROR(INDEX(Shareholder_Salary_Adj,P$1)/12,0)} -> 4583.3333 | Q49: {=IFERROR(INDEX(Shareholder_Salary_Adj,Q$1)/12,0)} -> 4583.3333 | R49: {=IFERROR(INDEX(Shareholder_Salary_Adj,R$1)/12,0)} -> 4583.3333 | ... BR49: {=IFERROR(INDEX(Shareholder_Salary_Adj,BR$1)/12,0)} -> 0
B50: Adjusted Pre-tax profit % | E50: =(E41-E49)/E6 -> -0.53818528 | F50: =(F41-F49)/F6 -> -0.034441258 | G50: =(G41-G49)/G6 -> 0.016091269 | H50: =(H41-H49)/H6 -> 0.032626309 | I50: =(I41-I49)/I6 -> 0.10954735 | K50: =(K41-K49)/K6 -> -1.2830418 | L50: =(L41-L49)/L6 -> -0.94595049 | M50: =(M41-M49)/M6 -> -0.82420013 | N50: =(N41-N49)/N6 -> -0.72323642 | O50: =(O41-O49)/O6 -> -0.63815464 | P50: =(P41-P49)/P6 -> -0.56548062 | Q50: =(Q41-Q49)/Q6 -> -0.50268462 | R50: =(R41-R49)/R6 -> -0.44788084 | ... BR50: =(BR41-BR49)/BR6 -> 0.12050205
B52: Non-Labor Gross Margin | E52: =E14 -> 176657.66 | F52: =F14 -> 312045.21 | G52: =G14 -> 362091.09 | H52: =H14 -> 395670.38 | I52: =I14 -> 428510.83 | K52: =K14 -> 8036.6585 | L52: =L14 -> 10120.237 | M52: =M14 -> 11162.026 | N52: =N14 -> 12203.815 | O52: =O14 -> 13245.604 | P52: =P14 -> 14287.393 | Q52: =Q14 -> 15329.182 | R52: =R14 -> 16370.971 | ... BR52: =BR14 -> 37028.626
B53: Total Wages | E53: =E26+E17 -> 43440.408 | F53: =F26+F17 -> 155170.02 | G53: =G26+G17 -> 180056.23 | H53: =H26+H17 -> 196754.12 | I53: =I26+I17 -> 213084.62 | K53: =K26+K17 -> 1976.2275 | L53: =L26+L17 -> 2488.5828 | M53: =M26+M17 -> 2744.7604 | N53: =N26+N17 -> 3000.9381 | O53: =O26+O17 -> 3257.1157 | P53: =P26+P17 -> 3513.2933 | Q53: =Q26+Q17 -> 3769.471 | R53: =R26+R17 -> 4025.6486 | ... BR53: =BR26+BR17 -> 18081.492
B54: Adjusted total wages | E54: =E53+E49 -> 98440.408 | F54: =F53+F49 -> 155170.02 | G54: =G53+G49 -> 180056.23 | H54: =H53+H49 -> 196754.12 | I54: =I53+I49 -> 213084.62 | K54: =K53+K49 -> 6559.5608 | L54: =L53+L49 -> 7071.9161 | M54: =M53+M49 -> 7328.0938 | N54: =N53+N49 -> 7584.2714 | O54: =O53+O49 -> 7840.449 | P54: =P53+P49 -> 8096.6267 | Q54: =Q53+Q49 -> 8352.8043 | R54: =R53+R49 -> 8608.9819 | ... BR54: =BR53+BR49 -> 18081.492
B56: Salary Cap @ 15% | E56: =((1-E45)*E6)-E12-E24-E25-E27-E28+E38 -> 61360.952 | F56: =((1-F45)*F6)-F12-F24-F25-F27-F28+F38 -> 127270.31 | G56: =((1-G45)*G6)-G12-G24-G25-G27-G28+G38 -> 164925.46 | H56: =((1-H45)*H6)-H12-H24-H25-H27-H28+H38 -> 182882.48 | I56: =((1-I45)*I6)-I12-I24-I25-I27-I28+I38 -> 200378.2 | K56: =((1-K45)*K6)-K12-K24-K25-K27-K28+K38 -> 1277.8642 | L56: =((1-L45)*L6)-L12-L24-L25-L27-L28+L38 -> 2473.3598 | M56: =((1-M45)*M6)-M12-M24-M25-M27-M28+M38 -> 3071.1076 | N56: =((1-N45)*N6)-N12-N24-N25-N27-N28+N38 -> 3668.8555 | O56: =((1-O45)*O6)-O12-O24-O25-O27-O28+O38 -> 4266.6033 | P56: =((1-P45)*P6)-P12-P24-P25-P27-P28+P38 -> 4864.3511 | Q56: =((1-Q45)*Q6)-Q12-Q24-Q25-Q27-Q28+Q38 -> 5462.0989 | R56: =((1-R45)*R6)-R12-R24-R25-R27-R28+R38 -> 6059.8468 | ... BR56: =((1-BR45)*BR6)-BR12-BR24-BR25-BR27-BR28+BR38 -> 17520.099
B57: (Over)/Under cap Using Adj Total Wages | E57: =E56-E54 -> -37079.456 | F57: =F56-F54 -> -27899.712 | G57: =G56-G54 -> -15130.77 | H57: =H56-H54 -> -13871.642 | I57: =I56-I54 -> -12706.421 | K57: =K56-K54 -> -5281.6967 | L57: =L56-L54 -> -4598.5563 | M57: =M56-M54 -> -4256.9861 | N57: =N56-N54 -> -3915.4159 | O57: =O56-O54 -> -3573.8457 | P57: =P56-P54 -> -3232.2756 | Q57: =Q56-Q54 -> -2890.7054 | R57: =R56-R54 -> -2549.1352 | ... BR57: =BR56-BR54 -> -561.3933
B59: Labor efficiency (NLGM/Wages) | E59: =IFERROR(E52/E53,"") -> 4.0666667 | F59: =IFERROR(F52/F53,"") -> 2.010989 | G59: =IFERROR(G52/G53,"") -> 2.010989 | H59: =IFERROR(H52/H53,"") -> 2.010989 | I59: =IFERROR(I52/I53,"") -> 2.010989 | K59: =IFERROR(K52/K53,"") -> 4.0666667 | L59: =IFERROR(L52/L53,"") -> 4.0666667 | M59: =IFERROR(M52/M53,"") -> 4.0666667 | N59: =IFERROR(N52/N53,"") -> 4.0666667 | O59: =IFERROR(O52/O53,"") -> 4.0666667 | P59: =IFERROR(P52/P53,"") -> 4.0666667 | Q59: =IFERROR(Q52/Q53,"") -> 4.0666667 | R59: =IFERROR(R52/R53,"") -> 4.0666667 | ... BR59: =IFERROR(BR52/BR53,"") -> 2.0478745
B60: Adjusted Labor efficiency (NLGM/Wages) | E60: =IFERROR(E52/E54,"") -> 1.7945645 | F60: =IFERROR(F52/F54,"") -> 2.010989 | G60: =IFERROR(G52/G54,"") -> 2.010989 | H60: =IFERROR(H52/H54,"") -> 2.010989 | I60: =IFERROR(I52/I54,"") -> 2.010989 | K60: =IFERROR(K52/K54,"") -> 1.2251824 | L60: =IFERROR(L52/L54,"") -> 1.4310459 | M60: =IFERROR(M52/M54,"") -> 1.5231827 | N60: =IFERROR(N52/N54,"") -> 1.6090952 | O60: =IFERROR(O52/O54,"") -> 1.6893935 | P60: =IFERROR(P52/P54,"") -> 1.7646106 | Q60: =IFERROR(Q52/Q54,"") -> 1.8352138 | R60: =IFERROR(R52/R54,"") -> 1.9016152 | ... BR60: =IFERROR(BR52/BR54,"") -> 2.0478745
B62: Discretionary marketing as % of Revenue | E62: =IFERROR(E25/E6,"") -> 0.05 | F62: =IFERROR(F25/F6,"") -> 0.04 | G62: =IFERROR(G25/G6,"") -> 0.02 | H62: =IFERROR(H25/H6,"") -> 0.02 | I62: =IFERROR(I25/I6,"") -> 0.02 | K62: =IFERROR(K25/K6,"") -> 0.05 | L62: =IFERROR(L25/L6,"") -> 0.05 | M62: =IFERROR(M25/M6,"") -> 0.05 | N62: =IFERROR(N25/N6,"") -> 0.05 | O62: =IFERROR(O25/O6,"") -> 0.05 | P62: =IFERROR(P25/P6,"") -> 0.05 | Q62: =IFERROR(Q25/Q6,"") -> 0.05 | R62: =IFERROR(R25/R6,"") -> 0.05 | ... BR62: =IFERROR(BR25/BR6,"") -> 0.02
B63: PR Taxes & Benefits as % All wages | E63: =IFERROR(E27/(E26+E17),"") -> 0.2 | F63: =IFERROR(F27/(F26+F17),"") -> 0.2 | G63: =IFERROR(G27/(G26+G17),"") -> 0.2 | H63: =IFERROR(H27/(H26+H17),"") -> 0.2 | I63: =IFERROR(I27/(I26+I17),"") -> 0.2 | K63: =IFERROR(K27/(K26+K17),"") -> 0.2 | L63: =IFERROR(L27/(L26+L17),"") -> 0.2 | M63: =IFERROR(M27/(M26+M17),"") -> 0.2 | N63: =IFERROR(N27/(N26+N17),"") -> 0.2 | O63: =IFERROR(O27/(O26+O17),"") -> 0.2 | P63: =IFERROR(P27/(P26+P17),"") -> 0.2 | Q63: =IFERROR(Q27/(Q26+Q17),"") -> 0.2 | R63: =IFERROR(R27/(R26+R17),"") -> 0.2 | ... BR63: =IFERROR(BR27/(BR26+BR17),"") -> 0.2
B64: Other Operating Expenses as % of Revenue | E64: =IFERROR(E28/E6,"") -> 0.03 | F64: =IFERROR(F28/F6,"") -> 0.03 | G64: =IFERROR(G28/G6,"") -> 0.03 | H64: =IFERROR(H28/H6,"") -> 0.03 | I64: =IFERROR(I28/I6,"") -> 0.03 | K64: =IFERROR(K28/K6,"") -> 0.03 | L64: =IFERROR(L28/L6,"") -> 0.03 | M64: =IFERROR(M28/M6,"") -> 0.03 | N64: =IFERROR(N28/N6,"") -> 0.03 | O64: =IFERROR(O28/O6,"") -> 0.03 | P64: =IFERROR(P28/P6,"") -> 0.03 | Q64: =IFERROR(Q28/Q6,"") -> 0.03 | R64: =IFERROR(R28/R6,"") -> 0.03 | ... BR64: =IFERROR(BR28/BR6,"") -> 0.03

Sheet Balance Sheet
B1: =Company_Name -> ABC Company
B2: Balance Sheet | E2: ='Input Assumptions'!E$18 -> 1 | F2: ='Input Assumptions'!F$18 -> 2 | G2: ='Input Assumptions'!G$18 -> 3 | H2: ='Input Assumptions'!H$18 -> 4 | I2: ='Input Assumptions'!I$18 -> 5 | K2: =IF(K$4<Fin_Year_End,1,IF(MONTH(K$4)=MONTH(Fin_Year_End)+1,MIN(J2+1,5),J2)) -> 1 | L2: =IF(L$4<Fin_Year_End,1,IF(MONTH(L$4)=MONTH(Fin_Year_End)+1,MIN(K2+1,5),K2)) -> 1 | M2: =IF(M$4<Fin_Year_End,1,IF(MONTH(M$4)=MONTH(Fin_Year_End)+1,MIN(L2+1,5),L2)) -> 1 | N2: =IF(N$4<Fin_Year_End,1,IF(MONTH(N$4)=MONTH(Fin_Year_End)+1,MIN(M2+1,5),M2)) -> 1 | O2: =IF(O$4<Fin_Year_End,1,IF(MONTH(O$4)=MONTH(Fin_Year_End)+1,MIN(N2+1,5),N2)) -> 1 | P2: =IF(P$4<Fin_Year_End,1,IF(MONTH(P$4)=MONTH(Fin_Year_End)+1,MIN(O2+1,5),O2)) -> 1 | Q2: =IF(Q$4<Fin_Year_End,1,IF(MONTH(Q$4)=MONTH(Fin_Year_End)+1,MIN(P2+1,5),P2)) -> 1 | R2: =IF(R$4<Fin_Year_End,1,IF(MONTH(R$4)=MONTH(Fin_Year_End)+1,MIN(Q2+1,5),Q2)) -> 1 | ... BR2: =IF(BR$4<Fin_Year_End,1,IF(MONTH(BR$4)=MONTH(Fin_Year_End)+1,MIN(BQ2+1,5),BQ2)) -> 5
E3: ='Input Assumptions'!E$17 -> 2024-2025 | F3: ='Input Assumptions'!F$17 -> 2025-2026 | G3: ='Input Assumptions'!G$17 -> 2026-2027 | H3: ='Input Assumptions'!H$17 -> 2027-2028 | I3: ='Input Assumptions'!I$17 -> 2028-2029
E4: =Model!E$12 -> Year 1 | F4: =Model!F$12 -> Year 2 | G4: =Model!G$12 -> Year 3 | H4: =Model!H$12 -> Year 4 | I4: =Model!I$12 -> Year 5 | K4: =EOMONTH(Start_Date,-1)+1 -> 45505 | L4: =EOMONTH(K4,0)+1 -> 45536 | M4: =EOMONTH(L4,0)+1 -> 45566 | N4: =EOMONTH(M4,0)+1 -> 45597 | O4: =EOMONTH(N4,0)+1 -> 45627 | P4: =EOMONTH(O4,0)+1 -> 45658 | Q4: =EOMONTH(P4,0)+1 -> 45689 | R4: =EOMONTH(Q4,0)+1 -> 45717 | S4: =EOMONTH(R4,0)+1 -> 45748 | ... BR4: =EOMONTH(BQ4,0)+1 -> 47300
B5: ASSETS
B6: Current Assets:
B7: Cash | E7: =INDEX($K7:$BR7,,MATCH(E$2,$K$2:$BR$2,0)+11) -> 12088.443 | F7: =INDEX($K7:$BR7,,MATCH(F$2,$K$2:$BR$2,0)+11) -> 6064.8014 | G7: =INDEX($K7:$BR7,,MATCH(G$2,$K$2:$BR$2,0)+11) -> 35316.959 | H7: =INDEX($K7:$BR7,,MATCH(H$2,$K$2:$BR$2,0)+11) -> 76777.854 | I7: =INDEX($K7:$BR7,,MATCH(I$2,$K$2:$BR$2,0)+11) -> 129224.97 | K7: =Model!K92 -> 98240.291 | L7: =Model!L92 -> 85290.703 | M7: =Model!M92 -> 75696.812 | N7: =Model!N92 -> 65534.673 | O7: =Model!O92 -> 57275.556 | P7: =Model!P92 -> 48983.37 | Q7: =Model!Q92 -> 38697.853 | R7: =Model!R92 -> 34235.882 | ... BR7: =Model!BR92 -> 129224.97
B8: Accounts receivable | E8: =INDEX($K8:$BR8,,MATCH(E$2,$K$2:$BR$2,0)+11) -> 32582.962 | F8: =INDEX($K8:$BR8,,MATCH(F$2,$K$2:$BR$2,0)+11) -> 45337.891 | G8: =INDEX($K8:$BR8,,MATCH(G$2,$K$2:$BR$2,0)+11) -> 50085.361 | H8: =INDEX($K8:$BR8,,MATCH(H$2,$K$2:$BR$2,0)+11) -> 54242.421 | I8: =INDEX($K8:$BR8,,MATCH(I$2,$K$2:$BR$2,0)+11) -> 58744.515 | K8: =Model!K93 -> 12749.855 | L8: =Model!L93 -> 16590.552 | M8: =Model!M93 -> 17708.132 | N8: =Model!N93 -> 20006.254 | O8: =Model!O93 -> 21013.65 | P8: =Model!P93 -> 22666.409 | Q8: =Model!Q93 -> 26924.793 | R8: =Model!R93 -> 25971.927 | ... BR8: =Model!BR93 -> 58744.515
B9: Other Current Assets | E9: =INDEX($K9:$BR9,,MATCH(E$2,$K$2:$BR$2,0)+11) -> 21253.018 | F9: =INDEX($K9:$BR9,,MATCH(F$2,$K$2:$BR$2,0)+11) -> 29572.726 | G9: =INDEX($K9:$BR9,,MATCH(G$2,$K$2:$BR$2,0)+11) -> 32669.377 | H9: =INDEX($K9:$BR9,,MATCH(H$2,$K$2:$BR$2,0)+11) -> 35380.919 | I9: =INDEX($K9:$BR9,,MATCH(I$2,$K$2:$BR$2,0)+11) -> 38317.518 | K9: =Model!K94 -> 8316.3985 | L9: =Model!L94 -> 10472.502 | M9: =Model!M94 -> 11550.553 | N9: =Model!N94 -> 12628.605 | O9: =Model!O94 -> 13706.657 | P9: =Model!P94 -> 14784.708 | Q9: =Model!Q94 -> 15862.76 | R9: =Model!R94 -> 16940.812 | ... BR9: =Model!BR94 -> 38317.518
B11: Total current assets | E11: =SUM(E7:E9) -> 65924.423 | F11: =SUM(F7:F9) -> 80975.419 | G11: =SUM(G7:G9) -> 118071.7 | H11: =SUM(H7:H9) -> 166401.19 | I11: =SUM(I7:I9) -> 226287 | K11: =SUM(K7:K9) -> 119306.54 | L11: =SUM(L7:L9) -> 112353.76 | M11: =SUM(M7:M9) -> 104955.5 | N11: =SUM(N7:N9) -> 98169.532 | O11: =SUM(O7:O9) -> 91995.862 | P11: =SUM(P7:P9) -> 86434.487 | Q11: =SUM(Q7:Q9) -> 81485.406 | R11: =SUM(R7:R9) -> 77148.62 | ... BR11: =SUM(BR7:BR9) -> 226287
B13: Fixed Assets:
B14: Equipment | E14: =INDEX($K14:$BR14,,MATCH(E$2,$K$2:$BR$2,0)+11) -> 177825 | F14: =INDEX($K14:$BR14,,MATCH(F$2,$K$2:$BR$2,0)+11) -> 177825 | G14: =INDEX($K14:$BR14,,MATCH(G$2,$K$2:$BR$2,0)+11) -> 177825 | H14: =INDEX($K14:$BR14,,MATCH(H$2,$K$2:$BR$2,0)+11) -> 177825 | I14: =INDEX($K14:$BR14,,MATCH(I$2,$K$2:$BR$2,0)+11) -> 177825 | K14: =Model!K239+J14 -> 177825 | L14: =Model!L239+K14 -> 177825 | M14: =Model!M239+L14 -> 177825 | N14: =Model!N239+M14 -> 177825 | O14: =Model!O239+N14 -> 177825 | P14: =Model!P239+O14 -> 177825 | Q14: =Model!Q239+P14 -> 177825 | R14: =Model!R239+Q14 -> 177825 | ... BR14: =Model!BR239+BQ14 -> 177825
B15: Accumulated Depreciation | E15: =INDEX($K15:$BR15,,MATCH(E$2,$K$2:$BR$2,0)+11) -> -44456.25 | F15: =INDEX($K15:$BR15,,MATCH(F$2,$K$2:$BR$2,0)+11) -> -88912.5 | G15: =INDEX($K15:$BR15,,MATCH(G$2,$K$2:$BR$2,0)+11) -> -133368.75 | H15: =INDEX($K15:$BR15,,MATCH(H$2,$K$2:$BR$2,0)+11) -> -177825 | I15: =INDEX($K15:$BR15,,MATCH(I$2,$K$2:$BR$2,0)+11) -> -177825 | K15: =Model!K241+J15 -> -3704.6875 | L15: =Model!L241+K15 -> -7409.375 | M15: =Model!M241+L15 -> -11114.062 | N15: =Model!N241+M15 -> -14818.75 | O15: =Model!O241+N15 -> -18523.438 | P15: =Model!P241+O15 -> -22228.125 | Q15: =Model!Q241+P15 -> -25932.812 | R15: =Model!R241+Q15 -> -29637.5 | ... BR15: =Model!BR241+BQ15 -> -177825
B17: Net book value of fixed assets | E17: =SUM(E14:E15) -> 133368.75 | F17: =SUM(F14:F15) -> 88912.5 | G17: =SUM(G14:G15) -> 44456.25 | H17: =SUM(H14:H15) -> 0 | I17: =SUM(I14:I15) -> 0 | K17: =SUM(K14:K15) -> 174120.31 | L17: =SUM(L14:L15) -> 170415.62 | M17: =SUM(M14:M15) -> 166710.94 | N17: =SUM(N14:N15) -> 163006.25 | O17: =SUM(O14:O15) -> 159301.56 | P17: =SUM(P14:P15) -> 155596.88 | Q17: =SUM(Q14:Q15) -> 151892.19 | R17: =SUM(R14:R15) -> 148187.5 | ... BR17: =SUM(BR14:BR15) -> 0
B19: Other Assets
B20: Other Assets | E20: =INDEX($K20:$BR20,,MATCH(E$2,$K$2:$BR$2,0)+11) -> 0 | F20: =INDEX($K20:$BR20,,MATCH(F$2,$K$2:$BR$2,0)+11) -> 0 | G20: =INDEX($K20:$BR20,,MATCH(G$2,$K$2:$BR$2,0)+11) -> 0 | H20: =INDEX($K20:$BR20,,MATCH(H$2,$K$2:$BR$2,0)+11) -> 0 | I20: =INDEX($K20:$BR20,,MATCH(I$2,$K$2:$BR$2,0)+11) -> 0 | K20: 0 | L20: 0 | M20: 0 | N20: 0 | O20: 0 | P20: 0 | Q20: 0 | R20: 0 | S20: 0 | T20: 0 | U20: 0 | V20: 0 | W20: 0 | X20: 0 | Y20: 0 | Z20: 0 | AA20: 0 | AB20: 0 | AC20: 0 | AD20: 0 | AE20: 0 | AF20: 0 | AG20: 0 | AH20: 0 | AI20: 0 | AJ20: 0 | AK20: 0 | AL20: 0 | AM20: 0 | AN20: 0 | AO20: 0 | AP20: 0 | AQ20: 0 | AR20: 0 | AS20: 0 | AT20: 0 | AU20: 0 | AV20: 0 | AW20: 0 | AX20: 0 | AY20: 0 | AZ20: 0 | BA20: 0 | BB20: 0 | BC20: 0 | BD20: 0 | BE20: 0 | BF20: 0 | BG20: 0 | BH20: 0 | BI20: 0 | BJ20: 0 | BK20: 0 | BL20: 0 | BM20: 0 | BN20: 0 | BO20: 0 | BP20: 0 | BQ20: 0 | BR20: 0
B21: Total Other Assets | E21: =SUM(E20) -> 0 | F21: =SUM(F20) -> 0 | G21: =SUM(G20) -> 0 | H21: =SUM(H20) -> 0 | I21: =SUM(I20) -> 0 | K21: =SUM(K20) -> 0 | L21: =SUM(L20) -> 0 | M21: =SUM(M20) -> 0 | N21: =SUM(N20) -> 0 | O21: =SUM(O20) -> 0 | P21: =SUM(P20) -> 0 | Q21: =SUM(Q20) -> 0 | R21: =SUM(R20) -> 0 | ... BR21: =SUM(BR20) -> 0
B23: Total Assets | E23: =E11+E17+E21 -> 199293.17 | F23: =F11+F17+F21 -> 169887.92 | G23: =G11+G17+G21 -> 162527.95 | H23: =H11+H17+H21 -> 166401.19 | I23: =I11+I17+I21 -> 226287 | K23: =K11+K17+K20 -> 293426.86 | L23: =L11+L17+L21 -> 282769.38 | M23: =M11+M17+M21 -> 271666.43 | N23: =N11+N17+N21 -> 261175.78 | O23: =O11+O17+O21 -> 251297.42 | P23: =P11+P17+P21 -> 242031.36 | Q23: =Q11+Q17+Q21 -> 233377.59 | R23: =R11+R17+R21 -> 225336.12 | S23: =S11+S17+S21 -> 217906.94 | ... BR23: =BR11+BR17+BR21 -> 226287
B25: LIABILITIES AND SHAREHOLDERS' EQUITY
B27: Current liabilities:
B28: Accounts Payable | E28: =INDEX($K28:$BR28,,MATCH(E$2,$K$2:$BR$2,0)+11) -> 20853.096 | F28: =INDEX($K28:$BR28,,MATCH(F$2,$K$2:$BR$2,0)+11) -> 29016.25 | G28: =INDEX($K28:$BR28,,MATCH(G$2,$K$2:$BR$2,0)+11) -> 32054.631 | H28: =INDEX($K28:$BR28,,MATCH(H$2,$K$2:$BR$2,0)+11) -> 34715.149 | I28: =INDEX($K28:$BR28,,MATCH(I$2,$K$2:$BR$2,0)+11) -> 37596.49 | K28: =Model!K103 -> 8159.9071 | L28: =Model!L103 -> 10275.439 | M28: =Model!M103 -> 11333.204 | N28: =Model!N103 -> 12390.97 | O28: =Model!O103 -> 13448.736 | P28: =Model!P103 -> 14506.502 | Q28: =Model!Q103 -> 15564.267 | R28: =Model!R103 -> 16622.033 | ... BR28: =Model!BR103 -> 37596.49
B29: Tax Payable | E29: =INDEX($K29:$BR29,,MATCH(E$2,$K$2:$BR$2,0)+11) -> 0 | F29: =INDEX($K29:$BR29,,MATCH(F$2,$K$2:$BR$2,0)+11) -> 0 | G29: =INDEX($K29:$BR29,,MATCH(G$2,$K$2:$BR$2,0)+11) -> 0 | H29: =INDEX($K29:$BR29,,MATCH(H$2,$K$2:$BR$2,0)+11) -> 0 | I29: =INDEX($K29:$BR29,,MATCH(I$2,$K$2:$BR$2,0)+11) -> 0 | K29: =Model!K104 -> 0 | L29: =Model!L104 -> 0 | M29: =Model!M104 -> 0 | N29: =Model!N104 -> 0 | O29: =Model!O104 -> 0 | P29: =Model!P104 -> 0 | Q29: =Model!Q104 -> 0 | R29: =Model!R104 -> 0 | ... BR29: =Model!BR104 -> 0
B30: Credit Card Payable | E30: =INDEX($K30:$BR30,,MATCH(E$2,$K$2:$BR$2,0)+11) -> 0 | F30: =INDEX($K30:$BR30,,MATCH(F$2,$K$2:$BR$2,0)+11) -> 0 | G30: =INDEX($K30:$BR30,,MATCH(G$2,$K$2:$BR$2,0)+11) -> 0 | H30: =INDEX($K30:$BR30,,MATCH(H$2,$K$2:$BR$2,0)+11) -> 0 | I30: =INDEX($K30:$BR30,,MATCH(I$2,$K$2:$BR$2,0)+11) -> 0 | K30: 0 | L30: 0 | M30: 0 | N30: 0 | O30: 0 | P30: 0 | Q30: 0 | R30: 0 | S30: 0 | T30: 0 | U30: 0 | V30: 0 | W30: 0 | X30: 0 | Y30: 0 | Z30: 0 | AA30: 0 | AB30: 0 | AC30: 0 | AD30: 0 | AE30: 0 | AF30: 0 | AG30: 0 | AH30: 0 | AI30: 0 | AJ30: 0 | AK30: 0 | AL30: 0 | AM30: 0 | AN30: 0 | AO30: 0 | AP30: 0 | AQ30: 0 | AR30: 0 | AS30: 0 | AT30: 0 | AU30: 0 | AV30: 0 | AW30: 0 | AX30: 0 | AY30: 0 | AZ30: 0 | BA30: 0 | BB30: 0 | BC30: 0 | BD30: 0 | BE30: 0 | BF30: 0 | BG30: 0 | BH30: 0 | BI30: 0 | BJ30: 0 | BK30: 0 | BL30: 0 | BM30: 0 | BN30: 0 | BO30: 0 | BP30: 0 | BQ30: 0 | BR30: 0
B31: Line of Credit | E31: =INDEX($K31:$BR31,,MATCH(E$2,$K$2:$BR$2,0)+11) -> 0 | F31: =INDEX($K31:$BR31,,MATCH(F$2,$K$2:$BR$2,0)+11) -> 0 | G31: =INDEX($K31:$BR31,,MATCH(G$2,$K$2:$BR$2,0)+11) -> 0 | H31: =INDEX($K31:$BR31,,MATCH(H$2,$K$2:$BR$2,0)+11) -> 0 | I31: =INDEX($K31:$BR31,,MATCH(I$2,$K$2:$BR$2,0)+11) -> 0 | K31: 0 | L31: 0 | M31: 0 | N31: 0 | O31: 0 | P31: 0 | Q31: 0 | R31: 0 | S31: 0 | T31: 0 | U31: 0 | V31: 0 | W31: 0 | X31: 0 | Y31: 0 | Z31: 0 | AA31: 0 | AB31: 0 | AC31: 0 | AD31: 0 | AE31: 0 | AF31: 0 | AG31: 0 | AH31: 0 | AI31: 0 | AJ31: 0 | AK31: 0 | AL31: 0 | AM31: 0 | AN31: 0 | AO31: 0 | AP31: 0 | AQ31: 0 | AR31: 0 | AS31: 0 | AT31: 0 | AU31: 0 | AV31: 0 | AW31: 0 | AX31: 0 | AY31: 0 | AZ31: 0 | BA31: 0 | BB31: 0 | BC31: 0 | BD31: 0 | BE31: 0 | BF31: 0 | BG31: 0 | BH31: 0 | BI31: 0 | BJ31: 0 | BK31: 0 | BL31: 0 | BM31: 0 | BN31: 0 | BO31: 0 | BP31: 0 | BQ31: 0 | BR31: 0
B33: Total current liabilities | E33: =SUM(E28:E32) -> 20853.096 | F33: =SUM(F28:F32) -> 29016.25 | G33: =SUM(G28:G32) -> 32054.631 | H33: =SUM(H28:H32) -> 34715.149 | I33: =SUM(I28:I32) -> 37596.49 | K33: =SUM(K28:K32) -> 8159.9071 | L33: =SUM(L28:L32) -> 10275.439 | M33: =SUM(M28:M32) -> 11333.204 | N33: =SUM(N28:N32) -> 12390.97 | O33: =SUM(O28:O32) -> 13448.736 | P33: =SUM(P28:P32) -> 14506.502 | Q33: =SUM(Q28:Q32) -> 15564.267 | R33: =SUM(R28:R32) -> 16622.033 | ... BR33: =SUM(BR28:BR32) -> 37596.49
B35: Long-term liabilities:
B36: Notes Payable | E36: =INDEX($K36:$BR36,,MATCH(E$2,$K$2:$BR$2,0)+11) -> 219450 | F36: =INDEX($K36:$BR36,,MATCH(F$2,$K$2:$BR$2,0)+11) -> 199500 | G36: =INDEX($K36:$BR36,,MATCH(G$2,$K$2:$BR$2,0)+11) -> 179550 | H36: =INDEX($K36:$BR36,,MATCH(H$2,$K$2:$BR$2,0)+11) -> 159600 | I36: =INDEX($K36:$BR36,,MATCH(I$2,$K$2:$BR$2,0)+11) -> 139650 | K36: =Model!K107 -> 237737.5 | L36: =Model!L107 -> 236075 | M36: =Model!M107 -> 234412.5 | N36: =Model!N107 -> 232750 | O36: =Model!O107 -> 231087.5 | P36: =Model!P107 -> 229425 | Q36: =Model!Q107 -> 227762.5 | R36: =Model!R107 -> 226100 | ... BR36: =Model!BR107 -> 139650
B38: Total long-term liabilities | E38: =SUM(E36) -> 219450 | F38: =SUM(F36) -> 199500 | G38: =SUM(G36) -> 179550 | H38: =SUM(H36) -> 159600 | I38: =SUM(I36) -> 139650 | K38: =SUM(K36) -> 237737.5 | L38: =SUM(L36) -> 236075 | M38: =SUM(M36) -> 234412.5 | N38: =SUM(N36) -> 232750 | O38: =SUM(O36) -> 231087.5 | P38: =SUM(P36) -> 229425 | Q38: =SUM(Q36) -> 227762.5 | R38: =SUM(R36) -> 226100 | ... BR38: =SUM(BR36) -> 139650
B40: Total Liabilities | E40: =E33+E38 -> 240303.1 | F40: =F33+F38 -> 228516.25 | G40: =G33+G38 -> 211604.63 | H40: =H33+H38 -> 194315.15 | I40: =I33+I38 -> 177246.49 | K40: =K33+K38 -> 245897.41 | L40: =L33+L38 -> 246350.44 | M40: =M33+M38 -> 245745.7 | N40: =N33+N38 -> 245140.97 | O40: =O33+O38 -> 244536.24 | P40: =P33+P38 -> 243931.5 | Q40: =Q33+Q38 -> 243326.77 | R40: =R33+R38 -> 242722.03 | ... BR40: =BR33+BR38 -> 177246.49
B42: Capital
B43: Common stock | E43: =INDEX($K43:$BR43,,MATCH(E$2,$K$2:$BR$2,0)+11) -> 59850 | F43: =INDEX($K43:$BR43,,MATCH(F$2,$K$2:$BR$2,0)+11) -> 59850 | G43: =INDEX($K43:$BR43,,MATCH(G$2,$K$2:$BR$2,0)+11) -> 59850 | H43: =INDEX($K43:$BR43,,MATCH(H$2,$K$2:$BR$2,0)+11) -> 59850 | I43: =INDEX($K43:$BR43,,MATCH(I$2,$K$2:$BR$2,0)+11) -> 59850 | K43: =Model!K114 -> 59850 | L43: =Model!L114 -> 59850 | M43: =Model!M114 -> 59850 | N43: =Model!N114 -> 59850 | O43: =Model!O114 -> 59850 | P43: =Model!P114 -> 59850 | Q43: =Model!Q114 -> 59850 | R43: =Model!R114 -> 59850 | ... BR43: =Model!BR114 -> 59850
B44: Retained earnings | E44: =INDEX($K44:$BR44,,MATCH(E$2,$K$2:$BR$2,0)+11) -> -100859.92 | F44: =INDEX($K44:$BR44,,MATCH(F$2,$K$2:$BR$2,0)+11) -> -118478.33 | G44: =INDEX($K44:$BR44,,MATCH(G$2,$K$2:$BR$2,0)+11) -> -108926.68 | H44: =INDEX($K44:$BR44,,MATCH(H$2,$K$2:$BR$2,0)+11) -> -87763.955 | I44: =INDEX($K44:$BR44,,MATCH(I$2,$K$2:$BR$2,0)+11) -> -10809.487 | K44: =Model!K115 -> -12320.55 | L44: =Model!L115 -> -23431.057 | M44: =Model!M115 -> -33929.27 | N44: =Model!N115 -> -43815.188 | O44: =Model!O115 -> -53088.811 | P44: =Model!P115 -> -61750.14 | Q44: =Model!Q115 -> -69799.174 | R44: =Model!R115 -> -77235.913 | ... BR44: =Model!BR115 -> -10809.487
B46: Total Capital | E46: =SUM(E43:E44) -> -41009.923 | F46: =SUM(F43:F44) -> -58628.332 | G46: =SUM(G43:G44) -> -49076.683 | H46: =SUM(H43:H44) -> -27913.955 | I46: =SUM(I43:I44) -> 49040.513 | K46: =SUM(K43:K44) -> 47529.45 | L46: =SUM(L43:L44) -> 36418.943 | M46: =SUM(M43:M44) -> 25920.73 | N46: =SUM(N43:N44) -> 16034.812 | O46: =SUM(O43:O44) -> 6761.1888 | P46: =SUM(P43:P44) -> -1900.1398 | Q46: =SUM(Q43:Q44) -> -9949.1736 | R46: =SUM(R43:R44) -> -17385.913 | ... BR46: =SUM(BR43:BR44) -> 49040.513
B48: Total liabilities and shareholders' equity | E48: =E40+E46 -> 199293.17 | F48: =F40+F46 -> 169887.92 | G48: =G40+G46 -> 162527.95 | H48: =H40+H46 -> 166401.19 | I48: =I40+I46 -> 226287 | K48: =K40+K46 -> 293426.86 | L48: =L40+L46 -> 282769.38 | M48: =M40+M46 -> 271666.43 | N48: =N40+N46 -> 261175.78 | O48: =O40+O46 -> 251297.42 | P48: =P40+P46 -> 242031.36 | Q48: =Q40+Q46 -> 233377.59 | R48: =R40+R46 -> 225336.12 | ... BR48: =BR40+BR46 -> 226287
B49: =SUM(E49:I49) -> 0 | E49: =ROUND(E23-E48,0) -> 0 | F49: =ROUND(F23-F48,0) -> 0 | G49: =ROUND(G23-G48,0) -> 0 | H49: =ROUND(H23-H48,0) -> 0 | I49: =ROUND(I23-I48,0) -> 0 | K49: =ROUND(K23-K48,0) -> 0 | L49: =ROUND(L23-L48,0) -> 0 | M49: =ROUND(M23-M48,0) -> 0 | N49: =ROUND(N23-N48,0) -> 0 | O49: =ROUND(O23-O48,0) -> 0 | P49: =ROUND(P23-P48,0) -> 0 | Q49: =ROUND(Q23-Q48,0) -> 0 | R49: =ROUND(R23-R48,0) -> 0 | ... BR49: =ROUND(BR23-BR48,0) -> 0
B51: A/R DSO (Based on last 2 months sales)
B52: A/P as % of COGS for this month and next month
B54: Core Capital | E54: =SUMIFS($K54:$BR54,$K$2:$BR$2,E$2)/12 -> 48376.397 | F54: =SUMIFS($K54:$BR54,$K$2:$BR$2,F$2)/12 -> 1654.0728 | G54: =SUMIFS($K54:$BR54,$K$2:$BR$2,G$2)/12 -> 18956.427 | H54: =SUMIFS($K54:$BR54,$K$2:$BR$2,H$2)/12 -> 55120.349 | I54: =SUMIFS($K54:$BR54,$K$2:$BR$2,I$2)/12 -> 102145.39 | K54: =K7-K31 -> 98240.291 | L54: =L7-L31 -> 85290.703 | M54: =M7-M31 -> 75696.812 | N54: =N7-N31 -> 65534.673 | O54: =O7-O31 -> 57275.556 | P54: =P7-P31 -> 48983.37 | Q54: =Q7-Q31 -> 38697.853 | R54: =R7-R31 -> 34235.882 | ... BR54: =BR7-BR31 -> 129224.97
B55: Core Capital target -Level 1 (1 month opex) | E55: =AVERAGEIFS($K55:$BR55,$K$2:$BR$2,E$2) -> 26826.397 | F55: =AVERAGEIFS($K55:$BR55,$K$2:$BR$2,F$2) -> 38559.734 | G55: =AVERAGEIFS($K55:$BR55,$K$2:$BR$2,G$2) -> 43306.994 | H55: =AVERAGEIFS($K55:$BR55,$K$2:$BR$2,H$2) -> 47101.301 | I55: =AVERAGEIFS($K55:$BR55,$K$2:$BR$2,I$2) -> 50817.639 | K55: ='P&L Statement'!K12+'P&L Statement'!K17+'P&L Statement'!K30 -> 19703.236 | L55: ='P&L Statement'!L12+'P&L Statement'!L17+'P&L Statement'!L30 -> 21923.442 | M55: ='P&L Statement'!M12+'P&L Statement'!M17+'P&L Statement'!M30 -> 23033.545 | N55: ='P&L Statement'!N12+'P&L Statement'!N17+'P&L Statement'!N30 -> 24143.648 | O55: ='P&L Statement'!O12+'P&L Statement'!O17+'P&L Statement'!O30 -> 25253.751 | P55: ='P&L Statement'!P12+'P&L Statement'!P17+'P&L Statement'!P30 -> 26363.854 | Q55: ='P&L Statement'!Q12+'P&L Statement'!Q17+'P&L Statement'!Q30 -> 27473.958 | R55: ='P&L Statement'!R12+'P&L Statement'!R17+'P&L Statement'!R30 -> 28584.061 | ... BR55: ='P&L Statement'!BR12+'P&L Statement'!BR17+'P&L Statement'!BR30 -> 52158.659
B56: Core Capital target -Level 2 (2 month opex) | E56: =AVERAGEIFS($K56:$BR56,$K$2:$BR$2,E$2) -> 53652.795 | F56: =AVERAGEIFS($K56:$BR56,$K$2:$BR$2,F$2) -> 77119.468 | G56: =AVERAGEIFS($K56:$BR56,$K$2:$BR$2,G$2) -> 86613.989 | H56: =AVERAGEIFS($K56:$BR56,$K$2:$BR$2,H$2) -> 94202.602 | I56: =AVERAGEIFS($K56:$BR56,$K$2:$BR$2,I$2) -> 101635.28 | K56: =K55*2 -> 39406.472 | L56: =L55*2 -> 43846.884 | M56: =M55*2 -> 46067.09 | N56: =N55*2 -> 48287.296 | O56: =O55*2 -> 50507.503 | P56: =P55*2 -> 52727.709 | Q56: =Q55*2 -> 54947.915 | R56: =R55*2 -> 57168.121 | ... BR56: =BR55*2 -> 104317.32
B57: Months of Core Capital | E57: =IFERROR(E54/E55,0) -> 1.8033132 | F57: =IFERROR(F54/F55,0) -> 0.042896375 | G57: =IFERROR(G54/G55,0) -> 0.43772206 | H57: =IFERROR(H54/H55,0) -> 1.1702511 | I57: =IFERROR(I54/I55,0) -> 2.010038
B58: Excess Core Capital (targeting 2 month of opex) | E58: =E54-E56 -> -5276.3976 | F58: =F54-F56 -> -75465.395 | G58: =G54-G56 -> -67657.562 | H58: =H54-H56 -> -39082.253 | I58: =I54-I56 -> 510.10731

Sheet Cash Flow Statement
B1: =Company_Name -> ABC Company
B2: Cash Flow | E2: ='Input Assumptions'!E$18 -> 1 | F2: ='Input Assumptions'!F$18 -> 2 | G2: ='Input Assumptions'!G$18 -> 3 | H2: ='Input Assumptions'!H$18 -> 4 | I2: ='Input Assumptions'!I$18 -> 5 | K2: =IF(K$4<Fin_Year_End,1,IF(MONTH(K$4)=MONTH(Fin_Year_End)+1,MIN(J2+1,5),J2)) -> 1 | L2: =IF(L$4<Fin_Year_End,1,IF(MONTH(L$4)=MONTH(Fin_Year_End)+1,MIN(K2+1,5),K2)) -> 1 | M2: =IF(M$4<Fin_Year_End,1,IF(MONTH(M$4)=MONTH(Fin_Year_End)+1,MIN(L2+1,5),L2)) -> 1 | N2: =IF(N$4<Fin_Year_End,1,IF(MONTH(N$4)=MONTH(Fin_Year_End)+1,MIN(M2+1,5),M2)) -> 1 | O2: =IF(O$4<Fin_Year_End,1,IF(MONTH(O$4)=MONTH(Fin_Year_End)+1,MIN(N2+1,5),N2)) -> 1 | P2: =IF(P$4<Fin_Year_End,1,IF(MONTH(P$4)=MONTH(Fin_Year_End)+1,MIN(O2+1,5),O2)) -> 1 | Q2: =IF(Q$4<Fin_Year_End,1,IF(MONTH(Q$4)=MONTH(Fin_Year_End)+1,MIN(P2+1,5),P2)) -> 1 | R2: =IF(R$4<Fin_Year_End,1,IF(MONTH(R$4)=MONTH(Fin_Year_End)+1,MIN(Q2+1,5),Q2)) -> 1 | ... BR2: =IF(BR$4<Fin_Year_End,1,IF(MONTH(BR$4)=MONTH(Fin_Year_End)+1,MIN(BQ2+1,5),BQ2)) -> 5
E3: ='Input Assumptions'!E$17 -> 2024-2025 | F3: ='Input Assumptions'!F$17 -> 2025-2026 | G3: ='Input Assumptions'!G$17 -> 2026-2027 | H3: ='Input Assumptions'!H$17 -> 2027-2028 | I3: ='Input Assumptions'!I$17 -> 2028-2029
E4: =Model!E$12 -> Year 1 | F4: =Model!F$12 -> Year 2 | G4: =Model!G$12 -> Year 3 | H4: =Model!H$12 -> Year 4 | I4: =Model!I$12 -> Year 5 | K4: =EOMONTH(Start_Date,-1)+1 -> 45505 | L4: =EOMONTH(K4,0)+1 -> 45536 | M4: =EOMONTH(L4,0)+1 -> 45566 | N4: =EOMONTH(M4,0)+1 -> 45597 | O4: =EOMONTH(N4,0)+1 -> 45627 | P4: =EOMONTH(O4,0)+1 -> 45658 | Q4: =EOMONTH(P4,0)+1 -> 45689 | R4: =EOMONTH(Q4,0)+1 -> 45717 | S4: =EOMONTH(R4,0)+1 -> 45748 | ... BR4: =EOMONTH(BQ4,0)+1 -> 47300
B5: Cash Flows from Operations
B7: Net Income | E7: =SUMIFS($K7:$BR7,$K$2:$BR$2,E$2) -> -100859.92 | F7: =SUMIFS($K7:$BR7,$K$2:$BR$2,F$2) -> -17618.409 | G7: =SUMIFS($K7:$BR7,$K$2:$BR$2,G$2) -> 9551.648 | H7: =SUMIFS($K7:$BR7,$K$2:$BR$2,H$2) -> 21162.728 | I7: =SUMIFS($K7:$BR7,$K$2:$BR$2,I$2) -> 76954.468 | K7: =Model!K123 -> -12320.55 | L7: =Model!L123 -> -11110.507 | M7: =Model!M123 -> -10498.213 | N7: =Model!N123 -> -9885.918 | O7: =Model!O123 -> -9273.6233 | P7: =Model!P123 -> -8661.3286 | Q7: =Model!Q123 -> -8049.0339 | R7: =Model!R123 -> -7436.7392 | ... BR7: =Model!BR123 -> 7314.7956
B9: Add Back:
B10: Depreciation | E10: =SUMIFS($K10:$BR10,$K$2:$BR$2,E$2) -> 44456.25 | F10: =SUMIFS($K10:$BR10,$K$2:$BR$2,F$2) -> 44456.25 | G10: =SUMIFS($K10:$BR10,$K$2:$BR$2,G$2) -> 44456.25 | H10: =SUMIFS($K10:$BR10,$K$2:$BR$2,H$2) -> 44456.25 | I10: =SUMIFS($K10:$BR10,$K$2:$BR$2,I$2) -> 0 | K10: =Model!K125 -> 3704.6875 | L10: =Model!L125 -> 3704.6875 | M10: =Model!M125 -> 3704.6875 | N10: =Model!N125 -> 3704.6875 | O10: =Model!O125 -> 3704.6875 | P10: =Model!P125 -> 3704.6875 | Q10: =Model!Q125 -> 3704.6875 | R10: =Model!R125 -> 3704.6875 | ... BR10: =Model!BR125 -> 0
B11: Changes in:
B12: Accounts receivable | E12: =SUMIFS($K12:$BR12,$K$2:$BR$2,E$2) -> -32582.962 | F12: =SUMIFS($K12:$BR12,$K$2:$BR$2,F$2) -> -12754.929 | G12: =SUMIFS($K12:$BR12,$K$2:$BR$2,G$2) -> -4747.4696 | H12: =SUMIFS($K12:$BR12,$K$2:$BR$2,H$2) -> -4157.0602 | I12: =SUMIFS($K12:$BR12,$K$2:$BR$2,I$2) -> -4502.0942 | K12: =Model!K127 -> -12749.855 | L12: =Model!L127 -> -3840.697 | M12: =Model!M127 -> -1117.5799 | N12: =Model!N127 -> -2298.122 | O12: =Model!O127 -> -1007.3959 | P12: =Model!P127 -> -1652.759 | Q12: =Model!Q127 -> -4258.3841 | R12: =Model!R127 -> 952.86614 | ... BR12: =Model!BR127 -> 1556.1461
B13: Other Current Assets | E13: =SUMIFS($K13:$BR13,$K$2:$BR$2,E$2) -> -21253.018 | F13: =SUMIFS($K13:$BR13,$K$2:$BR$2,F$2) -> -8319.708 | G13: =SUMIFS($K13:$BR13,$K$2:$BR$2,G$2) -> -3096.6509 | H13: =SUMIFS($K13:$BR13,$K$2:$BR$2,H$2) -> -2711.5422 | I13: =SUMIFS($K13:$BR13,$K$2:$BR$2,I$2) -> -2936.5989 | K13: =Model!K130 -> -8316.3985 | L13: =Model!L130 -> -2156.1033 | M13: =Model!M130 -> -1078.0517 | N13: =Model!N130 -> -1078.0517 | O13: =Model!O130 -> -1078.0517 | P13: =Model!P130 -> -1078.0517 | Q13: =Model!Q130 -> -1078.0517 | R13: =Model!R130 -> -1078.0517 | ... BR13: =Model!BR130 -> -253.7584
B14: Other Assets | E14: =SUMIFS($K14:$BR14,$K$2:$BR$2,E$2) -> 0 | F14: =SUMIFS($K14:$BR14,$K$2:$BR$2,F$2) -> 0 | G14: =SUMIFS($K14:$BR14,$K$2:$BR$2,G$2) -> 0 | H14: =SUMIFS($K14:$BR14,$K$2:$BR$2,H$2) -> 0 | I14: =SUMIFS($K14:$BR14,$K$2:$BR$2,I$2) -> 0
B15: Accounts Payable | E15: =SUMIFS($K15:$BR15,$K$2:$BR$2,E$2) -> 20853.096 | F15: =SUMIFS($K15:$BR15,$K$2:$BR$2,F$2) -> 8163.1544 | G15: =SUMIFS($K15:$BR15,$K$2:$BR$2,G$2) -> 3038.3806 | H15: =SUMIFS($K15:$BR15,$K$2:$BR$2,H$2) -> 2660.5185 | I15: =SUMIFS($K15:$BR15,$K$2:$BR$2,I$2) -> 2881.3403 | K15: =Model!K128 -> 8159.9071 | L15: =Model!L128 -> 2115.5315 | M15: =Model!M128 -> 1057.7657 | N15: =Model!N128 -> 1057.7657 | O15: =Model!O128 -> 1057.7657 | P15: =Model!P128 -> 1057.7657 | Q15: =Model!Q128 -> 1057.7657 | R15: =Model!R128 -> 1057.7657 | ... BR15: =Model!BR128 -> 248.98338
B16: Tax Payable | E16: =SUMIFS($K16:$BR16,$K$2:$BR$2,E$2) -> 0 | F16: =SUMIFS($K16:$BR16,$K$2:$BR$2,F$2) -> 0 | G16: =SUMIFS($K16:$BR16,$K$2:$BR$2,G$2) -> 0 | H16: =SUMIFS($K16:$BR16,$K$2:$BR$2,H$2) -> 0 | I16: =SUMIFS($K16:$BR16,$K$2:$BR$2,I$2) -> 0 | K16: =Model!K129 -> 0 | L16: =Model!L129 -> 0 | M16: =Model!M129 -> 0 | N16: =Model!N129 -> 0 | O16: =Model!O129 -> 0 | P16: =Model!P129 -> 0 | Q16: =Model!Q129 -> 0 | R16: =Model!R129 -> 0 | ... BR16: =Model!BR129 -> 0
B18: Net cash flows from operations | E18: =SUM(E7:E17) -> -89386.557 | F18: =SUM(F7:F17) -> 13926.359 | G18: =SUM(G7:G17) -> 49202.158 | H18: =SUM(H7:H17) -> 61410.894 | I18: =SUM(I7:I17) -> 72397.115 | K18: =SUM(K7:K17) -> -21522.209 | L18: =SUM(L7:L17) -> -11287.089 | M18: =SUM(M7:M17) -> -7931.391 | N18: =SUM(N7:N17) -> -8499.6384 | O18: =SUM(O7:O17) -> -6596.6176 | P18: =SUM(P7:P17) -> -6629.686 | Q18: =SUM(Q7:Q17) -> -8623.0164 | R18: =SUM(R7:R17) -> -2799.4715 | ... BR18: =SUM(BR7:BR17) -> 8866.1667
B20: Cash Flows from Investing
B21: Purchase of fixed assets | E21: =SUMIFS($K21:$BR21,$K$2:$BR$2,E$2) -> -177825 | F21: =SUMIFS($K21:$BR21,$K$2:$BR$2,F$2) -> 0 | G21: =SUMIFS($K21:$BR21,$K$2:$BR$2,G$2) -> 0 | H21: =SUMIFS($K21:$BR21,$K$2:$BR$2,H$2) -> 0 | I21: =SUMIFS($K21:$BR21,$K$2:$BR$2,I$2) -> 0 | K21: =Model!K134 -> -177825 | L21: =Model!L134 -> 0 | M21: =Model!M134 -> 0 | N21: =Model!N134 -> 0 | O21: =Model!O134 -> 0 | P21: =Model!P134 -> 0 | Q21: =Model!Q134 -> 0 | R21: =Model!R134 -> 0 | ... BR21: =Model!BR134 -> 0
B23: Net cash flows before financing | E23: =SUMIFS($K23:$BR23,$K$2:$BR$2,E$2) -> -267211.56 | F23: =SUMIFS($K23:$BR23,$K$2:$BR$2,F$2) -> 13926.359 | G23: =SUMIFS($K23:$BR23,$K$2:$BR$2,G$2) -> 49202.158 | H23: =SUMIFS($K23:$BR23,$K$2:$BR$2,H$2) -> 61410.894 | I23: =SUMIFS($K23:$BR23,$K$2:$BR$2,I$2) -> 72397.115 | K23: =K18+K21 -> -199347.21 | L23: =L18+L21 -> -11287.089 | M23: =M18+M21 -> -7931.391 | N23: =N18+N21 -> -8499.6384 | O23: =O18+O21 -> -6596.6176 | P23: =P18+P21 -> -6629.686 | Q23: =Q18+Q21 -> -8623.0164 | R23: =R18+R21 -> -2799.4715 | ... BR23: =BR18+BR21 -> 8866.1667
B25: Cash flows from Financing
B26: Notes payable | E26: =SUMIFS($K26:$BR26,$K$2:$BR$2,E$2) -> 219450 | F26: =SUMIFS($K26:$BR26,$K$2:$BR$2,F$2) -> -19950 | G26: =SUMIFS($K26:$BR26,$K$2:$BR$2,G$2) -> -19950 | H26: =SUMIFS($K26:$BR26,$K$2:$BR$2,H$2) -> -19950 | I26: =SUMIFS($K26:$BR26,$K$2:$BR$2,I$2) -> -19950 | K26: =Model!K$136+Model!K$137 -> 237737.5 | L26: =Model!L$136+Model!L$137 -> -1662.5 | M26: =Model!M$136+Model!M$137 -> -1662.5 | N26: =Model!N$136+Model!N$137 -> -1662.5 | O26: =Model!O$136+Model!O$137 -> -1662.5 | P26: =Model!P$136+Model!P$137 -> -1662.5 | Q26: =Model!Q$136+Model!Q$137 -> -1662.5 | R26: =Model!R$136+Model!R$137 -> -1662.5 | ... BR26: =Model!BR$136+Model!BR$137 -> -1662.5
B27: Line of credit | E27: =SUMIFS($K27:$BR27,$K$2:$BR$2,E$2) -> 0 | F27: =SUMIFS($K27:$BR27,$K$2:$BR$2,F$2) -> 0 | G27: =SUMIFS($K27:$BR27,$K$2:$BR$2,G$2) -> 0 | H27: =SUMIFS($K27:$BR27,$K$2:$BR$2,H$2) -> 0 | I27: =SUMIFS($K27:$BR27,$K$2:$BR$2,I$2) -> 0
B28: Interest expense | E28: =SUMIFS($K28:$BR28,$K$2:$BR$2,E$2) -> 0 | F28: =SUMIFS($K28:$BR28,$K$2:$BR$2,F$2) -> 0 | G28: =SUMIFS($K28:$BR28,$K$2:$BR$2,G$2) -> 0 | H28: =SUMIFS($K28:$BR28,$K$2:$BR$2,H$2) -> 0 | I28: =SUMIFS($K28:$BR28,$K$2:$BR$2,I$2) -> 0
B29: =Model!B138 -> Distributions | E29: =SUMIFS($K29:$BR29,$K$2:$BR$2,E$2) -> 0 | F29: =SUMIFS($K29:$BR29,$K$2:$BR$2,F$2) -> 0 | G29: =SUMIFS($K29:$BR29,$K$2:$BR$2,G$2) -> 0 | H29: =SUMIFS($K29:$BR29,$K$2:$BR$2,H$2) -> 0 | I29: =SUMIFS($K29:$BR29,$K$2:$BR$2,I$2) -> 0 | K29: =Model!K$138 -> 0 | L29: =Model!L$138 -> 0 | M29: =Model!M$138 -> 0 | N29: =Model!N$138 -> 0 | O29: =Model!O$138 -> 0 | P29: =Model!P$138 -> 0 | Q29: =Model!Q$138 -> 0 | R29: =Model!R$138 -> 0 | ... BR29: =Model!BR$138 -> 0
B30: =Model!B139 -> Equity issuance | E30: =SUMIFS($K30:$BR30,$K$2:$BR$2,E$2) -> 59850 | F30: =SUMIFS($K30:$BR30,$K$2:$BR$2,F$2) -> 0 | G30: =SUMIFS($K30:$BR30,$K$2:$BR$2,G$2) -> 0 | H30: =SUMIFS($K30:$BR30,$K$2:$BR$2,H$2) -> 0 | I30: =SUMIFS($K30:$BR30,$K$2:$BR$2,I$2) -> 0 | K30: =Model!K$139 -> 59850 | L30: =Model!L$139 | M30: =Model!M$139 | N30: =Model!N$139 | O30: =Model!O$139 | P30: =Model!P$139 | Q30: =Model!Q$139 | R30: =Model!R$139 | ... BR30: =Model!BR$139
B32: Net cash flows from financing | E32: =SUM(E26:E31) -> 279300 | F32: =SUM(F26:F31) -> -19950 | G32: =SUM(G26:G31) -> -19950 | H32: =SUM(H26:H31) -> -19950 | I32: =SUM(I26:I31) -> -19950 | K32: =SUM(K26:K31) -> 297587.5 | L32: =SUM(L26:L31) -> -1662.5 | M32: =SUM(M26:M31) -> -1662.5 | N32: =SUM(N26:N31) -> -1662.5 | O32: =SUM(O26:O31) -> -1662.5 | P32: =SUM(P26:P31) -> -1662.5 | Q32: =SUM(Q26:Q31) -> -1662.5 | R32: =SUM(R26:R31) -> -1662.5 | ... BR32: =SUM(BR26:BR31) -> -1662.5
B34: Net cash flows | E34: =E23+E32 -> 12088.443 | F34: =F23+F32 -> -6023.6413 | G34: =G23+G32 -> 29252.158 | H34: =H23+H32 -> 41460.894 | I34: =I23+I32 -> 52447.115 | K34: =K23+K32 -> 98240.291 | L34: =L23+L32 -> -12949.589 | M34: =M23+M32 -> -9593.891 | N34: =N23+N32 -> -10162.138 | O34: =O23+O32 -> -8259.1176 | P34: =P23+P32 -> -8292.186 | Q34: =Q23+Q32 -> -10285.516 | R34: =R23+R32 -> -4461.9715 | ... BR34: =BR23+BR32 -> 7203.6667
B36: Beginning cash | E36: =K36 | F36: =E38 -> 12088.443 | G36: =F38 -> 6064.8014 | H36: =G38 -> 35316.959 | I36: =H38 -> 76777.854 | K36: =J38 | L36: =K38 -> 98240.291 | M36: =L38 -> 85290.703 | N36: =M38 -> 75696.812 | O36: =N38 -> 65534.673 | P36: =O38 -> 57275.556 | Q36: =P38 -> 48983.37 | R36: =Q38 -> 38697.853 | ... BR36: =BQ38 -> 122021.3
B38: Ending cash | E38: =E36+E34 -> 12088.443 | F38: =F36+F34 -> 6064.8014 | G38: =G36+G34 -> 35316.959 | H38: =H36+H34 -> 76777.854 | I38: =I36+I34 -> 129224.97 | K38: =K36+K34 -> 98240.291 | L38: =L36+L34 -> 85290.703 | M38: =M36+M34 -> 75696.812 | N38: =N36+N34 -> 65534.673 | O38: =O36+O34 -> 57275.556 | P38: =P36+P34 -> 48983.37 | Q38: =Q36+Q34 -> 38697.853 | R38: =R36+R34 -> 34235.882 | ... BR38: =BR36+BR34 -> 129224.97
B39: Check | E39: =ROUND(Model!E144-E38,0) -> 0 | F39: =ROUND(Model!F144-F38,0) -> 0 | G39: =ROUND(Model!G144-G38,0) -> 0 | H39: =ROUND(Model!H144-H38,0) -> 0 | I39: =ROUND(Model!I144-I38,0) -> 0 | K39: =ROUND(Model!K144-K38,0) -> 0 | L39: =ROUND(Model!L144-L38,0) -> 0 | M39: =ROUND(Model!M144-M38,0) -> 0 | N39: =ROUND(Model!N144-N38,0) -> 0 | O39: =ROUND(Model!O144-O38,0) -> 0 | P39: =ROUND(Model!P144-P38,0) -> 0 | Q39: =ROUND(Model!Q144-Q38,0) -> 0 | R39: =ROUND(Model!R144-R38,0) -> 0 | ... BR39: =ROUND(Model!BR144-BR38,0) -> 0
B41: LOC Balance
B42: Base Cash Balance
B44: Cash Available to Be Paid on Line
B46: Cash Needed to be Drawn on Line

Sheet Returns on Invested Capital
B1: =Company_Name -> ABC Company | E1: Explanation
B2: Returns on Invested Capital
E3: ='Input Assumptions'!E$17 -> 2024-2025 | F3: ='Input Assumptions'!F$17 -> 2025-2026 | G3: ='Input Assumptions'!G$17 -> 2026-2027 | H3: ='Input Assumptions'!H$17 -> 2027-2028 | I3: ='Input Assumptions'!I$17 -> 2028-2029
B4: Calculation for Returns on Invested Capital | E4: =Model!E$12 -> Year 1 | F4: =Model!F$12 -> Year 2 | G4: =Model!G$12 -> Year 3 | H4: =Model!H$12 -> Year 4 | I4: =Model!I$12 -> Year 5
B5: Invested Capital
B6: Outside cash (equity injected) | E6: =SUM(Model!$E$139:E139) -> 59850 | F6: =SUM(Model!$E$139:F139) -> 59850 | G6: =SUM(Model!$E$139:G139) -> 59850 | H6: =SUM(Model!$E$139:H139) -> 59850 | I6: =SUM(Model!$E$139:I139) -> 59850
B7: Total loans (debt injected) | E7: =SUM(Model!$E$136:E136) -> 239400 | F7: =SUM(Model!$E$136:F136) -> 239400 | G7: =SUM(Model!$E$136:G136) -> 239400 | H7: =SUM(Model!$E$136:H136) -> 239400 | I7: =SUM(Model!$E$136:I136) -> 239400
B8: Total Cash Invested | E8: =SUM(E6:E7) -> 299250 | F8: =SUM(F6:F7) -> 299250 | G8: =SUM(G6:G7) -> 299250 | H8: =SUM(H6:H7) -> 299250 | I8: =SUM(I6:I7) -> 299250
B9: Total Sweat Equity | E9: =SUM('Input Assumptions'!$E$38:E38) -> 55000 | F9: =SUM('Input Assumptions'!$E$38:F38) -> 55000 | G9: =SUM('Input Assumptions'!$E$38:G38) -> 55000 | H9: =SUM('Input Assumptions'!$E$38:H38) -> 55000 | I9: =SUM('Input Assumptions'!$E$38:I38) -> 55000
B10: Retained Earnings (less distributions) | E10: =Model!E$115 -> -100859.92 | F10: =Model!F$115 -> -118478.33 | G10: =Model!G$115 -> -108926.68 | H10: =Model!H$115 -> -87763.955 | I10: =Model!I$115 -> -10809.487
B11: Total Invested Capital | E11: =SUM(E8,E9,E10) -> 253390.08 | F11: =SUM(F8,F9,F10) -> 235771.67 | G11: =SUM(G8,G9,G10) -> 245323.32 | H11: =SUM(H8,H9,H10) -> 266486.04 | I11: =SUM(I8,I9,I10) -> 343440.51
B13: Pre-Tax Net Income | E13: =Model!E$78 -> -100859.92 | F13: =Model!F$78 -> -17618.409 | G13: =Model!G$78 -> 9551.648 | H13: =Model!H$78 -> 21162.728 | I13: =Model!I$78 -> 76954.468
B14: Pre-Tax Net Income (includes expensing Sweat Equity) | E14: =E13-'Input Assumptions'!E38 -> -155859.92 | F14: =F13-'Input Assumptions'!F38 -> -17618.409 | G14: =G13-'Input Assumptions'!G38 -> 9551.648 | H14: =H13-'Input Assumptions'!H38 -> 21162.728 | I14: =I13-'Input Assumptions'!I38 -> 76954.468
B15: Tax Rate | E15: =Corp_Tax -> 0.21 | F15: =Corp_Tax -> 0.21 | G15: =Corp_Tax -> 0.21 | H15: =Corp_Tax -> 0.21 | I15: =Corp_Tax -> 0.21
B16: Taxes Due | E16: =E13*E15 -> -21180.584 | F16: =F13*F15 -> -3699.8659 | G16: =G13*G15 -> 2005.8461 | H16: =H13*H15 -> 4444.1729 | I16: =I13*I15 -> 16160.438
B17: After Tax Net Income | E17: =E13-E16 -> -79679.339 | F17: =F13-F16 -> -13918.543 | G17: =G13-G16 -> 7545.8019 | H17: =H13-H16 -> 16718.555 | I17: =I13-I16 -> 60794.03
B19: ROIC | E19: =E14/E11 -> -0.61509876 | F19: =F14/F11 -> -0.074726574 | G19: =G14/G11 -> 0.038934938 | H19: =H14/H11 -> 0.07941402 | I19: =I14/I11 -> 0.22406928
B20: Average Total Core Capital per Month | E20: ='Balance Sheet'!E54 -> 48376.397 | F20: ='Balance Sheet'!F54 -> 1654.0728 | G20: ='Balance Sheet'!G54 -> 18956.427 | H20: ='Balance Sheet'!H54 -> 55120.349 | I20: ='Balance Sheet'!I54 -> 102145.39
B21: Months of Core Capital | E21: ='Balance Sheet'!E57 -> 1.8033132 | F21: ='Balance Sheet'!F57 -> 0.042896375 | G21: ='Balance Sheet'!G57 -> 0.43772206 | H21: ='Balance Sheet'!H57 -> 1.1702511 | I21: ='Balance Sheet'!I57 -> 2.010038
B22: Excess Core Capital (assuming 2 month of opex target) | E22: ='Balance Sheet'!E58 -> -5276.3976 | F22: ='Balance Sheet'!F58 -> -75465.395 | G22: ='Balance Sheet'!G58 -> -67657.562 | H22: ='Balance Sheet'!H58 -> -39082.253 | I22: ='Balance Sheet'!I58 -> 510.10731

Sheet Valuation
B1: =Company_Name -> ABC Company
B2: Valuation | E2: ='Input Assumptions'!E$18 -> 1 | F2: ='Input Assumptions'!F$18 -> 2 | G2: ='Input Assumptions'!G$18 -> 3 | H2: ='Input Assumptions'!H$18 -> 4 | I2: ='Input Assumptions'!I$18 -> 5
E3: ='Input Assumptions'!E$17 -> 2024-2025 | F3: ='Input Assumptions'!F$17 -> 2025-2026 | G3: ='Input Assumptions'!G$17 -> 2026-2027 | H3: ='Input Assumptions'!H$17 -> 2027-2028 | I3: ='Input Assumptions'!I$17 -> 2028-2029
B4: Explanation | E4: =Model!E$12 -> Year 1 | F4: =Model!F$12 -> Year 2 | G4: =Model!G$12 -> Year 3 | H4: =Model!H$12 -> Year 4 | I4: =Model!I$12 -> Year 5
B5: EBITDA Multiple | E5: =EBITDA_Multiple -> 5
B7: Gross Sales | E7: =Model!E$26 -> 289602.72 | F7: =Model!F$26 -> 511549.52 | G7: =Model!G$26 -> 593591.95 | H7: =Model!H$26 -> 648639.97 | I7: =Model!I$26 -> 702476.76
B8: Net Operating Income | E8: =Model!E70 -> -32314.048 | F8: =Model!F70 -> 48832.716 | G8: =Model!G70 -> 73908.023 | H8: =Model!H70 -> 83424.353 | I8: =Model!I70 -> 92665.093
B9: ='Input Assumptions'!D38 -> Shareholder salary adjustment (+=underpayed) | E9: ='Input Assumptions'!E38 -> 55000 | F9: ='Input Assumptions'!F38 -> 0 | G9: ='Input Assumptions'!G38 -> 0 | H9: ='Input Assumptions'!H38 -> 0 | I9: ='Input Assumptions'!I38 -> 0
B10: Adj Net Operating Income | E10: =E8-E9 -> -87314.048 | F10: =F8-F9 -> 48832.716 | G10: =G8-G9 -> 73908.023 | H10: =H8-H9 -> 83424.353 | I10: =I8-I9 -> 92665.093
B11: Adj Net Operating Income as % of Revenue | E11: =IFERROR(E10/E7,0) -> -0.30149595 | F11: =IFERROR(F10/F7,0) -> 0.095460388 | G11: =IFERROR(G10/G7,0) -> 0.12450981 | H11: =IFERROR(H10/H7,0) -> 0.12861427 | I11: =IFERROR(I10/I7,0) -> 0.13191197
B13: Equity (invested capital) | E13: =Model!E$139 -> 59850 | F13: =Model!F$139 -> 0 | G13: =Model!G$139 -> 0 | H13: =Model!H$139 -> 0 | I13: =Model!I$139 -> 0
B15: Estimated value | E15: =E$10*$E$5 -> -436570.24 | F15: =F$10*$E$5 -> 244163.58 | G15: =G$10*$E$5 -> 369540.12 | H15: =H$10*$E$5 -> 417121.77 | I15: =I$10*$E$5 -> 463325.47
B16: ="Estimated taxes on sale ("&Corp_Tax*100&"%)" -> Estimated taxes on sale (21%) | E16: =Corp_Tax*E15 -> -91679.75 | F16: =Corp_Tax*F15 -> 51274.352 | G16: =Corp_Tax*G15 -> 77603.424 | H16: =Corp_Tax*H15 -> 87595.571 | I16: =Corp_Tax*I15 -> 97298.348
B18: Net after-tax proceeds from sale | E18: =E15-E16 -> -344890.49 | F18: =F15-F16 -> 192889.23 | G18: =G15-G16 -> 291936.69 | H18: =H15-H16 -> 329526.2 | I18: =I15-I16 -> 366027.12
B19: Replacement return required | E19: =IF(E10<0,0,IFERROR(E10/E18,0)) -> 0 | F19: =IF(F10<0,0,IFERROR(F10/F18,0)) -> 0.25316456 | G19: =IF(G10<0,0,IFERROR(G10/G18,0)) -> 0.25316456 | H19: =IF(H10<0,0,IFERROR(H10/H18,0)) -> 0.25316456 | I19: =IF(I10<0,0,IFERROR(I10/I18,0)) -> 0.25316456
B20: Business Annual ROIC | E20: ='Returns on Invested Capital'!E19 -> -0.61509876 | F20: ='Returns on Invested Capital'!F19 -> -0.074726574 | G20: ='Returns on Invested Capital'!G19 -> 0.038934938 | H20: ='Returns on Invested Capital'!H19 -> 0.07941402 | I20: ='Returns on Invested Capital'!I19 -> 0.22406928

Sheet Model
B1: Summary Year Then Month | E1: ='Input Assumptions'!E$18 -> 1 | F1: ='Input Assumptions'!F$18 -> 2 | G1: ='Input Assumptions'!G$18 -> 3 | H1: ='Input Assumptions'!H$18 -> 4 | I1: ='Input Assumptions'!I$18 -> 5 | K1: 1 | L1: =K1+1 -> 2 | M1: =L1+1 -> 3 | N1: =M1+1 -> 4 | O1: =N1+1 -> 5 | P1: =O1+1 -> 6 | Q1: =P1+1 -> 7 | R1: =Q1+1 -> 8 | S1: =R1+1 -> 9 | ... BR1: =BQ1+1 -> 60
B2: Year | K2: =IF(K$13<Fin_Year_End,1,IF(MONTH(K$13)=MONTH(Fin_Year_End)+1,MIN(J2+1,5),J2)) -> 1 | L2: =IF(L$13<Fin_Year_End,1,IF(MONTH(L$13)=MONTH(Fin_Year_End)+1,MIN(K2+1,5),K2)) -> 1 | M2: =IF(M$13<Fin_Year_End,1,IF(MONTH(M$13)=MONTH(Fin_Year_End)+1,MIN(L2+1,5),L2)) -> 1 | N2: =IF(N$13<Fin_Year_End,1,IF(MONTH(N$13)=MONTH(Fin_Year_End)+1,MIN(M2+1,5),M2)) -> 1 | O2: =IF(O$13<Fin_Year_End,1,IF(MONTH(O$13)=MONTH(Fin_Year_End)+1,MIN(N2+1,5),N2)) -> 1 | P2: =IF(P$13<Fin_Year_End,1,IF(MONTH(P$13)=MONTH(Fin_Year_End)+1,MIN(O2+1,5),O2)) -> 1 | Q2: =IF(Q$13<Fin_Year_End,1,IF(MONTH(Q$13)=MONTH(Fin_Year_End)+1,MIN(P2+1,5),P2)) -> 1 | R2: =IF(R$13<Fin_Year_End,1,IF(MONTH(R$13)=MONTH(Fin_Year_End)+1,MIN(Q2+1,5),Q2)) -> 1 | ... BR2: =IF(BR$13<Fin_Year_End,1,IF(MONTH(BR$13)=MONTH(Fin_Year_End)+1,MIN(BQ2+1,5),BQ2)) -> 5
B3: Until AUV Reached | J3: =AUV_Reached -> 18 | K3: =MAX(0,J$3-1) -> 17 | L3: =MAX(0,K$3-1) -> 16 | M3: =MAX(0,L$3-1) -> 15 | N3: =MAX(0,M$3-1) -> 14 | O3: =MAX(0,N$3-1) -> 13 | P3: =MAX(0,O$3-1) -> 12 | Q3: =MAX(0,P$3-1) -> 11 | R3: =MAX(0,Q$3-1) -> 10 | ... BR3: =MAX(0,BQ$3-1) -> 0
B4: Until AUV Reached | J4: =AUV_Start -> 0.3 | K4: =IFERROR(IF(AND(COLUMN()=11,$J$4<>0),$J4,IF($J$4<>0,$J$4+(((1-$J$4)*(AUV_Reached-K$3))/AUV_Reached),(AUV_Reached-K$3)/AUV_Reached)),0) -> 0.3 | L4: =IFERROR(IF(AND(COLUMN()=11,$J$4<>0),$J4,IF($J$4<>0,$J$4+(((1-$J$4)*(AUV_Reached-L$3))/AUV_Reached),(AUV_Reached-L$3)/AUV_Reached)),0) -> 0.37777778 | M4: =IFERROR(IF(AND(COLUMN()=11,$J$4<>0),$J4,IF($J$4<>0,$J$4+(((1-$J$4)*(AUV_Reached-M$3))/AUV_Reached),(AUV_Reached-M$3)/AUV_Reached)),0) -> 0.41666667 | N4: =IFERROR(IF(AND(COLUMN()=11,$J$4<>0),$J4,IF($J$4<>0,$J$4+(((1-$J$4)*(AUV_Reached-N$3))/AUV_Reached),(AUV_Reached-N$3)/AUV_Reached)),0) -> 0.45555556 | O4: =IFERROR(IF(AND(COLUMN()=11,$J$4<>0),$J4,IF($J$4<>0,$J$4+(((1-$J$4)*(AUV_Reached-O$3))/AUV_Reached),(AUV_Reached-O$3)/AUV_Reached)),0) -> 0.49444444 | P4: =IFERROR(IF(AND(COLUMN()=11,$J$4<>0),$J4,IF($J$4<>0,$J$4+(((1-$J$4)*(AUV_Reached-P$3))/AUV_Reached),(AUV_Reached-P$3)/AUV_Reached)),0) -> 0.53333333 | Q4: =IFERROR(IF(AND(COLUMN()=11,$J$4<>0),$J4,IF($J$4<>0,$J$4+(((1-$J$4)*(AUV_Reached-Q$3))/AUV_Reached),(AUV_Reached-Q$3)/AUV_Reached)),0) -> 0.57222222 | R4: =IFERROR(IF(AND(COLUMN()=11,$J$4<>0),$J4,IF($J$4<>0,$J$4+(((1-$J$4)*(AUV_Reached-R$3))/AUV_Reached),(AUV_Reached-R$3)/AUV_Reached)),0) -> 0.61111111 | ... BR4: =IFERROR(IF(AND(COLUMN()=11,$J$4<>0),$J4,IF($J$4<>0,$J$4+(((1-$J$4)*(AUV_Reached-BR$3))/AUV_Reached),(AUV_Reached-BR$3)/AUV_Reached)),0) -> 1
B5: Growth Rate | K5: {=INDEX(Growth_Rate,K$2)} -> 0.13 | L5: {=INDEX(Growth_Rate,L$2)} -> 0.13 | M5: {=INDEX(Growth_Rate,M$2)} -> 0.13 | N5: {=INDEX(Growth_Rate,N$2)} -> 0.13 | O5: {=INDEX(Growth_Rate,O$2)} -> 0.13 | P5: {=INDEX(Growth_Rate,P$2)} -> 0.13 | Q5: {=INDEX(Growth_Rate,Q$2)} -> 0.13 | R5: {=INDEX(Growth_Rate,R$2)} -> 0.13 | ... BR5: {=INDEX(Growth_Rate,BR$2)} -> 0.08
B6: End of Month | K6: =EOMONTH(Start_Date,0) -> 45535 | L6: =EOMONTH(K6,1) -> 45565 | M6: =EOMONTH(L6,1) -> 45596 | N6: =EOMONTH(M6,1) -> 45626 | O6: =EOMONTH(N6,1) -> 45657 | P6: =EOMONTH(O6,1) -> 45688 | Q6: =EOMONTH(P6,1) -> 45716 | R6: =EOMONTH(Q6,1) -> 45747 | S6: =EOMONTH(R6,1) -> 45777 | ... BR6: =EOMONTH(BQ6,1) -> 47330
B7: End of Financial Year | K7: =IF(MONTH(K$13)=MONTH(Fin_Year_End),1,0) -> 0 | L7: =IF(MONTH(L$13)=MONTH(Fin_Year_End),1,0) -> 0 | M7: =IF(MONTH(M$13)=MONTH(Fin_Year_End),1,0) -> 0 | N7: =IF(MONTH(N$13)=MONTH(Fin_Year_End),1,0) -> 0 | O7: =IF(MONTH(O$13)=MONTH(Fin_Year_End),1,0) -> 0 | P7: =IF(MONTH(P$13)=MONTH(Fin_Year_End),1,0) -> 0 | Q7: =IF(MONTH(Q$13)=MONTH(Fin_Year_End),1,0) -> 0 | R7: =IF(MONTH(R$13)=MONTH(Fin_Year_End),1,0) -> 0 | ... BR7: =IF(MONTH(BR$13)=MONTH(Fin_Year_End),1,0) -> 1
B8: Corporation Tax Payment Month | K8: =IF(AND(OFFSET(K7,0,-Corp_Tax_Pay_Lag)=1,OFFSET(K6,0,-Corp_Tax_Pay_Lag)=EOMONTH(K6,-Corp_Tax_Pay_Lag)),1,0) -> 0 | L8: =IF(AND(OFFSET(L7,0,-Corp_Tax_Pay_Lag)=1,OFFSET(L6,0,-Corp_Tax_Pay_Lag)=EOMONTH(L6,-Corp_Tax_Pay_Lag)),1,0) -> 0 | M8: =IF(AND(OFFSET(M7,0,-Corp_Tax_Pay_Lag)=1,OFFSET(M6,0,-Corp_Tax_Pay_Lag)=EOMONTH(M6,-Corp_Tax_Pay_Lag)),1,0) -> 0 | N8: =IF(AND(OFFSET(N7,0,-Corp_Tax_Pay_Lag)=1,OFFSET(N6,0,-Corp_Tax_Pay_Lag)=EOMONTH(N6,-Corp_Tax_Pay_Lag)),1,0) -> 0 | O8: =IF(AND(OFFSET(O7,0,-Corp_Tax_Pay_Lag)=1,OFFSET(O6,0,-Corp_Tax_Pay_Lag)=EOMONTH(O6,-Corp_Tax_Pay_Lag)),1,0) -> 0 | P8: =IF(AND(OFFSET(P7,0,-Corp_Tax_Pay_Lag)=1,OFFSET(P6,0,-Corp_Tax_Pay_Lag)=EOMONTH(P6,-Corp_Tax_Pay_Lag)),1,0) -> 0 | Q8: =IF(AND(OFFSET(Q7,0,-Corp_Tax_Pay_Lag)=1,OFFSET(Q6,0,-Corp_Tax_Pay_Lag)=EOMONTH(Q6,-Corp_Tax_Pay_Lag)),1,0) -> 0 | R8: =IF(AND(OFFSET(R7,0,-Corp_Tax_Pay_Lag)=1,OFFSET(R6,0,-Corp_Tax_Pay_Lag)=EOMONTH(R6,-Corp_Tax_Pay_Lag)),1,0) -> 0 | ... BR8: =IF(AND(OFFSET(BR7,0,-Corp_Tax_Pay_Lag)=1,OFFSET(BR6,0,-Corp_Tax_Pay_Lag)=EOMONTH(BR6,-Corp_Tax_Pay_Lag)),1,0) -> 0
B9: Click Hyperlink to Navigate
B10: Profit & Loss
B11: Balance Sheet | C11: Working Capital | D11: Breakeven | E11: =Curr_USD -> $ USD | F11: =Curr_USD -> $ USD | G11: =Curr_USD -> $ USD | H11: =Curr_USD -> $ USD | I11: =Curr_USD -> $ USD | K11: =Curr_USD -> $ USD | L11: =Curr_USD -> $ USD | M11: =Curr_USD -> $ USD | N11: =Curr_USD -> $ USD | O11: =Curr_USD -> $ USD | P11: =Curr_USD -> $ USD | Q11: =Curr_USD -> $ USD | R11: =Curr_USD -> $ USD | ... BR11: =Curr_USD -> $ USD
B12: Cash Flow | C12: Debt | D12: ROI | E12: ='Input Assumptions'!E19 -> Year 1 | F12: ='Input Assumptions'!F19 -> Year 2 | G12: ='Input Assumptions'!G19 -> Year 3 | H12: ='Input Assumptions'!H19 -> Year 4 | I12: ='Input Assumptions'!I19 -> Year 5 | K12: =YEAR(K$13) -> 2024 | L12: =YEAR(L$13) -> 2024 | M12: =YEAR(M$13) -> 2024 | N12: =YEAR(N$13) -> 2024 | O12: =YEAR(O$13) -> 2024 | P12: =YEAR(P$13) -> 2025 | Q12: =YEAR(Q$13) -> 2025 | R12: =YEAR(R$13) -> 2025 | ... BR12: =YEAR(BR$13) -> 2029
B13: Corporation Tax | C13: Capex | D13: Valuation | E13: ='Input Assumptions'!E17 -> 2024-2025 | F13: ='Input Assumptions'!F17 -> 2025-2026 | G13: ='Input Assumptions'!G17 -> 2026-2027 | H13: ='Input Assumptions'!H17 -> 2027-2028 | I13: ='Input Assumptions'!I17 -> 2028-2029 | K13: =EOMONTH(Start_Date,-1)+1 -> 45505 | L13: =EOMONTH(K13,0)+1 -> 45536 | M13: =EOMONTH(L13,0)+1 -> 45566 | N13: =EOMONTH(M13,0)+1 -> 45597 | O13: =EOMONTH(N13,0)+1 -> 45627 | P13: =EOMONTH(O13,0)+1 -> 45658 | Q13: =EOMONTH(P13,0)+1 -> 45689 | R13: =EOMONTH(Q13,0)+1 -> 45717 | S13: =EOMONTH(R13,0)+1 -> 45748 | ... BR13: =EOMONTH(BQ13,0)+1 -> 47300
B15: Profit & Loss
B17: Ramp-Up / Forecast | K17: =IF(K$13<EOMONTH(Start_Date,AUV_Reached-1)+1,Ramp_up_to_AUV_Nm,Growth_Rate_Nm) -> Ramp up to AUV | L17: =IF(L$13<EOMONTH(Start_Date,AUV_Reached-1)+1,Ramp_up_to_AUV_Nm,Growth_Rate_Nm) -> Ramp up to AUV | M17: =IF(M$13<EOMONTH(Start_Date,AUV_Reached-1)+1,Ramp_up_to_AUV_Nm,Growth_Rate_Nm) -> Ramp up to AUV | N17: =IF(N$13<EOMONTH(Start_Date,AUV_Reached-1)+1,Ramp_up_to_AUV_Nm,Growth_Rate_Nm) -> Ramp up to AUV | O17: =IF(O$13<EOMONTH(Start_Date,AUV_Reached-1)+1,Ramp_up_to_AUV_Nm,Growth_Rate_Nm) -> Ramp up to AUV | P17: =IF(P$13<EOMONTH(Start_Date,AUV_Reached-1)+1,Ramp_up_to_AUV_Nm,Growth_Rate_Nm) -> Ramp up to AUV | Q17: =IF(Q$13<EOMONTH(Start_Date,AUV_Reached-1)+1,Ramp_up_to_AUV_Nm,Growth_Rate_Nm) -> Ramp up to AUV | R17: =IF(R$13<EOMONTH(Start_Date,AUV_Reached-1)+1,Ramp_up_to_AUV_Nm,Growth_Rate_Nm) -> Ramp up to AUV | ... BR17: =IF(BR$13<EOMONTH(Start_Date,AUV_Reached-1)+1,Ramp_up_to_AUV_Nm,Growth_Rate_Nm) -> Growth Rate
B19: Ramp up to AUV
B21: Ramp up to AUV / Growth Rate | K21: =IF(K$17=Ramp_up_to_AUV_Nm,K$4,K$5) -> 0.3 | L21: =IF(L$17=Ramp_up_to_AUV_Nm,L$4,L$5) -> 0.37777778 | M21: =IF(M$17=Ramp_up_to_AUV_Nm,M$4,M$5) -> 0.41666667 | N21: =IF(N$17=Ramp_up_to_AUV_Nm,N$4,N$5) -> 0.45555556 | O21: =IF(O$17=Ramp_up_to_AUV_Nm,O$4,O$5) -> 0.49444444 | P21: =IF(P$17=Ramp_up_to_AUV_Nm,P$4,P$5) -> 0.53333333 | Q21: =IF(Q$17=Ramp_up_to_AUV_Nm,Q$4,Q$5) -> 0.57222222 | R21: =IF(R$17=Ramp_up_to_AUV_Nm,R$4,R$5) -> 0.61111111 | ... BR21: =IF(BR$17=Ramp_up_to_AUV_Nm,BR$4,BR$5) -> 0.08
B22: Average Annual Sales | K22: =K23*12 -> 158098.2 | L22: =L23*12 -> 199086.62 | M22: =M23*12 -> 219580.83 | N22: =N23*12 -> 240075.04 | O22: =O23*12 -> 260569.26 | P22: =P23*12 -> 281063.47 | Q22: =Q23*12 -> 301557.68 | R22: =R23*12 -> 322051.89 | ... BR22: =BR23*12 -> 728431.99
B23: Revenue | E23: =SUMIFS($K$23:$BR$23,$K$2:$BR$2,E$1) -> 289602.72 | F23: =SUMIFS($K$23:$BR$23,$K$2:$BR$2,F$1) -> 511549.52 | G23: =SUMIFS($K$23:$BR$23,$K$2:$BR$2,G$1) -> 593591.95 | H23: =SUMIFS($K$23:$BR$23,$K$2:$BR$2,H$1) -> 648639.97 | I23: =SUMIFS($K$23:$BR$23,$K$2:$BR$2,I$1) -> 702476.76 | K23: =IF(K$17=Ramp_up_to_AUV_Nm,(K$21*Gross_Sales)/12,Gross_Sales/12*(1+(K$21/12))) -> 13174.85 | L23: =IF(L$17=Ramp_up_to_AUV_Nm,(L$21*Gross_Sales)/12,K$23*(1+(L$21/12))) -> 16590.552 | M23: =IF(M$17=Ramp_up_to_AUV_Nm,(M$21*Gross_Sales)/12,L$23*(1+(M$21/12))) -> 18298.403 | N23: =IF(N$17=Ramp_up_to_AUV_Nm,(N$21*Gross_Sales)/12,M$23*(1+(N$21/12))) -> 20006.254 | O23: =IF(O$17=Ramp_up_to_AUV_Nm,(O$21*Gross_Sales)/12,N$23*(1+(O$21/12))) -> 21714.105 | P23: =IF(P$17=Ramp_up_to_AUV_Nm,(P$21*Gross_Sales)/12,O$23*(1+(P$21/12))) -> 23421.956 | Q23: =IF(Q$17=Ramp_up_to_AUV_Nm,(Q$21*Gross_Sales)/12,P$23*(1+(Q$21/12))) -> 25129.806 | R23: =IF(R$17=Ramp_up_to_AUV_Nm,(R$21*Gross_Sales)/12,Q$23*(1+(R$21/12))) -> 26837.657 | S23: =IF(S$17=Ramp_up_to_AUV_Nm,(S$21*Gross_Sales)/12,R$23*(1+(S$21/12))) -> 28545.508 | ... BR23: =IF(BR$17=Ramp_up_to_AUV_Nm,(BR$21*Gross_Sales)/12,BQ$23*(1+(BR$21/12))) -> 60702.666
B24: Average Growth Rate | E24: =AVERAGEIFS($K24:$BR24,$K$2:$BR$2,E$1)*12 -> 0.54953704 | F24: =AVERAGEIFS($K24:$BR24,$K$2:$BR$2,F$1)*12 -> 0.51638889 | G24: =AVERAGEIFS($K24:$BR24,$K$2:$BR$2,G$1)*12 -> 0.1 | H24: =AVERAGEIFS($K24:$BR24,$K$2:$BR$2,H$1)*12 -> 0.08 | I24: =AVERAGEIFS($K24:$BR24,$K$2:$BR$2,I$1)*12 -> 0.08 | K24: =K21/12 -> 0.025 | L24: =L21/12 -> 0.031481481 | M24: =M21/12 -> 0.034722222 | N24: =N21/12 -> 0.037962963 | O24: =O21/12 -> 0.041203704 | P24: =P21/12 -> 0.044444444 | Q24: =Q21/12 -> 0.047685185 | R24: =R21/12 -> 0.050925926 | ... BR24: =BR21/12 -> 0.0066666667
B26: Revenue | E26: =E23 -> 289602.72 | F26: =F23 -> 511549.52 | G26: =G23 -> 593591.95 | H26: =H23 -> 648639.97 | I26: =I23 -> 702476.76 | K26: =K23 -> 13174.85 | L26: =L23 -> 16590.552 | M26: =M23 -> 18298.403 | N26: =N23 -> 20006.254 | O26: =O23 -> 21714.105 | P26: =P23 -> 23421.956 | Q26: =Q23 -> 25129.806 | R26: =R23 -> 26837.657 | ... BR26: =BR23 -> 60702.666
B28: Royalties (as % of revenue) | E28: =AVERAGEIFS($K28:$BR28,$K$2:$BR$2,E$1) -> 0.07 | F28: =AVERAGEIFS($K28:$BR28,$K$2:$BR$2,F$1) -> 0.07 | G28: =AVERAGEIFS($K28:$BR28,$K$2:$BR$2,G$1) -> 0.07 | H28: =AVERAGEIFS($K28:$BR28,$K$2:$BR$2,H$1) -> 0.07 | I28: =AVERAGEIFS($K28:$BR28,$K$2:$BR$2,I$1) -> 0.07 | K28: {=INDEX(Royalty_Fee,K$2)} -> 0.07 | L28: {=INDEX(Royalty_Fee,L$2)} -> 0.07 | M28: {=INDEX(Royalty_Fee,M$2)} -> 0.07 | N28: {=INDEX(Royalty_Fee,N$2)} -> 0.07 | O28: {=INDEX(Royalty_Fee,O$2)} -> 0.07 | P28: {=INDEX(Royalty_Fee,P$2)} -> 0.07 | Q28: {=INDEX(Royalty_Fee,Q$2)} -> 0.07 | R28: {=INDEX(Royalty_Fee,R$2)} -> 0.07 | ... BR28: {=INDEX(Royalty_Fee,BR$2)} -> 0.07
B29: Royalties | E29: =SUMIFS($K29:$BR29,$K$2:$BR$2,E$1) -> -20272.19 | F29: =SUMIFS($K29:$BR29,$K$2:$BR$2,F$1) -> -35808.467 | G29: =SUMIFS($K29:$BR29,$K$2:$BR$2,G$1) -> -41551.437 | H29: =SUMIFS($K29:$BR29,$K$2:$BR$2,H$1) -> -45404.798 | I29: =SUMIFS($K29:$BR29,$K$2:$BR$2,I$1) -> -49173.373 | K29: =-K28*K$26 -> -922.2395 | L29: =-L28*L$26 -> -1161.3386 | M29: =-M28*M$26 -> -1280.8882 | N29: =-N28*N$26 -> -1400.4378 | O29: =-O28*O$26 -> -1519.9873 | P29: =-P28*P$26 -> -1639.5369 | Q29: =-Q28*Q$26 -> -1759.0865 | R29: =-R28*R$26 -> -1878.636 | ... BR29: =-BR28*BR$26 -> -4249.1866
B31: Ad Fund / Brand Fund (as % of revenue) | E31: =AVERAGEIFS($K31:$BR31,$K$2:$BR$2,E$1) -> 0 | F31: =AVERAGEIFS($K31:$BR31,$K$2:$BR$2,F$1) -> 0 | G31: =AVERAGEIFS($K31:$BR31,$K$2:$BR$2,G$1) -> 0 | H31: =AVERAGEIFS($K31:$BR31,$K$2:$BR$2,H$1) -> 0 | I31: =AVERAGEIFS($K31:$BR31,$K$2:$BR$2,I$1) -> 0 | K31: {=INDEX(Marketing_Fee,K$2)} -> 0 | L31: {=INDEX(Marketing_Fee,L$2)} -> 0 | M31: {=INDEX(Marketing_Fee,M$2)} -> 0 | N31: {=INDEX(Marketing_Fee,N$2)} -> 0 | O31: {=INDEX(Marketing_Fee,O$2)} -> 0 | P31: {=INDEX(Marketing_Fee,P$2)} -> 0 | Q31: {=INDEX(Marketing_Fee,Q$2)} -> 0 | R31: {=INDEX(Marketing_Fee,R$2)} -> 0 | ... BR31: {=INDEX(Marketing_Fee,BR$2)} -> 0
B32: Ad Fund / Brand Fund | E32: =SUMIFS($K32:$BR32,$K$2:$BR$2,E$1) -> 0 | F32: =SUMIFS($K32:$BR32,$K$2:$BR$2,F$1) -> 0 | G32: =SUMIFS($K32:$BR32,$K$2:$BR$2,G$1) -> 0 | H32: =SUMIFS($K32:$BR32,$K$2:$BR$2,H$1) -> 0 | I32: =SUMIFS($K32:$BR32,$K$2:$BR$2,I$1) -> 0 | K32: =-K31*K$26 -> 0 | L32: =-L31*L$26 -> 0 | M32: =-M31*M$26 -> 0 | N32: =-N31*N$26 -> 0 | O32: =-O31*O$26 -> 0 | P32: =-P31*P$26 -> 0 | Q32: =-Q31*Q$26 -> 0 | R32: =-R31*R$26 -> 0 | ... BR32: =-BR31*BR$26 -> 0
B34: Materials (as % of revenue) | E34: {=INDEX(Materials_COGs,E$1)} -> 0.32 | F34: {=INDEX(Materials_COGs,F$1)} -> 0.32 | G34: {=INDEX(Materials_COGs,G$1)} -> 0.32 | H34: {=INDEX(Materials_COGs,H$1)} -> 0.32 | I34: {=INDEX(Materials_COGs,I$1)} -> 0.32 | K34: {=INDEX(Materials_COGs,K$2)} -> 0.32 | L34: {=INDEX(Materials_COGs,L$2)} -> 0.32 | M34: {=INDEX(Materials_COGs,M$2)} -> 0.32 | N34: {=INDEX(Materials_COGs,N$2)} -> 0.32 | O34: {=INDEX(Materials_COGs,O$2)} -> 0.32 | P34: {=INDEX(Materials_COGs,P$2)} -> 0.32 | Q34: {=INDEX(Materials_COGs,Q$2)} -> 0.32 | R34: {=INDEX(Materials_COGs,R$2)} -> 0.32 | ... BR34: {=INDEX(Materials_COGs,BR$2)} -> 0.32
B35: Materials | E35: =SUMIFS($K35:$BR35,$K$2:$BR$2,E$1) -> -92672.871 | F35: =SUMIFS($K35:$BR35,$K$2:$BR$2,F$1) -> -163695.85 | G35: =SUMIFS($K35:$BR35,$K$2:$BR$2,G$1) -> -189949.43 | H35: =SUMIFS($K35:$BR35,$K$2:$BR$2,H$1) -> -207564.79 | I35: =SUMIFS($K35:$BR35,$K$2:$BR$2,I$1) -> -224792.56 | K35: =-K34*K$26 -> -4215.952 | L35: =-L34*L$26 -> -5308.9766 | M35: =-M34*M$26 -> -5855.4889 | N35: =-N34*N$26 -> -6402.0012 | O35: =-O34*O$26 -> -6948.5135 | P35: =-P34*P$26 -> -7495.0258 | Q35: =-Q34*Q$26 -> -8041.5381 | R35: =-R34*R$26 -> -8588.0504 | ... BR35: =-BR34*BR$26 -> -19424.853
B37: Gross Profit as % of Revenue | E37: =AVERAGEIFS($K37:$BR37,$K$2:$BR$2,E$1) -> 0.61 | F37: =AVERAGEIFS($K37:$BR37,$K$2:$BR$2,F$1) -> 0.61 | G37: =AVERAGEIFS($K37:$BR37,$K$2:$BR$2,G$1) -> 0.61 | H37: =AVERAGEIFS($K37:$BR37,$K$2:$BR$2,H$1) -> 0.61 | I37: =AVERAGEIFS($K37:$BR37,$K$2:$BR$2,I$1) -> 0.61 | K37: =IFERROR(K38/K26,0) -> 0.61 | L37: =IFERROR(L38/L26,0) -> 0.61 | M37: =IFERROR(M38/M26,0) -> 0.61 | N37: =IFERROR(N38/N26,0) -> 0.61 | O37: =IFERROR(O38/O26,0) -> 0.61 | P37: =IFERROR(P38/P26,0) -> 0.61 | Q37: =IFERROR(Q38/Q26,0) -> 0.61 | R37: =IFERROR(R38/R26,0) -> 0.61 | ... BR37: =IFERROR(BR38/BR26,0) -> 0.61
B38: Gross Profit | E38: =SUMIFS($K38:$BR38,$K$2:$BR$2,E$1) -> 176657.66 | F38: =SUMIFS($K38:$BR38,$K$2:$BR$2,F$1) -> 312045.21 | G38: =SUMIFS($K38:$BR38,$K$2:$BR$2,G$1) -> 362091.09 | H38: =SUMIFS($K38:$BR38,$K$2:$BR$2,H$1) -> 395670.38 | I38: =SUMIFS($K38:$BR38,$K$2:$BR$2,I$1) -> 428510.83 | K38: =K26+K29+K32+K35 -> 8036.6585 | L38: =L26+L29+L32+L35 -> 10120.237 | M38: =M26+M29+M32+M35 -> 11162.026 | N38: =N26+N29+N32+N35 -> 12203.815 | O38: =O26+O29+O32+O35 -> 13245.604 | P38: =P26+P29+P32+P35 -> 14287.393 | Q38: =Q26+Q29+Q32+Q35 -> 15329.182 | R38: =R26+R29+R32+R35 -> 16370.971 | ... BR38: =BR26+BR29+BR32+BR35 -> 37028.626
B41: Direct Labor (as % of revenue) | E41: {=INDEX(Direct_Labor_Cost,E$1)} -> 0.15 | F41: {=INDEX(Direct_Labor_Cost,F$1)} -> 0.15 | G41: {=INDEX(Direct_Labor_Cost,G$1)} -> 0.15 | H41: {=INDEX(Direct_Labor_Cost,H$1)} -> 0.15 | I41: {=INDEX(Direct_Labor_Cost,I$1)} -> 0.15 | K41: {=INDEX(Direct_Labor_Cost,K$2)} -> 0.15 | L41: {=INDEX(Direct_Labor_Cost,L$2)} -> 0.15 | M41: {=INDEX(Direct_Labor_Cost,M$2)} -> 0.15 | N41: {=INDEX(Direct_Labor_Cost,N$2)} -> 0.15 | O41: {=INDEX(Direct_Labor_Cost,O$2)} -> 0.15 | P41: {=INDEX(Direct_Labor_Cost,P$2)} -> 0.15 | Q41: {=INDEX(Direct_Labor_Cost,Q$2)} -> 0.15 | R41: {=INDEX(Direct_Labor_Cost,R$2)} -> 0.15 | ... BR41: {=INDEX(Direct_Labor_Cost,BR$2)} -> 0.15
B42: Direct Labor | E42: =SUMIFS($K42:$BR42,$K$2:$BR$2,E$1) -> -43440.408 | F42: =SUMIFS($K42:$BR42,$K$2:$BR$2,F$1) -> -76732.428 | G42: =SUMIFS($K42:$BR42,$K$2:$BR$2,G$1) -> -89038.793 | H42: =SUMIFS($K42:$BR42,$K$2:$BR$2,H$1) -> -97295.995 | I42: =SUMIFS($K42:$BR42,$K$2:$BR$2,I$1) -> -105371.51 | K42: =-(K41*K$26) -> -1976.2275 | L42: =-(L41*L$26) -> -2488.5828 | M42: =-(M41*M$26) -> -2744.7604 | N42: =-(N41*N$26) -> -3000.9381 | O42: =-(O41*O$26) -> -3257.1157 | P42: =-(P41*P$26) -> -3513.2933 | Q42: =-(Q41*Q$26) -> -3769.471 | R42: =-(R41*R$26) -> -4025.6486 | ... BR42: =-(BR41*BR$26) -> -9105.3998
B44: Contribution Margin | E44: =SUMIFS($K44:$BR44,$K$2:$BR$2,E$1) -> 133217.25 | F44: =SUMIFS($K44:$BR44,$K$2:$BR$2,F$1) -> 235312.78 | G44: =SUMIFS($K44:$BR44,$K$2:$BR$2,G$1) -> 273052.3 | H44: =SUMIFS($K44:$BR44,$K$2:$BR$2,H$1) -> 298374.38 | I44: =SUMIFS($K44:$BR44,$K$2:$BR$2,I$1) -> 323139.31 | K44: =K$26+K$29+K$32+K$35+K$42 -> 6060.431 | L44: =L$26+L$29+L$32+L$35+L$42 -> 7631.6539 | M44: =M$26+M$29+M$32+M$35+M$42 -> 8417.2653 | N44: =N$26+N$29+N$32+N$35+N$42 -> 9202.8767 | O44: =O$26+O$29+O$32+O$35+O$42 -> 9988.4881 | P44: =P$26+P$29+P$32+P$35+P$42 -> 10774.1 | Q44: =Q$26+Q$29+Q$32+Q$35+Q$42 -> 11559.711 | R44: =R$26+R$29+R$32+R$35+R$42 -> 12345.322 | ... BR44: =BR$26+BR$29+BR$32+BR$35+BR$42 -> 27923.226
B45: As % of GP | E45: =IFERROR(E44/E$26,0) -> 0.46 | F45: =IFERROR(F44/F$26,0) -> 0.46 | G45: =IFERROR(G44/G$26,0) -> 0.46 | H45: =IFERROR(H44/H$26,0) -> 0.46 | I45: =IFERROR(I44/I$26,0) -> 0.46 | K45: =IFERROR(K44/K$26,0) -> 0.46 | L45: =IFERROR(L44/L$26,0) -> 0.46 | M45: =IFERROR(M44/M$26,0) -> 0.46 | N45: =IFERROR(N44/N$26,0) -> 0.46 | O45: =IFERROR(O44/O$26,0) -> 0.46 | P45: =IFERROR(P44/P$26,0) -> 0.46 | Q45: =IFERROR(Q44/Q$26,0) -> 0.46 | R45: =IFERROR(R44/R$26,0) -> 0.46 | ... BR45: =IFERROR(BR44/BR$26,0) -> 0.46
B47: Operating Expenses
B48: Labor - (Management and Admin) | E48: =SUMIFS($K48:$BR48,$K$2:$BR$2,E$1) -> 0 | F48: =SUMIFS($K48:$BR48,$K$2:$BR$2,F$1) -> -78437.593 | G48: =SUMIFS($K48:$BR48,$K$2:$BR$2,G$1) -> -91017.433 | H48: =SUMIFS($K48:$BR48,$K$2:$BR$2,H$1) -> -99458.128 | I48: =SUMIFS($K48:$BR48,$K$2:$BR$2,I$1) -> -107713.1 | K48: {=-IFERROR(INDEX(Management_Salaries,K$2)/12,0)} -> 0 | L48: {=-IFERROR(INDEX(Management_Salaries,L$2)/12,0)} -> 0 | M48: {=-IFERROR(INDEX(Management_Salaries,M$2)/12,0)} -> 0 | N48: {=-IFERROR(INDEX(Management_Salaries,N$2)/12,0)} -> 0 | O48: {=-IFERROR(INDEX(Management_Salaries,O$2)/12,0)} -> 0 | P48: {=-IFERROR(INDEX(Management_Salaries,P$2)/12,0)} -> 0 | Q48: {=-IFERROR(INDEX(Management_Salaries,Q$2)/12,0)} -> 0 | R48: {=-IFERROR(INDEX(Management_Salaries,R$2)/12,0)} -> 0 | ... BR48: {=-IFERROR(INDEX(Management_Salaries,BR$2)/12,0)} -> -8976.092
B49: Payroll Taxes & Benefits - % | E49: {=INDEX(Payroll_Tax,E$1)} -> 0.2 | F49: {=INDEX(Payroll_Tax,F$1)} -> 0.2 | G49: {=INDEX(Payroll_Tax,G$1)} -> 0.2 | H49: {=INDEX(Payroll_Tax,H$1)} -> 0.2 | I49: {=INDEX(Payroll_Tax,I$1)} -> 0.2 | K49: {=INDEX(Payroll_Tax,K$2)} -> 0.2 | L49: {=INDEX(Payroll_Tax,L$2)} -> 0.2 | M49: {=INDEX(Payroll_Tax,M$2)} -> 0.2 | N49: {=INDEX(Payroll_Tax,N$2)} -> 0.2 | O49: {=INDEX(Payroll_Tax,O$2)} -> 0.2 | P49: {=INDEX(Payroll_Tax,P$2)} -> 0.2 | Q49: {=INDEX(Payroll_Tax,Q$2)} -> 0.2 | R49: {=INDEX(Payroll_Tax,R$2)} -> 0.2 | ... BR49: {=INDEX(Payroll_Tax,BR$2)} -> 0.2
B50: Payroll Taxes & Benefits | E50: =SUMIFS($K50:$BR50,$K$2:$BR$2,E$1) -> -8688.0816 | F50: =SUMIFS($K50:$BR50,$K$2:$BR$2,F$1) -> -31034.004 | G50: =SUMIFS($K50:$BR50,$K$2:$BR$2,G$1) -> -36011.245 | H50: =SUMIFS($K50:$BR50,$K$2:$BR$2,H$1) -> -39350.825 | I50: =SUMIFS($K50:$BR50,$K$2:$BR$2,I$1) -> -42616.924 | K50: =(K48+K42)*K49 -> -395.2455 | L50: =(L48+L42)*L49 -> -497.71656 | M50: =(M48+M42)*M49 -> -548.95208 | N50: =(N48+N42)*N49 -> -600.18761 | O50: =(O48+O42)*O49 -> -651.42314 | P50: =(P48+P42)*P49 -> -702.65867 | Q50: =(Q48+Q42)*Q49 -> -753.89419 | R50: =(R48+R42)*R49 -> -805.12972 | ... BR50: =(BR48+BR42)*BR49 -> -3616.2984
B51: Labor - (Management and Admin) + Payroll Benefits | E51: =SUMIFS($K51:$BR51,$K$2:$BR$2,E$1) -> -8688.0816 | F51: =SUMIFS($K51:$BR51,$K$2:$BR$2,F$1) -> -109471.6 | G51: =SUMIFS($K51:$BR51,$K$2:$BR$2,G$1) -> -127028.68 | H51: =SUMIFS($K51:$BR51,$K$2:$BR$2,H$1) -> -138808.95 | I51: =SUMIFS($K51:$BR51,$K$2:$BR$2,I$1) -> -150330.03 | K51: =K48+K50 -> -395.2455 | L51: =L48+L50 -> -497.71656 | M51: =M48+M50 -> -548.95208 | N51: =N48+N50 -> -600.18761 | O51: =O48+O50 -> -651.42314 | P51: =P48+P50 -> -702.65867 | Q51: =Q48+Q50 -> -753.89419 | R51: =R48+R50 -> -805.12972 | ... BR51: =BR48+BR50 -> -12592.39
B53: Facilities | E53: =SUMIFS($K53:$BR53,$K$2:$BR$2,E$1) -> -40000 | F53: =SUMIFS($K53:$BR53,$K$2:$BR$2,F$1) -> -41200 | G53: =SUMIFS($K53:$BR53,$K$2:$BR$2,G$1) -> -42436 | H53: =SUMIFS($K53:$BR53,$K$2:$BR$2,H$1) -> -43709.08 | I53: =SUMIFS($K53:$BR53,$K$2:$BR$2,I$1) -> -45020.352 | K53: {=-IFERROR(INDEX(Facilities,K$2)/12,0)} -> -3333.3333 | L53: {=-IFERROR(INDEX(Facilities,L$2)/12,0)} -> -3333.3333 | M53: {=-IFERROR(INDEX(Facilities,M$2)/12,0)} -> -3333.3333 | N53: {=-IFERROR(INDEX(Facilities,N$2)/12,0)} -> -3333.3333 | O53: {=-IFERROR(INDEX(Facilities,O$2)/12,0)} -> -3333.3333 | P53: {=-IFERROR(INDEX(Facilities,P$2)/12,0)} -> -3333.3333 | Q53: {=-IFERROR(INDEX(Facilities,Q$2)/12,0)} -> -3333.3333 | R53: {=-IFERROR(INDEX(Facilities,R$2)/12,0)} -> -3333.3333 | ... BR53: {=-IFERROR(INDEX(Facilities,BR$2)/12,0)} -> -3751.696
B54: Facilities | E54: =SUMIFS($K54:$BR54,$K$2:$BR$2,E$1) -> -40000 | F54: =SUMIFS($K54:$BR54,$K$2:$BR$2,F$1) -> -41200 | G54: =SUMIFS($K54:$BR54,$K$2:$BR$2,G$1) -> -42436 | H54: =SUMIFS($K54:$BR54,$K$2:$BR$2,H$1) -> -43709.08 | I54: =SUMIFS($K54:$BR54,$K$2:$BR$2,I$1) -> -45020.352 | K54: =K53 -> -3333.3333 | L54: =L53 -> -3333.3333 | M54: =M53 -> -3333.3333 | N54: =N53 -> -3333.3333 | O54: =O53 -> -3333.3333 | P54: =P53 -> -3333.3333 | Q54: =Q53 -> -3333.3333 | R54: =R53 -> -3333.3333 | ... BR54: =BR53 -> -3751.696
B56: Marketing (as % of revenue) | E56: {=INDEX(Marketing,E$1)} -> 0.05 | F56: {=INDEX(Marketing,F$1)} -> 0.04 | G56: {=INDEX(Marketing,G$1)} -> 0.02 | H56: {=INDEX(Marketing,H$1)} -> 0.02 | I56: {=INDEX(Marketing,I$1)} -> 0.02 | K56: {=INDEX(Marketing,K$2)} -> 0.05 | L56: {=INDEX(Marketing,L$2)} -> 0.05 | M56: {=INDEX(Marketing,M$2)} -> 0.05 | N56: {=INDEX(Marketing,N$2)} -> 0.05 | O56: {=INDEX(Marketing,O$2)} -> 0.05 | P56: {=INDEX(Marketing,P$2)} -> 0.05 | Q56: {=INDEX(Marketing,Q$2)} -> 0.05 | R56: {=INDEX(Marketing,R$2)} -> 0.05 | ... BR56: {=INDEX(Marketing,BR$2)} -> 0.02
B57: Marketing | E57: =SUMIFS($K57:$BR57,$K$2:$BR$2,E$1) -> -14480.136 | F57: =SUMIFS($K57:$BR57,$K$2:$BR$2,F$1) -> -20461.981 | G57: =SUMIFS($K57:$BR57,$K$2:$BR$2,G$1) -> -11871.839 | H57: =SUMIFS($K57:$BR57,$K$2:$BR$2,H$1) -> -12972.799 | I57: =SUMIFS($K57:$BR57,$K$2:$BR$2,I$1) -> -14049.535 | K57: =-K$26*K56 -> -658.7425 | L57: =-L$26*L56 -> -829.52759 | M57: =-M$26*M56 -> -914.92014 | N57: =-N$26*N56 -> -1000.3127 | O57: =-O$26*O56 -> -1085.7052 | P57: =-P$26*P56 -> -1171.0978 | Q57: =-Q$26*Q56 -> -1256.4903 | R57: =-R$26*R56 -> -1341.8829 | ... BR57: =-BR$26*BR56 -> -1214.0533
B58: =B57 -> Marketing | E58: =SUMIFS($K58:$BR58,$K$2:$BR$2,E$1) -> -14480.136 | F58: =SUMIFS($K58:$BR58,$K$2:$BR$2,F$1) -> -20461.981 | G58: =SUMIFS($K58:$BR58,$K$2:$BR$2,G$1) -> -11871.839 | H58: =SUMIFS($K58:$BR58,$K$2:$BR$2,H$1) -> -12972.799 | I58: =SUMIFS($K58:$BR58,$K$2:$BR$2,I$1) -> -14049.535 | K58: =K57 -> -658.7425 | L58: =L57 -> -829.52759 | M58: =M57 -> -914.92014 | N58: =N57 -> -1000.3127 | O58: =O57 -> -1085.7052 | P58: =P57 -> -1171.0978 | Q58: =Q57 -> -1256.4903 | R58: =R57 -> -1341.8829 | ... BR58: =BR57 -> -1214.0533
B60: Other Operating Expenses (as % of revenue) | E60: {=INDEX(Operating_Expenses,E$1)} -> 0.03 | F60: {=INDEX(Operating_Expenses,F$1)} -> 0.03 | G60: {=INDEX(Operating_Expenses,G$1)} -> 0.03 | H60: {=INDEX(Operating_Expenses,H$1)} -> 0.03 | I60: {=INDEX(Operating_Expenses,I$1)} -> 0.03 | K60: {=INDEX(Operating_Expenses,K$2)} -> 0.03 | L60: {=INDEX(Operating_Expenses,L$2)} -> 0.03 | M60: {=INDEX(Operating_Expenses,M$2)} -> 0.03 | N60: {=INDEX(Operating_Expenses,N$2)} -> 0.03 | O60: {=INDEX(Operating_Expenses,O$2)} -> 0.03 | P60: {=INDEX(Operating_Expenses,P$2)} -> 0.03 | Q60: {=INDEX(Operating_Expenses,Q$2)} -> 0.03 | R60: {=INDEX(Operating_Expenses,R$2)} -> 0.03 | ... BR60: {=INDEX(Operating_Expenses,BR$2)} -> 0.03
B61: Other Operating Expenses | E61: =SUMIFS($K61:$BR61,$K$2:$BR$2,E$1) -> -8688.0816 | F61: =SUMIFS($K61:$BR61,$K$2:$BR$2,F$1) -> -15346.486 | G61: =SUMIFS($K61:$BR61,$K$2:$BR$2,G$1) -> -17807.759 | H61: =SUMIFS($K61:$BR61,$K$2:$BR$2,H$1) -> -19459.199 | I61: =SUMIFS($K61:$BR61,$K$2:$BR$2,I$1) -> -21074.303 | K61: =-K$26*K60 -> -395.2455 | L61: =-L$26*L60 -> -497.71656 | M61: =-M$26*M60 -> -548.95208 | N61: =-N$26*N60 -> -600.18761 | O61: =-O$26*O60 -> -651.42314 | P61: =-P$26*P60 -> -702.65867 | Q61: =-Q$26*Q60 -> -753.89419 | R61: =-R$26*R60 -> -805.12972 | ... BR61: =-BR$26*BR60 -> -1821.08
B62: =B61 -> Other Operating Expenses | E62: =SUMIFS($K62:$BR62,$K$2:$BR$2,E$1) -> -8688.0816 | F62: =SUMIFS($K62:$BR62,$K$2:$BR$2,F$1) -> -15346.486 | G62: =SUMIFS($K62:$BR62,$K$2:$BR$2,G$1) -> -17807.759 | H62: =SUMIFS($K62:$BR62,$K$2:$BR$2,H$1) -> -19459.199 | I62: =SUMIFS($K62:$BR62,$K$2:$BR$2,I$1) -> -21074.303 | K62: =K61 -> -395.2455 | L62: =L61 -> -497.71656 | M62: =M61 -> -548.95208 | N62: =N61 -> -600.18761 | O62: =O61 -> -651.42314 | P62: =P61 -> -702.65867 | Q62: =Q61 -> -753.89419 | R62: =R61 -> -805.12972 | ... BR62: =BR61 -> -1821.08
B64: Other Investment Spending | E64: =SUMIFS($K64:$BR64,$K$2:$BR$2,E$1) -> -93675 | F64: =SUMIFS($K64:$BR64,$K$2:$BR$2,F$1) -> 0 | G64: =SUMIFS($K64:$BR64,$K$2:$BR$2,G$1) -> 0 | H64: =SUMIFS($K64:$BR64,$K$2:$BR$2,H$1) -> 0 | I64: =SUMIFS($K64:$BR64,$K$2:$BR$2,I$1) -> 0 | K64: {=-IFERROR(INDEX(Other_Inv_Spending,K$2)/12,0)} -> -7806.25 | L64: {=-IFERROR(INDEX(Other_Inv_Spending,L$2)/12,0)} -> -7806.25 | M64: {=-IFERROR(INDEX(Other_Inv_Spending,M$2)/12,0)} -> -7806.25 | N64: {=-IFERROR(INDEX(Other_Inv_Spending,N$2)/12,0)} -> -7806.25 | O64: {=-IFERROR(INDEX(Other_Inv_Spending,O$2)/12,0)} -> -7806.25 | P64: {=-IFERROR(INDEX(Other_Inv_Spending,P$2)/12,0)} -> -7806.25 | Q64: {=-IFERROR(INDEX(Other_Inv_Spending,Q$2)/12,0)} -> -7806.25 | R64: {=-IFERROR(INDEX(Other_Inv_Spending,R$2)/12,0)} -> -7806.25 | ... BR64: {=-IFERROR(INDEX(Other_Inv_Spending,BR$2)/12,0)} -> 0
B65: =B64 -> Other Investment Spending | E65: =SUMIFS($K65:$BR65,$K$2:$BR$2,E$1) -> -93675 | F65: =SUMIFS($K65:$BR65,$K$2:$BR$2,F$1) -> 0 | G65: =SUMIFS($K65:$BR65,$K$2:$BR$2,G$1) -> 0 | H65: =SUMIFS($K65:$BR65,$K$2:$BR$2,H$1) -> 0 | I65: =SUMIFS($K65:$BR65,$K$2:$BR$2,I$1) -> 0 | K65: =K64 -> -7806.25 | L65: =L64 -> -7806.25 | M65: =M64 -> -7806.25 | N65: =N64 -> -7806.25 | O65: =O64 -> -7806.25 | P65: =P64 -> -7806.25 | Q65: =Q64 -> -7806.25 | R65: =R64 -> -7806.25 | ... BR65: =BR64 -> 0
B67: Total Other OPEX (inc. Man & Admin Wages) | E67: =SUMIFS($K67:$BR67,$K$2:$BR$2,E$1) -> -165531.3 | F67: =SUMIFS($K67:$BR67,$K$2:$BR$2,F$1) -> -186480.06 | G67: =SUMIFS($K67:$BR67,$K$2:$BR$2,G$1) -> -199144.28 | H67: =SUMIFS($K67:$BR67,$K$2:$BR$2,H$1) -> -214950.03 | I67: =SUMIFS($K67:$BR67,$K$2:$BR$2,I$1) -> -230474.22 | K67: =K$51+K$54+K$58+K$62+K65 -> -12588.817 | L67: =L$51+L$54+L$58+L$62+L65 -> -12964.544 | M67: =M$51+M$54+M$58+M$62+M65 -> -13152.408 | N67: =N$51+N$54+N$58+N$62+N65 -> -13340.271 | O67: =O$51+O$54+O$58+O$62+O65 -> -13528.135 | P67: =P$51+P$54+P$58+P$62+P65 -> -13715.998 | Q67: =Q$51+Q$54+Q$58+Q$62+Q65 -> -13903.862 | R67: =R$51+R$54+R$58+R$62+R65 -> -14091.726 | ... BR67: =BR$51+BR$54+BR$58+BR$62+BR65 -> -19379.22
B68: Total Other OPEX (as % of revenue) | E68: =IFERROR(E67/E$26,0) -> -0.57158061 | F68: =IFERROR(F67/F$26,0) -> -0.36453961 | G68: =IFERROR(G67/G$26,0) -> -0.33549019 | H68: =IFERROR(H67/H$26,0) -> -0.33138573 | I68: =IFERROR(I67/I$26,0) -> -0.32808803 | K68: =IFERROR(K67/K$26,0) -> -0.9555188 | L68: =IFERROR(L67/L$26,0) -> -0.7814414 | M68: =IFERROR(M67/M$26,0) -> -0.71877353 | N68: =IFERROR(N67/N$26,0) -> -0.66680506 | O68: =IFERROR(O67/O$26,0) -> -0.62301141 | P68: =IFERROR(P67/P$26,0) -> -0.58560432 | Q68: =IFERROR(Q67/Q$26,0) -> -0.5532817 | R68: =IFERROR(R67/R$26,0) -> -0.52507286 | ... BR68: =IFERROR(BR67/BR$26,0) -> -0.31924825
B70: Net Operating income | E70: =SUMIFS($K70:$BR70,$K$2:$BR$2,E$1) -> -32314.048 | F70: =SUMIFS($K70:$BR70,$K$2:$BR$2,F$1) -> 48832.716 | G70: =SUMIFS($K70:$BR70,$K$2:$BR$2,G$1) -> 73908.023 | H70: =SUMIFS($K70:$BR70,$K$2:$BR$2,H$1) -> 83424.353 | I70: =SUMIFS($K70:$BR70,$K$2:$BR$2,I$1) -> 92665.093 | K70: =K$44+K$67 -> -6528.3858 | L70: =L$44+L$67 -> -5332.8902 | M70: =M$44+M$67 -> -4735.1424 | N70: =N$44+N$67 -> -4137.3945 | O70: =O$44+O$67 -> -3539.6467 | P70: =P$44+P$67 -> -2941.8989 | Q70: =Q$44+Q$67 -> -2344.1511 | R70: =R$44+R$67 -> -1746.4032 | ... BR70: =BR$44+BR$67 -> 8544.0065
B71: Net Operating Income (as % of revenue) | E71: =IFERROR(E70/E$26,0) -> -0.11158061 | F71: =IFERROR(F70/F$26,0) -> 0.095460388 | G71: =IFERROR(G70/G$26,0) -> 0.12450981 | H71: =IFERROR(H70/H$26,0) -> 0.12861427 | I71: =IFERROR(I70/I$26,0) -> 0.13191197 | K71: =IFERROR(K70/K$26,0) -> -0.4955188 | L71: =IFERROR(L70/L$26,0) -> -0.3214414 | M71: =IFERROR(M70/M$26,0) -> -0.25877353 | N71: =IFERROR(N70/N$26,0) -> -0.20680506 | O71: =IFERROR(O70/O$26,0) -> -0.16301141 | P71: =IFERROR(P70/P$26,0) -> -0.12560432 | Q71: =IFERROR(Q70/Q$26,0) -> -0.0932817 | R71: =IFERROR(R70/R$26,0) -> -0.065072864 | ... BR71: =IFERROR(BR70/BR$26,0) -> 0.14075175
B73: Depreciation & Amortization | E73: =SUMIFS($K73:$BR73,$K$2:$BR$2,E$1) -> -44456.25 | F73: =SUMIFS($K73:$BR73,$K$2:$BR$2,F$1) -> -44456.25 | G73: =SUMIFS($K73:$BR73,$K$2:$BR$2,G$1) -> -44456.25 | H73: =SUMIFS($K73:$BR73,$K$2:$BR$2,H$1) -> -44456.25 | I73: =SUMIFS($K73:$BR73,$K$2:$BR$2,I$1) -> 0 | K73: =K$241 -> -3704.6875 | L73: =L$241 -> -3704.6875 | M73: =M$241 -> -3704.6875 | N73: =N$241 -> -3704.6875 | O73: =O$241 -> -3704.6875 | P73: =P$241 -> -3704.6875 | Q73: =Q$241 -> -3704.6875 | R73: =R$241 -> -3704.6875 | ... BR73: =BR$241 -> 0
B76: Interest | E76: =SUMIFS($K76:$BR76,$K$2:$BR$2,E$1) -> -24089.625 | F76: =SUMIFS($K76:$BR76,$K$2:$BR$2,F$1) -> -21994.875 | G76: =SUMIFS($K76:$BR76,$K$2:$BR$2,G$1) -> -19900.125 | H76: =SUMIFS($K76:$BR76,$K$2:$BR$2,H$1) -> -17805.375 | I76: =SUMIFS($K76:$BR76,$K$2:$BR$2,I$1) -> -15710.625 | K76: =K196+K203+K210 -> -2087.4766 | L76: =L196+L203+L210 -> -2072.9297 | M76: =M196+M203+M210 -> -2058.3828 | N76: =N196+N203+N210 -> -2043.8359 | O76: =O196+O203+O210 -> -2029.2891 | P76: =P196+P203+P210 -> -2014.7422 | Q76: =Q196+Q203+Q210 -> -2000.1953 | R76: =R196+R203+R210 -> -1985.6484 | ... BR76: =BR196+BR203+BR210 -> -1229.2109
B78: Net Profit Before Tax | E78: =SUMIFS($K78:$BR78,$K$2:$BR$2,E$1) -> -100859.92 | F78: =SUMIFS($K78:$BR78,$K$2:$BR$2,F$1) -> -17618.409 | G78: =SUMIFS($K78:$BR78,$K$2:$BR$2,G$1) -> 9551.648 | H78: =SUMIFS($K78:$BR78,$K$2:$BR$2,H$1) -> 21162.728 | I78: =SUMIFS($K78:$BR78,$K$2:$BR$2,I$1) -> 76954.468 | K78: =K$70+K$73+K$76 -> -12320.55 | L78: =L$70+L$73+L$76 -> -11110.507 | M78: =M$70+M$73+M$76 -> -10498.213 | N78: =N$70+N$73+N$76 -> -9885.918 | O78: =O$70+O$73+O$76 -> -9273.6233 | P78: =P$70+P$73+P$76 -> -8661.3286 | Q78: =Q$70+Q$73+Q$76 -> -8049.0339 | R78: =R$70+R$73+R$76 -> -7436.7392 | ... BR78: =BR$70+BR$73+BR$76 -> 7314.7956
B79: Net PBT(as % of revenue) | E79: =IFERROR(E78/E$26,0) -> -0.34826994 | F79: =IFERROR(F78/F$26,0) -> -0.034441258 | G79: =IFERROR(G78/G$26,0) -> 0.016091269 | H79: =IFERROR(H78/H$26,0) -> 0.032626309 | I79: =IFERROR(I78/I$26,0) -> 0.10954735 | K79: =IFERROR(K78/K$26,0) -> -0.93515675 | L79: =IFERROR(L78/L$26,0) -> -0.66968884 | M79: =IFERROR(M78/M$26,0) -> -0.5737229 | N79: =IFERROR(N78/N$26,0) -> -0.49414139 | O79: =IFERROR(O78/O$26,0) -> -0.42707832 | P79: =IFERROR(P78/P$26,0) -> -0.36979528 | Q79: =IFERROR(Q78/Q$26,0) -> -0.32029828 | R79: =IFERROR(R78/R$26,0) -> -0.27710091 | ... BR79: =IFERROR(BR78/BR$26,0) -> 0.12050205
B81: Adj Net Profit Before Tax | E81: =SUMIFS($K81:$BR81,$K$2:$BR$2,E$1) -> -155859.92 | F81: =SUMIFS($K81:$BR81,$K$2:$BR$2,F$1) -> -72618.409 | G81: =SUMIFS($K81:$BR81,$K$2:$BR$2,G$1) -> -45448.352 | H81: =SUMIFS($K81:$BR81,$K$2:$BR$2,H$1) -> -33837.272 | I81: =SUMIFS($K81:$BR81,$K$2:$BR$2,I$1) -> 21954.468 | K81: =K$70+K$73+K$76-IFERROR(('Input Assumptions'!$E$38/12),0) -> -16903.883 | L81: =L$70+L$73+L$76-IFERROR(('Input Assumptions'!$E$38/12),0) -> -15693.841 | M81: =M$70+M$73+M$76-IFERROR(('Input Assumptions'!$E$38/12),0) -> -15081.546 | N81: =N$70+N$73+N$76-IFERROR(('Input Assumptions'!$E$38/12),0) -> -14469.251 | O81: =O$70+O$73+O$76-IFERROR(('Input Assumptions'!$E$38/12),0) -> -13856.957 | P81: =P$70+P$73+P$76-IFERROR(('Input Assumptions'!$E$38/12),0) -> -13244.662 | Q81: =Q$70+Q$73+Q$76-IFERROR(('Input Assumptions'!$E$38/12),0) -> -12632.367 | R81: =R$70+R$73+R$76-IFERROR(('Input Assumptions'!$E$38/12),0) -> -12020.073 | ... BR81: =BR$70+BR$73+BR$76-IFERROR(('Input Assumptions'!$E$38/12),0) -> 2731.4623
B82: Net PBT(as % of revenue) | E82: =IFERROR(E81/E$26,0) -> -0.53818528 | F82: =IFERROR(F81/F$26,0) -> -0.14195773 | G82: =IFERROR(G81/G$26,0) -> -0.076564973 | H82: =IFERROR(H81/H$26,0) -> -0.052166492 | I82: =IFERROR(I81/I$26,0) -> 0.031252946 | K82: =IFERROR(K81/K$26,0) -> -1.2830418 | L82: =IFERROR(L81/L$26,0) -> -0.94595049 | M82: =IFERROR(M81/M$26,0) -> -0.82420013 | N82: =IFERROR(N81/N$26,0) -> -0.72323642 | O82: =IFERROR(O81/O$26,0) -> -0.63815464 | P82: =IFERROR(P81/P$26,0) -> -0.56548062 | Q82: =IFERROR(Q81/Q$26,0) -> -0.50268462 | R82: =IFERROR(R81/R$26,0) -> -0.44788084 | ... BR82: =IFERROR(BR81/BR$26,0) -> 0.044997402
B84: Corporation Tax (as % of profits) | E84: =Corp_Tax -> 0.21 | F84: =Corp_Tax -> 0.21 | G84: =Corp_Tax -> 0.21 | H84: =Corp_Tax -> 0.21 | I84: =Corp_Tax -> 0.21 | K84: =Corp_Tax -> 0.21 | L84: =Corp_Tax -> 0.21 | M84: =Corp_Tax -> 0.21 | N84: =Corp_Tax -> 0.21 | O84: =Corp_Tax -> 0.21 | P84: =Corp_Tax -> 0.21 | Q84: =Corp_Tax -> 0.21 | R84: =Corp_Tax -> 0.21 | ... BR84: =Corp_Tax -> 0.21
B85: Corporation Tax | E85: =SUMIFS($K85:$BR85,$K$2:$BR$2,E$1) -> 0 | F85: =SUMIFS($K85:$BR85,$K$2:$BR$2,F$1) -> 0 | G85: =SUMIFS($K85:$BR85,$K$2:$BR$2,G$1) -> 0 | H85: =SUMIFS($K85:$BR85,$K$2:$BR$2,H$1) -> 0 | I85: =SUMIFS($K85:$BR85,$K$2:$BR$2,I$1) -> 0 | K85: =IF(SUMIFS($K81:$BR81,$K$2:$BR$2,K$2)<0,0,IF(J$152=0,(K$78)*K84,0)) -> 0 | L85: =IF(SUMIFS($K81:$BR81,$K$2:$BR$2,L$2)<0,0,IF(K$152=0,(L$78)*L84,0)) -> 0 | M85: =IF(SUMIFS($K81:$BR81,$K$2:$BR$2,M$2)<0,0,IF(L$152=0,(M$78)*M84,0)) -> 0 | N85: =IF(SUMIFS($K81:$BR81,$K$2:$BR$2,N$2)<0,0,IF(M$152=0,(N$78)*N84,0)) -> 0 | O85: =IF(SUMIFS($K81:$BR81,$K$2:$BR$2,O$2)<0,0,IF(N$152=0,(O$78)*O84,0)) -> 0 | P85: =IF(SUMIFS($K81:$BR81,$K$2:$BR$2,P$2)<0,0,IF(O$152=0,(P$78)*P84,0)) -> 0 | Q85: =IF(SUMIFS($K81:$BR81,$K$2:$BR$2,Q$2)<0,0,IF(P$152=0,(Q$78)*Q84,0)) -> 0 | R85: =IF(SUMIFS($K81:$BR81,$K$2:$BR$2,R$2)<0,0,IF(Q$152=0,(R$78)*R84,0)) -> 0 | ... BR85: =IF(SUMIFS($K81:$BR81,$K$2:$BR$2,BR$2)<0,0,IF(BQ$152=0,(BR$78)*BR84,0)) -> 0
B87: Net Profit After Tax | E87: =SUMIFS($K87:$BR87,$K$2:$BR$2,E$1) -> -100859.92 | F87: =SUMIFS($K87:$BR87,$K$2:$BR$2,F$1) -> -17618.409 | G87: =SUMIFS($K87:$BR87,$K$2:$BR$2,G$1) -> 9551.648 | H87: =SUMIFS($K87:$BR87,$K$2:$BR$2,H$1) -> 21162.728 | I87: =SUMIFS($K87:$BR87,$K$2:$BR$2,I$1) -> 76954.468 | K87: =IF(K$78<=0,K$78,K$78-K$85) -> -12320.55 | L87: =IF(L$78<=0,L$78,L$78-L$85) -> -11110.507 | M87: =IF(M$78<=0,M$78,M$78-M$85) -> -10498.213 | N87: =IF(N$78<=0,N$78,N$78-N$85) -> -9885.918 | O87: =IF(O$78<=0,O$78,O$78-O$85) -> -9273.6233 | P87: =IF(P$78<=0,P$78,P$78-P$85) -> -8661.3286 | Q87: =IF(Q$78<=0,Q$78,Q$78-Q$85) -> -8049.0339 | R87: =IF(R$78<=0,R$78,R$78-R$85) -> -7436.7392 | ... BR87: =IF(BR$78<=0,BR$78,BR$78-BR$85) -> 7314.7956
B88: Net PAT % | E88: =IFERROR(E87/E$26,0) -> -0.34826994 | F88: =IFERROR(F87/F$26,0) -> -0.034441258 | G88: =IFERROR(G87/G$26,0) -> 0.016091269 | H88: =IFERROR(H87/H$26,0) -> 0.032626309 | I88: =IFERROR(I87/I$26,0) -> 0.10954735 | K88: =IFERROR(K87/K$26,0) -> -0.93515675 | L88: =IFERROR(L87/L$26,0) -> -0.66968884 | M88: =IFERROR(M87/M$26,0) -> -0.5737229 | N88: =IFERROR(N87/N$26,0) -> -0.49414139 | O88: =IFERROR(O87/O$26,0) -> -0.42707832 | P88: =IFERROR(P87/P$26,0) -> -0.36979528 | Q88: =IFERROR(Q87/Q$26,0) -> -0.32029828 | R88: =IFERROR(R87/R$26,0) -> -0.27710091 | ... BR88: =IFERROR(BR87/BR$26,0) -> 0.12050205
B90: Balance Sheet
B92: Cash | E92: =INDEX($K92:$BR92,,MATCH(E$1,$K$2:$BR$2,0)+11) -> 12088.443 | F92: =INDEX($K92:$BR92,,MATCH(F$1,$K$2:$BR$2,0)+11) -> 6064.8014 | G92: =INDEX($K92:$BR92,,MATCH(G$1,$K$2:$BR$2,0)+11) -> 35316.959 | H92: =INDEX($K92:$BR92,,MATCH(H$1,$K$2:$BR$2,0)+11) -> 76777.854 | I92: =INDEX($K92:$BR92,,MATCH(I$1,$K$2:$BR$2,0)+11) -> 129224.97 | K92: =K$144 -> 98240.291 | L92: =L$144 -> 85290.703 | M92: =M$144 -> 75696.812 | N92: =N$144 -> 65534.673 | O92: =O$144 -> 57275.556 | P92: =P$144 -> 48983.37 | Q92: =Q$144 -> 38697.853 | R92: =R$144 -> 34235.882 | ... BR92: =BR$144 -> 129224.97
B93: Receivables | E93: =INDEX($K93:$BR93,,MATCH(E$1,$K$2:$BR$2,0)+11) -> 32582.962 | F93: =INDEX($K93:$BR93,,MATCH(F$1,$K$2:$BR$2,0)+11) -> 45337.891 | G93: =INDEX($K93:$BR93,,MATCH(G$1,$K$2:$BR$2,0)+11) -> 50085.361 | H93: =INDEX($K93:$BR93,,MATCH(H$1,$K$2:$BR$2,0)+11) -> 54242.421 | I93: =INDEX($K93:$BR93,,MATCH(I$1,$K$2:$BR$2,0)+11) -> 58744.515 | K93: =K166 -> 12749.855 | L93: =L166 -> 16590.552 | M93: =M166 -> 17708.132 | N93: =N166 -> 20006.254 | O93: =O166 -> 21013.65 | P93: =P166 -> 22666.409 | Q93: =Q166 -> 26924.793 | R93: =R166 -> 25971.927 | ... BR93: =BR166 -> 58744.515
B94: Inventory | E94: =INDEX($K94:$BR94,,MATCH(E$1,$K$2:$BR$2,0)+11) -> 21253.018 | F94: =INDEX($K94:$BR94,,MATCH(F$1,$K$2:$BR$2,0)+11) -> 29572.726 | G94: =INDEX($K94:$BR94,,MATCH(G$1,$K$2:$BR$2,0)+11) -> 32669.377 | H94: =INDEX($K94:$BR94,,MATCH(H$1,$K$2:$BR$2,0)+11) -> 35380.919 | I94: =INDEX($K94:$BR94,,MATCH(I$1,$K$2:$BR$2,0)+11) -> 38317.518 | K94: =K185 -> 8316.3985 | L94: =L185 -> 10472.502 | M94: =M185 -> 11550.553 | N94: =N185 -> 12628.605 | O94: =O185 -> 13706.657 | P94: =P185 -> 14784.708 | Q94: =Q185 -> 15862.76 | R94: =R185 -> 16940.812 | ... BR94: =BR185 -> 38317.518
B95: Current Assets | E95: =INDEX($K95:$BR95,,MATCH(E$1,$K$2:$BR$2,0)+11) -> 65924.423 | F95: =INDEX($K95:$BR95,,MATCH(F$1,$K$2:$BR$2,0)+11) -> 80975.419 | G95: =INDEX($K95:$BR95,,MATCH(G$1,$K$2:$BR$2,0)+11) -> 118071.7 | H95: =INDEX($K95:$BR95,,MATCH(H$1,$K$2:$BR$2,0)+11) -> 166401.19 | I95: =INDEX($K95:$BR95,,MATCH(I$1,$K$2:$BR$2,0)+11) -> 226287 | K95: =SUM(K92:K94) -> 119306.54 | L95: =SUM(L92:L94) -> 112353.76 | M95: =SUM(M92:M94) -> 104955.5 | N95: =SUM(N92:N94) -> 98169.532 | O95: =SUM(O92:O94) -> 91995.862 | P95: =SUM(P92:P94) -> 86434.487 | Q95: =SUM(Q92:Q94) -> 81485.406 | R95: =SUM(R92:R94) -> 77148.62 | ... BR95: =SUM(BR92:BR94) -> 226287
B97: Property and Equipment | E97: =INDEX($K97:$BR97,,MATCH(E$1,$K$2:$BR$2,0)+11) -> 133368.75 | F97: =INDEX($K97:$BR97,,MATCH(F$1,$K$2:$BR$2,0)+11) -> 88912.5 | G97: =INDEX($K97:$BR97,,MATCH(G$1,$K$2:$BR$2,0)+11) -> 44456.25 | H97: =INDEX($K97:$BR97,,MATCH(H$1,$K$2:$BR$2,0)+11) -> 0 | I97: =INDEX($K97:$BR97,,MATCH(I$1,$K$2:$BR$2,0)+11) -> 0 | K97: =K$243 -> 174120.31 | L97: =L$243 -> 170415.62 | M97: =M$243 -> 166710.94 | N97: =N$243 -> 163006.25 | O97: =O$243 -> 159301.56 | P97: =P$243 -> 155596.88 | Q97: =Q$243 -> 151892.19 | R97: =R$243 -> 148187.5 | ... BR97: =BR$243 -> 0
B98: Non Current Assets | E98: =INDEX($K98:$BR98,,MATCH(E$1,$K$2:$BR$2,0)+11) -> 133368.75 | F98: =INDEX($K98:$BR98,,MATCH(F$1,$K$2:$BR$2,0)+11) -> 88912.5 | G98: =INDEX($K98:$BR98,,MATCH(G$1,$K$2:$BR$2,0)+11) -> 44456.25 | H98: =INDEX($K98:$BR98,,MATCH(H$1,$K$2:$BR$2,0)+11) -> 0 | I98: =INDEX($K98:$BR98,,MATCH(I$1,$K$2:$BR$2,0)+11) -> 0 | K98: =SUM(K97) -> 174120.31 | L98: =SUM(L97) -> 170415.62 | M98: =SUM(M97) -> 166710.94 | N98: =SUM(N97) -> 163006.25 | O98: =SUM(O97) -> 159301.56 | P98: =SUM(P97) -> 155596.88 | Q98: =SUM(Q97) -> 151892.19 | R98: =SUM(R97) -> 148187.5 | ... BR98: =SUM(BR97) -> 0
B100: Total Assets | E100: =INDEX($K100:$BR100,,MATCH(E$1,$K$2:$BR$2,0)+11) -> 199293.17 | F100: =INDEX($K100:$BR100,,MATCH(F$1,$K$2:$BR$2,0)+11) -> 169887.92 | G100: =INDEX($K100:$BR100,,MATCH(G$1,$K$2:$BR$2,0)+11) -> 162527.95 | H100: =INDEX($K100:$BR100,,MATCH(H$1,$K$2:$BR$2,0)+11) -> 166401.19 | I100: =INDEX($K100:$BR100,,MATCH(I$1,$K$2:$BR$2,0)+11) -> 226287 | K100: =K95+K98 -> 293426.86 | L100: =L95+L98 -> 282769.38 | M100: =M95+M98 -> 271666.43 | N100: =N95+N98 -> 261175.78 | O100: =O95+O98 -> 251297.42 | P100: =P95+P98 -> 242031.36 | Q100: =Q95+Q98 -> 233377.59 | R100: =R95+R98 -> 225336.12 | ... BR100: =BR95+BR98 -> 226287
B103: Accounts Payable | E103: =INDEX($K103:$BR103,,MATCH(E$1,$K$2:$BR$2,0)+11) -> 20853.096 | F103: =INDEX($K103:$BR103,,MATCH(F$1,$K$2:$BR$2,0)+11) -> 29016.25 | G103: =INDEX($K103:$BR103,,MATCH(G$1,$K$2:$BR$2,0)+11) -> 32054.631 | H103: =INDEX($K103:$BR103,,MATCH(H$1,$K$2:$BR$2,0)+11) -> 34715.149 | I103: =INDEX($K103:$BR103,,MATCH(I$1,$K$2:$BR$2,0)+11) -> 37596.49 | K103: =K$180 -> 8159.9071 | L103: =L$180 -> 10275.439 | M103: =M$180 -> 11333.204 | N103: =N$180 -> 12390.97 | O103: =O$180 -> 13448.736 | P103: =P$180 -> 14506.502 | Q103: =Q$180 -> 15564.267 | R103: =R$180 -> 16622.033 | ... BR103: =BR$180 -> 37596.49
B104: Tax Payable | E104: =INDEX($K104:$BR104,,MATCH(E$1,$K$2:$BR$2,0)+11) -> 0 | F104: =INDEX($K104:$BR104,,MATCH(F$1,$K$2:$BR$2,0)+11) -> 0 | G104: =INDEX($K104:$BR104,,MATCH(G$1,$K$2:$BR$2,0)+11) -> 0 | H104: =INDEX($K104:$BR104,,MATCH(H$1,$K$2:$BR$2,0)+11) -> 0 | I104: =INDEX($K104:$BR104,,MATCH(I$1,$K$2:$BR$2,0)+11) -> 0 | K104: =K$159 -> 0 | L104: =L$159 -> 0 | M104: =M$159 -> 0 | N104: =N$159 -> 0 | O104: =O$159 -> 0 | P104: =P$159 -> 0 | Q104: =Q$159 -> 0 | R104: =R$159 -> 0 | ... BR104: =BR$159 -> 0
B105: Current Liabilities | E105: =INDEX($K105:$BR105,,MATCH(E$1,$K$2:$BR$2,0)+11) -> 20853.096 | F105: =INDEX($K105:$BR105,,MATCH(F$1,$K$2:$BR$2,0)+11) -> 29016.25 | G105: =INDEX($K105:$BR105,,MATCH(G$1,$K$2:$BR$2,0)+11) -> 32054.631 | H105: =INDEX($K105:$BR105,,MATCH(H$1,$K$2:$BR$2,0)+11) -> 34715.149 | I105: =INDEX($K105:$BR105,,MATCH(I$1,$K$2:$BR$2,0)+11) -> 37596.49 | K105: =SUM(K103:K104) -> 8159.9071 | L105: =SUM(L103:L104) -> 10275.439 | M105: =SUM(M103:M104) -> 11333.204 | N105: =SUM(N103:N104) -> 12390.97 | O105: =SUM(O103:O104) -> 13448.736 | P105: =SUM(P103:P104) -> 14506.502 | Q105: =SUM(Q103:Q104) -> 15564.267 | R105: =SUM(R103:R104) -> 16622.033 | ... BR105: =SUM(BR103:BR104) -> 37596.49
B107: Long-Term Liabilities | E107: =INDEX($K107:$BR107,,MATCH(E$1,$K$2:$BR$2,0)+11) -> 219450 | F107: =INDEX($K107:$BR107,,MATCH(F$1,$K$2:$BR$2,0)+11) -> 199500 | G107: =INDEX($K107:$BR107,,MATCH(G$1,$K$2:$BR$2,0)+11) -> 179550 | H107: =INDEX($K107:$BR107,,MATCH(H$1,$K$2:$BR$2,0)+11) -> 159600 | I107: =INDEX($K107:$BR107,,MATCH(I$1,$K$2:$BR$2,0)+11) -> 139650 | K107: =K$194+K201+K208 -> 237737.5 | L107: =L$194+L201+L208 -> 236075 | M107: =M$194+M201+M208 -> 234412.5 | N107: =N$194+N201+N208 -> 232750 | O107: =O$194+O201+O208 -> 231087.5 | P107: =P$194+P201+P208 -> 229425 | Q107: =Q$194+Q201+Q208 -> 227762.5 | R107: =R$194+R201+R208 -> 226100 | ... BR107: =BR$194+BR201+BR208 -> 139650
B108: Total Long-Term Liabilities | E108: =INDEX($K108:$BR108,,MATCH(E$1,$K$2:$BR$2,0)+11) -> 219450 | F108: =INDEX($K108:$BR108,,MATCH(F$1,$K$2:$BR$2,0)+11) -> 199500 | G108: =INDEX($K108:$BR108,,MATCH(G$1,$K$2:$BR$2,0)+11) -> 179550 | H108: =INDEX($K108:$BR108,,MATCH(H$1,$K$2:$BR$2,0)+11) -> 159600 | I108: =INDEX($K108:$BR108,,MATCH(I$1,$K$2:$BR$2,0)+11) -> 139650 | K108: =SUM(K107) -> 237737.5 | L108: =SUM(L107) -> 236075 | M108: =SUM(M107) -> 234412.5 | N108: =SUM(N107) -> 232750 | O108: =SUM(O107) -> 231087.5 | P108: =SUM(P107) -> 229425 | Q108: =SUM(Q107) -> 227762.5 | R108: =SUM(R107) -> 226100 | ... BR108: =SUM(BR107) -> 139650
B110: Total Liabilities | E110: =INDEX($K110:$BR110,,MATCH(E$1,$K$2:$BR$2,0)+11) -> 240303.1 | F110: =INDEX($K110:$BR110,,MATCH(F$1,$K$2:$BR$2,0)+11) -> 228516.25 | G110: =INDEX($K110:$BR110,,MATCH(G$1,$K$2:$BR$2,0)+11) -> 211604.63 | H110: =INDEX($K110:$BR110,,MATCH(H$1,$K$2:$BR$2,0)+11) -> 194315.15 | I110: =INDEX($K110:$BR110,,MATCH(I$1,$K$2:$BR$2,0)+11) -> 177246.49 | K110: =K105+K108 -> 245897.41 | L110: =L105+L108 -> 246350.44 | M110: =M105+M108 -> 245745.7 | N110: =N105+N108 -> 245140.97 | O110: =O105+O108 -> 244536.24 | P110: =P105+P108 -> 243931.5 | Q110: =Q105+Q108 -> 243326.77 | R110: =R105+R108 -> 242722.03 | ... BR110: =BR105+BR108 -> 177246.49
B112: Total Net Assets | E112: =INDEX($K112:$BR112,,MATCH(E$1,$K$2:$BR$2,0)+11) -> -41009.923 | F112: =INDEX($K112:$BR112,,MATCH(F$1,$K$2:$BR$2,0)+11) -> -58628.332 | G112: =INDEX($K112:$BR112,,MATCH(G$1,$K$2:$BR$2,0)+11) -> -49076.683 | H112: =INDEX($K112:$BR112,,MATCH(H$1,$K$2:$BR$2,0)+11) -> -27913.955 | I112: =INDEX($K112:$BR112,,MATCH(I$1,$K$2:$BR$2,0)+11) -> 49040.513 | K112: =K$100-K$105-K$108 -> 47529.45 | L112: =L$100-L$105-L$108 -> 36418.943 | M112: =M$100-M$105-M$108 -> 25920.73 | N112: =N$100-N$105-N$108 -> 16034.812 | O112: =O$100-O$105-O$108 -> 6761.1888 | P112: =P$100-P$105-P$108 -> -1900.1398 | Q112: =Q$100-Q$105-Q$108 -> -9949.1736 | R112: =R$100-R$105-R$108 -> -17385.913 | ... BR112: =BR$100-BR$105-BR$108 -> 49040.513
B114: Equity | E114: =INDEX($K114:$BR114,,MATCH(E$1,$K$2:$BR$2,0)+11) -> 59850 | F114: =INDEX($K114:$BR114,,MATCH(F$1,$K$2:$BR$2,0)+11) -> 59850 | G114: =INDEX($K114:$BR114,,MATCH(G$1,$K$2:$BR$2,0)+11) -> 59850 | H114: =INDEX($K114:$BR114,,MATCH(H$1,$K$2:$BR$2,0)+11) -> 59850 | I114: =INDEX($K114:$BR114,,MATCH(I$1,$K$2:$BR$2,0)+11) -> 59850 | K114: =SUM($K$139:K$139) -> 59850 | L114: =SUM($K$139:L$139) -> 59850 | M114: =SUM($K$139:M$139) -> 59850 | N114: =SUM($K$139:N$139) -> 59850 | O114: =SUM($K$139:O$139) -> 59850 | P114: =SUM($K$139:P$139) -> 59850 | Q114: =SUM($K$139:Q$139) -> 59850 | R114: =SUM($K$139:R$139) -> 59850 | ... BR114: =SUM($K$139:BR$139) -> 59850
B115: Retained Earnings | E115: =INDEX($K115:$BR115,,MATCH(E$1,$K$2:$BR$2,0)+11) -> -100859.92 | F115: =INDEX($K115:$BR115,,MATCH(F$1,$K$2:$BR$2,0)+11) -> -118478.33 | G115: =INDEX($K115:$BR115,,MATCH(G$1,$K$2:$BR$2,0)+11) -> -108926.68 | H115: =INDEX($K115:$BR115,,MATCH(H$1,$K$2:$BR$2,0)+11) -> -87763.955 | I115: =INDEX($K115:$BR115,,MATCH(I$1,$K$2:$BR$2,0)+11) -> -10809.487 | K115: =K123+J115+K138 -> -12320.55 | L115: =L123+K115+L138 -> -23431.057 | M115: =M123+L115+M138 -> -33929.27 | N115: =N123+M115+N138 -> -43815.188 | O115: =O123+N115+O138 -> -53088.811 | P115: =P123+O115+P138 -> -61750.14 | Q115: =Q123+P115+Q138 -> -69799.174 | R115: =R123+Q115+R138 -> -77235.913 | ... BR115: =BR123+BQ115+BR138 -> -10809.487
B116: Total Liabilities and Equity | E116: =INDEX($K116:$BR116,,MATCH(E$1,$K$2:$BR$2,0)+11) -> -41009.923 | F116: =INDEX($K116:$BR116,,MATCH(F$1,$K$2:$BR$2,0)+11) -> -58628.332 | G116: =INDEX($K116:$BR116,,MATCH(G$1,$K$2:$BR$2,0)+11) -> -49076.683 | H116: =INDEX($K116:$BR116,,MATCH(H$1,$K$2:$BR$2,0)+11) -> -27913.955 | I116: =INDEX($K116:$BR116,,MATCH(I$1,$K$2:$BR$2,0)+11) -> 49040.513 | K116: =SUM(K114:K115) -> 47529.45 | L116: =SUM(L114:L115) -> 36418.943 | M116: =SUM(M114:M115) -> 25920.73 | N116: =SUM(N114:N115) -> 16034.812 | O116: =SUM(O114:O115) -> 6761.1888 | P116: =SUM(P114:P115) -> -1900.1398 | Q116: =SUM(Q114:Q115) -> -9949.1736 | R116: =SUM(R114:R115) -> -17385.913 | ... BR116: =SUM(BR114:BR115) -> 49040.513
B117: Check | D117: =SUM(K117:BR117) -> 0 | E117: =ROUND(E112-E116,0) -> 0 | F117: =ROUND(F112-F116,0) -> 0 | G117: =ROUND(G112-G116,0) -> 0 | H117: =ROUND(H112-H116,0) -> 0 | I117: =ROUND(I112-I116,0) -> 0 | K117: =ROUND(K112-K116,0) -> 0 | L117: =ROUND(L112-L116,0) -> 0 | M117: =ROUND(M112-M116,0) -> 0 | N117: =ROUND(N112-N116,0) -> 0 | O117: =ROUND(O112-O116,0) -> 0 | P117: =ROUND(P112-P116,0) -> 0 | Q117: =ROUND(Q112-Q116,0) -> 0 | R117: =ROUND(R112-R116,0) -> 0 | ... BR117: =ROUND(BR112-BR116,0) -> 0
B119: Cash Flow
B121: Opening Cash Balance | E121: =K121 | F121: =E144 -> 12088.443 | G121: =F144 -> 6064.8014 | H121: =G144 -> 35316.959 | I121: =H144 -> 76777.854 | K121: =J144 | L121: =K144 -> 98240.291 | M121: =L144 -> 85290.703 | N121: =M144 -> 75696.812 | O121: =N144 -> 65534.673 | P121: =O144 -> 57275.556 | Q121: =P144 -> 48983.37 | R121: =Q144 -> 38697.853 | ... BR121: =BQ144 -> 122021.3
B123: Net income | E123: =SUMIF($K$2:$BR$2,E$1,$K123:$BR123) -> -100859.92 | F123: =SUMIF($K$2:$BR$2,F$1,$K123:$BR123) -> -17618.409 | G123: =SUMIF($K$2:$BR$2,G$1,$K123:$BR123) -> 9551.648 | H123: =SUMIF($K$2:$BR$2,H$1,$K123:$BR123) -> 21162.728 | I123: =SUMIF($K$2:$BR$2,I$1,$K123:$BR123) -> 76954.468 | K123: =K$87 -> -12320.55 | L123: =L$87 -> -11110.507 | M123: =M$87 -> -10498.213 | N123: =N$87 -> -9885.918 | O123: =O$87 -> -9273.6233 | P123: =P$87 -> -8661.3286 | Q123: =Q$87 -> -8049.0339 | R123: =R$87 -> -7436.7392 | ... BR123: =BR$87 -> 7314.7956
B124: Adjustments to Net Income
B125: Depreciation and Amortization | E125: =SUMIFS($K125:$BR125,$K$2:$BR$2,E$1) -> 44456.25 | F125: =SUMIFS($K125:$BR125,$K$2:$BR$2,F$1) -> 44456.25 | G125: =SUMIFS($K125:$BR125,$K$2:$BR$2,G$1) -> 44456.25 | H125: =SUMIFS($K125:$BR125,$K$2:$BR$2,H$1) -> 44456.25 | I125: =SUMIFS($K125:$BR125,$K$2:$BR$2,I$1) -> 0 | K125: =-K$73 -> 3704.6875 | L125: =-L$73 -> 3704.6875 | M125: =-M$73 -> 3704.6875 | N125: =-N$73 -> 3704.6875 | O125: =-O$73 -> 3704.6875 | P125: =-P$73 -> 3704.6875 | Q125: =-Q$73 -> 3704.6875 | R125: =-R$73 -> 3704.6875 | ... BR125: =-BR$73 -> 0
B126: Changes in Assets and Liabilities
B127: Accounts Receivable | E127: =SUMIFS($K127:$BR127,$K$2:$BR$2,E$1) -> -32582.962 | F127: =SUMIFS($K127:$BR127,$K$2:$BR$2,F$1) -> -12754.929 | G127: =SUMIFS($K127:$BR127,$K$2:$BR$2,G$1) -> -4747.4696 | H127: =SUMIFS($K127:$BR127,$K$2:$BR$2,H$1) -> -4157.0602 | I127: =SUMIFS($K127:$BR127,$K$2:$BR$2,I$1) -> -4502.0942 | K127: =-K166 -> -12749.855 | L127: =K166-L166 -> -3840.697 | M127: =L166-M166 -> -1117.5799 | N127: =M166-N166 -> -2298.122 | O127: =N166-O166 -> -1007.3959 | P127: =O166-P166 -> -1652.759 | Q127: =P166-Q166 -> -4258.3841 | R127: =Q166-R166 -> 952.86614 | S127: =R166-S166 -> -2573.5818 | ... BR127: =BQ166-BR166 -> 1556.1461
B128: Accounts Payable | E128: =SUMIFS($K128:$BR128,$K$2:$BR$2,E$1) -> 20853.096 | F128: =SUMIFS($K128:$BR128,$K$2:$BR$2,F$1) -> 8163.1544 | G128: =SUMIFS($K128:$BR128,$K$2:$BR$2,G$1) -> 3038.3806 | H128: =SUMIFS($K128:$BR128,$K$2:$BR$2,H$1) -> 2660.5185 | I128: =SUMIFS($K128:$BR128,$K$2:$BR$2,I$1) -> 2881.3403 | K128: =K180 -> 8159.9071 | L128: =L180-K180 -> 2115.5315 | M128: =M180-L180 -> 1057.7657 | N128: =N180-M180 -> 1057.7657 | O128: =O180-N180 -> 1057.7657 | P128: =P180-O180 -> 1057.7657 | Q128: =Q180-P180 -> 1057.7657 | R128: =R180-Q180 -> 1057.7657 | S128: =S180-R180 -> 1057.7657 | ... BR128: =BR180-BQ180 -> 248.98338
B129: Tax Payable | E129: =SUMIFS($K129:$BR129,$K$2:$BR$2,E$1) -> 0 | F129: =SUMIFS($K129:$BR129,$K$2:$BR$2,F$1) -> 0 | G129: =SUMIFS($K129:$BR129,$K$2:$BR$2,G$1) -> 0 | H129: =SUMIFS($K129:$BR129,$K$2:$BR$2,H$1) -> 0 | I129: =SUMIFS($K129:$BR129,$K$2:$BR$2,I$1) -> 0 | K129: =K104-J104 -> 0 | L129: =L104-K104 -> 0 | M129: =M104-L104 -> 0 | N129: =N104-M104 -> 0 | O129: =O104-N104 -> 0 | P129: =P104-O104 -> 0 | Q129: =Q104-P104 -> 0 | R129: =R104-Q104 -> 0 | ... BR129: =BR104-BQ104 -> 0
B130: Inventories | E130: =SUMIFS($K130:$BR130,$K$2:$BR$2,E$1) -> -21253.018 | F130: =SUMIFS($K130:$BR130,$K$2:$BR$2,F$1) -> -8319.708 | G130: =SUMIFS($K130:$BR130,$K$2:$BR$2,G$1) -> -3096.6509 | H130: =SUMIFS($K130:$BR130,$K$2:$BR$2,H$1) -> -2711.5422 | I130: =SUMIFS($K130:$BR130,$K$2:$BR$2,I$1) -> -2936.5989 | K130: =J185-K185 -> -8316.3985 | L130: =K185-L185 -> -2156.1033 | M130: =L185-M185 -> -1078.0517 | N130: =M185-N185 -> -1078.0517 | O130: =N185-O185 -> -1078.0517 | P130: =O185-P185 -> -1078.0517 | Q130: =P185-Q185 -> -1078.0517 | R130: =Q185-R185 -> -1078.0517 | ... BR130: =BQ185-BR185 -> -253.7584
B131: Operating Cash Assets | E131: =SUM(E$123:E$130) -> -89386.557 | F131: =SUM(F$123:F$130) -> 13926.359 | G131: =SUM(G$123:G$130) -> 49202.158 | H131: =SUM(H$123:H$130) -> 61410.894 | I131: =SUM(I$123:I$130) -> 72397.115 | K131: =SUM(K$123:K$130) -> -21522.209 | L131: =SUM(L$123:L$130) -> -11287.089 | M131: =SUM(M$123:M$130) -> -7931.391 | N131: =SUM(N$123:N$130) -> -8499.6384 | O131: =SUM(O$123:O$130) -> -6596.6176 | P131: =SUM(P$123:P$130) -> -6629.686 | Q131: =SUM(Q$123:Q$130) -> -8623.0164 | R131: =SUM(R$123:R$130) -> -2799.4715 | ... BR131: =SUM(BR$123:BR$130) -> 8866.1667
B133: Equipment / Capital Expenditure | E133: =SUMIFS($K133:$BR133,$K$2:$BR$2,E$1) -> -177825 | F133: =SUMIFS($K133:$BR133,$K$2:$BR$2,F$1) -> 0 | G133: =SUMIFS($K133:$BR133,$K$2:$BR$2,G$1) -> 0 | H133: =SUMIFS($K133:$BR133,$K$2:$BR$2,H$1) -> 0 | I133: =SUMIFS($K133:$BR133,$K$2:$BR$2,I$1) -> 0 | K133: =-K$239 -> -177825 | L133: =-L$239 -> 0 | M133: =-M$239 -> 0 | N133: =-N$239 -> 0 | O133: =-O$239 -> 0 | P133: =-P$239 -> 0 | Q133: =-Q$239 -> 0 | R133: =-R$239 -> 0 | ... BR133: =-BR$239 -> 0
B134: Investment Cash | E134: =SUM(E133) -> -177825 | F134: =SUM(F133) -> 0 | G134: =SUM(G133) -> 0 | H134: =SUM(H133) -> 0 | I134: =SUM(I133) -> 0 | K134: =SUM(K133) -> -177825 | L134: =SUM(L133) -> 0 | M134: =SUM(M133) -> 0 | N134: =SUM(N133) -> 0 | O134: =SUM(O133) -> 0 | P134: =SUM(P133) -> 0 | Q134: =SUM(Q133) -> 0 | R134: =SUM(R133) -> 0 | ... BR134: =SUM(BR133) -> 0
B136: Debt Drawdown | E136: =SUMIFS($K136:$BR136,$K$2:$BR$2,E$1) -> 239400 | F136: =SUMIFS($K136:$BR136,$K$2:$BR$2,F$1) -> 0 | G136: =SUMIFS($K136:$BR136,$K$2:$BR$2,G$1) -> 0 | H136: =SUMIFS($K136:$BR136,$K$2:$BR$2,H$1) -> 0 | I136: =SUMIFS($K136:$BR136,$K$2:$BR$2,I$1) -> 0 | K136: =K192+K199+K206 -> 239400 | L136: =L192+L199+L206 -> 0 | M136: =M192+M199+M206 -> 0 | N136: =N192+N199+N206 -> 0 | O136: =O192+O199+O206 -> 0 | P136: =P192+P199+P206 -> 0 | Q136: =Q192+Q199+Q206 -> 0 | R136: =R192+R199+R206 -> 0 | ... BR136: =BR192+BR199+BR206 -> 0
B137: Debt Repayment | E137: =SUMIFS($K137:$BR137,$K$2:$BR$2,E$1) -> -19950 | F137: =SUMIFS($K137:$BR137,$K$2:$BR$2,F$1) -> -19950 | G137: =SUMIFS($K137:$BR137,$K$2:$BR$2,G$1) -> -19950 | H137: =SUMIFS($K137:$BR137,$K$2:$BR$2,H$1) -> -19950 | I137: =SUMIFS($K137:$BR137,$K$2:$BR$2,I$1) -> -19950 | K137: =K193+K200+K207 -> -1662.5 | L137: =L193+L200+L207 -> -1662.5 | M137: =M193+M200+M207 -> -1662.5 | N137: =N193+N200+N207 -> -1662.5 | O137: =O193+O200+O207 -> -1662.5 | P137: =P193+P200+P207 -> -1662.5 | Q137: =Q193+Q200+Q207 -> -1662.5 | R137: =R193+R200+R207 -> -1662.5 | ... BR137: =BR193+BR200+BR207 -> -1662.5
B138: ='Input Assumptions'!$B$55 -> Distributions | E138: =SUMIFS($K138:$BR138,$K$2:$BR$2,E$1) -> 0 | F138: =SUMIFS($K138:$BR138,$K$2:$BR$2,F$1) -> 0 | G138: =SUMIFS($K138:$BR138,$K$2:$BR$2,G$1) -> 0 | H138: =SUMIFS($K138:$BR138,$K$2:$BR$2,H$1) -> 0 | I138: =SUMIFS($K138:$BR138,$K$2:$BR$2,I$1) -> 0 | K138: {=-IFERROR((INDEX(Distributions,K$2)/12),0)} -> 0 | L138: {=-IFERROR((INDEX(Distributions,L$2)/12),0)} -> 0 | M138: {=-IFERROR((INDEX(Distributions,M$2)/12),0)} -> 0 | N138: {=-IFERROR((INDEX(Distributions,N$2)/12),0)} -> 0 | O138: {=-IFERROR((INDEX(Distributions,O$2)/12),0)} -> 0 | P138: {=-IFERROR((INDEX(Distributions,P$2)/12),0)} -> 0 | Q138: {=-IFERROR((INDEX(Distributions,Q$2)/12),0)} -> 0 | R138: {=-IFERROR((INDEX(Distributions,R$2)/12),0)} -> 0 | ... BR138: {=-IFERROR((INDEX(Distributions,BR$2)/12),0)} -> 0
B139: Equity issuance | E139: =SUMIFS($K139:$BR139,$K$2:$BR$2,E$1) -> 59850 | F139: =SUMIFS($K139:$BR139,$K$2:$BR$2,F$1) -> 0 | G139: =SUMIFS($K139:$BR139,$K$2:$BR$2,G$1) -> 0 | H139: =SUMIFS($K139:$BR139,$K$2:$BR$2,H$1) -> 0 | I139: =SUMIFS($K139:$BR139,$K$2:$BR$2,I$1) -> 0 | K139: ='Input Assumptions'!$E$48 -> 59850 | W139: ='Input Assumptions'!$F$48 | AI139: ='Input Assumptions'!$G$48 | AU139: ='Input Assumptions'!$H$48 | BG139: ='Input Assumptions'!$I$48
B140: Financing | E140: =SUM(E136:E139) -> 279300 | F140: =SUM(F136:F139) -> -19950 | G140: =SUM(G136:G139) -> -19950 | H140: =SUM(H136:H139) -> -19950 | I140: =SUM(I136:I139) -> -19950 | K140: =SUM(K136:K139) -> 297587.5 | L140: =SUM(L136:L139) -> -1662.5 | M140: =SUM(M136:M139) -> -1662.5 | N140: =SUM(N136:N139) -> -1662.5 | O140: =SUM(O136:O139) -> -1662.5 | P140: =SUM(P136:P139) -> -1662.5 | Q140: =SUM(Q136:Q139) -> -1662.5 | R140: =SUM(R136:R139) -> -1662.5 | ... BR140: =SUM(BR136:BR139) -> -1662.5
B142: Increase / (Decrease) in Cash | E142: =SUMIFS($K142:$BR142,$K$2:$BR$2,E$1) -> 12088.443 | F142: =SUMIFS($K142:$BR142,$K$2:$BR$2,F$1) -> -6023.6413 | G142: =SUMIFS($K142:$BR142,$K$2:$BR$2,G$1) -> 29252.158 | H142: =SUMIFS($K142:$BR142,$K$2:$BR$2,H$1) -> 41460.894 | I142: =SUMIFS($K142:$BR142,$K$2:$BR$2,I$1) -> 52447.115 | K142: =K$131+K$134+K$140 -> 98240.291 | L142: =L$131+L$134+L$140 -> -12949.589 | M142: =M$131+M$134+M$140 -> -9593.891 | N142: =N$131+N$134+N$140 -> -10162.138 | O142: =O$131+O$134+O$140 -> -8259.1176 | P142: =P$131+P$134+P$140 -> -8292.186 | Q142: =Q$131+Q$134+Q$140 -> -10285.516 | R142: =R$131+R$134+R$140 -> -4461.9715 | ... BR142: =BR$131+BR$134+BR$140 -> 7203.6667
...

Sheet Audit
B1: Audit Sheet
B4: Model Name | D4: Franchise Template | F4: Tech Support
B5: Model Version | F5: Contact Details | H5: support@vettedbiz.com
B7: Summary Sheet Error Checks | F7: Summary Custom Checks
B9: =IF(COUNTIF(B$13:B$1048576,FALSE)<>0,FALSE,TRUE) -> TRUE | D9: Sheets | F9: =IF(COUNTIF(F$13:F$1048576,FALSE)<>0,FALSE,TRUE) -> TRUE
B11: Sheet Error Checks | F11: Model Sheet Checks
D12: Click on Hyperlink to Navigate to Sheet
B13: =IF(ISERROR(SUM('Input Assumptions'!$1:$1048576)),FALSE,TRUE) -> TRUE | D13: Inputs | F13: =IF((BS_Check)=0,TRUE,FALSE) -> TRUE | H13: =$J13&" Imbalance Check I" -> Balance Sheet Imbalance Check I | J13: Balance Sheet
B14: =IF(ISERROR(SUM('Summary Financials'!$1:$1048576)),FALSE,TRUE) -> TRUE | D14: Summary Financials | F14: =IF(('Balance Sheet'!$49:$49)=0,TRUE,FALSE) -> TRUE | H14: =$J14&" Imbalance Check II" -> Balance Sheet Imbalance Check II | J14: Balance Sheet
B15: =IF(ISERROR(SUM('P&L Statement'!$1:$1048576)),FALSE,TRUE) -> TRUE | D15: P&L Statement | F15: =IF(ISERROR(SUM(Model!$9:$90)),FALSE,TRUE) -> TRUE | H15: =$J15&" Check" -> Profit & Loss Check | J15: Profit & Loss
B16: =IF(ISERROR(SUM('Balance Sheet'!$1:$1048576)),FALSE,TRUE) -> TRUE | D16: Balance Sheet | F16: =IF(ISERROR(SUM(Model!$90:$119)),FALSE,TRUE) -> TRUE | H16: =$J16&" Check" -> Balance Sheet Check | J16: Balance Sheet
B17: =IF(ISERROR(SUM('Cash Flow Statement'!$1:$1048576)),FALSE,TRUE) -> TRUE | D17: Cash Flow Statement | F17: =IF(ISERROR(SUM(Model!$119:$146)),FALSE,TRUE) -> TRUE | H17: =$J17&" Check I" -> Cash Flow Check I | J17: Cash Flow
B18: =IF(ISERROR(SUM('Returns on Invested Capital'!$1:$1048576)),FALSE,TRUE) -> TRUE | D18: Returns on Invested Capital | F18: =IF(ISERROR(SUM('Cash Flow Statement'!$39:$39)),FALSE,TRUE) -> TRUE | H18: =$J18&" Check II" -> Cash Flow Check II | J18: Cash Flow
B19: =IF(ISERROR(SUM(Valuation!$1:$1048576)),FALSE,TRUE) -> TRUE | D19: Valuation | F19: =IF(ISERROR(SUM(Model!$146:$161)),FALSE,TRUE) -> TRUE | H19: =$J19&" Check" -> Corporation Tax Check | J19: Corporation Tax
B20: =IF(ISERROR(SUM(Model!$1:$1048576)),FALSE,TRUE) -> TRUE | D20: Model | F20: =IF(ISERROR(SUM(Model!$161:$189)),FALSE,TRUE) -> TRUE | H20: =$J20&" Check" -> Working Capital Check | J20: Working Capital
F21: =IF(ISERROR(SUM(Model!$189:$212)),FALSE,TRUE) -> TRUE | H21: =$J21&" Check" -> Debt Check | J21: Debt
F22: =IF(ISERROR(SUM(Model!$212:$245)),FALSE,TRUE) -> TRUE | H22: =$J22&" Check" -> Capex Check | J22: Capex
F23: =IF(ISERROR(SUM(Model!$245:$282)),FALSE,TRUE) -> TRUE | H23: =$J23&" Check" -> Breakeven Check | J23: Breakeven
F24: =IF(ISERROR(SUM(Model!$282:$304)),FALSE,TRUE) -> TRUE | H24: =$J24&" Check" -> ROI Check | J24: ROI
F25: =IF(ISERROR(SUM(Model!$304:$321)),FALSE,TRUE) -> TRUE | H25: =$J25&" Check" -> Valuation Check | J25: Valuation

Sheet Feedback & Support
B2: Feedback & Support
B4: Thank you for choosing our Financial Projections model to support your franchise analysis efforts! Your insights and experiences are vital to us, and we constantly strive to refine our tools to better serve your needs.
B6: Feedback:
B8: We value your opinions! Please share any feedback, suggestions, or experiences you've had with this model. Whether there's a feature you love, something you believe can be improved, or additional functionalities you'd like to see, we want to hear from you. Email support@vettedbiz.com to provide your feedback.
B10: Support:
B12: If you encounter any challenges or have questions about the model, our dedicated support team is here to help. Reach out to us at support@vettedbiz.com or visit for https://www.vettedbiz.com/ FAQs and helpful resources.
B14: Remember, your feedback helps us create a better tool for you and everyone else on the franchise journey. Thank you for being an essential part of our community!
B16: Warm regards,
B17: Vetted Biz Team
